Workbook

Sheet FACTSHEET
A1: FACTSHEET - GLOBAL ESG-BASED PORTFOLIO PERFORMANCE AMONG MAJOR FRENCH COMPANIES (2020–2024)
A3: Region | B3: Western Europe | C3: Ecology is important, but social and governance factors also play a crucial role. It makes little sense to promote environmental progress while degrading workers’ labour conditions, and several studies have shown that having more women on boards leads to better decision-making. Therefore, after careful reflection, we decided to focus on the overall ESG score, which combines environmental, social, and governance dimensions, rather than considering only the environmental aspect of the assets. We combined this ESG approach with a territorial criterion to support French companies with higher market capitalizations, using the CAC 40 as the parent index for comparison. Consequently, we selected the 29 largest companies by market capitalization and built portfolios strictly according to their ESG scores in order to study their returns and dynamics over the period from January 1, 2020, to January 1, 2024. Given the restricted sample size and the fact that ESG performance was our sole selection criterion, the resulting portfolios are somewhat unbalanced and highly dependent on the movements of certain assets. Nevertheless, it remains interesting to analyze their performance in relation to the sustainability of the companies.
A4: Country | B4: France
A5: Parent Index | B5: CAC 40
A6: #Constituents | B6: 29
A7: Start Date | B7: 43831
A8: End Date | B8: 45292
A9: Screening | B9: GLOBAL ESG
A10: Frequency | B10: Daily
A11: Currency | B11: EUR
A13: PORTFOLIO'S COMPOSITION
H15: AVERAGE DAILY RETURN AND RISK OF OUR 4 PORTFOLIOS AND PARENTING INDEX
A16: PORTFOLIO | B16: COMPANY | C16: MARKET CAP | D16: SECTOR | F16: ESG
I17: 2020 | K17: 2021 | M17: 2022 | O17: 2023
A18: PTF 10% | B18: Schneider Electric S.E. | C18: 122.95 | D18: Specialty Industrial Machinery | F18: =VLOOKUP(B18,Table3[[COMPANY NAME]:[GLOBAL ESG]],14,0) -> 9.4 | I18: RETURN | J18: RISK | K18: RETURN | L18: RISK | M18: RETURN | N18: RISK | O18: RETURN | P18: RISK | Q18: SHARPE
B19: Kering SA | C19: 29.1 | D19: Luxury Goods | F19: =VLOOKUP(B19,Table3[[COMPANY NAME]:[GLOBAL ESG]],14,0) -> 10.7 | H19: AVG PTF 10% | I19: 0.00041374898 | J19: 0.023547358 | K19: 0.0011761945 | L19: 0.014092721 | M19: -0.001159725 | N19: 0.019574992 | O19: 6.9683905e-05 | P19: 0.013976509 | Q19: -0.073496684
B20: Capgemini SE | C20: 21.24 | D20: Information Technology Services | F20: =VLOOKUP(B20,Table3[[COMPANY NAME]:[GLOBAL ESG]],14,0) -> 7.6 | H20: AVG PTF 20% | I20: 0.00077324801 | J20: 0.019673415 | K20: 0.0017493279 | L20: 0.013069733 | M20: -0.00044462558 | N20: 0.020223077 | O20: 0.00080645849 | P20: 0.013868085 | Q20: 0.54972047
H21: AVG PTF 50% | I21: 0.00061846363 | J21: 0.019125869 | K21: 0.0015892455 | L21: 0.012013791 | M21: -0.00036148371 | N21: 0.018827885 | O21: 0.00068572294 | P21: 0.012963744 | Q21: 0.49889449
A22: PTF 20% | B22: Hermès International Société en commandite par actions | C22: 213.76 | D22: Luxury Goods | F22: =VLOOKUP(B22,Table3[[COMPANY NAME]:[GLOBAL ESG]],14,0) -> 12.7 | H22: AVG PTF 100% | I22: 0.00036325297 | J22: 0.019728774 | K22: 0.0013431895 | L22: 0.011267582 | M22: -0.00028248958 | N22: 0.017226774 | O22: 0.00062251281 | P22: 0.011719348 | Q22: 0.38903477
B23: Schneider Electric S.E. | C23: 122.95 | D23: Specialty Industrial Machinery | F23: =VLOOKUP(B23,Table3[[COMPANY NAME]:[GLOBAL ESG]],14,0) -> 9.4 | H23: CAC40 | I23: -9.0463382e-05 | J23: 0.020196029 | K23: 0.0010372077 | L23: 0.0092290634 | M23: -0.00029089428 | N23: 0.01370195 | O23: 0.00060548674 | P23: 0.0085918956
B24: Dassault Systèmes SE | C24: 35.37 | D24: Software - Application | F24: =VLOOKUP(B24,Table3[[COMPANY NAME]:[GLOBAL ESG]],14,0) -> 12.8
B25: Kering SA | C25: 29.1 | D25: Luxury Goods | F25: =VLOOKUP(B25,Table3[[COMPANY NAME]:[GLOBAL ESG]],14,0) -> 10.7
B26: Compagnie Générale des Établissements Michelin Société en commandite par actions | C26: 21.79 | D26: Automobiles & Auto Parts | F26: =VLOOKUP(B26,Table3[[COMPANY NAME]:[GLOBAL ESG]],14,0) -> 11.5
B27: Capgemini SE | C27: 21.24 | D27: Information Technology Services | F27: =VLOOKUP(B27,Table3[[COMPANY NAME]:[GLOBAL ESG]],14,0) -> 7.6
A30: PTF 50% | B30: LVMH Moët Hennessy - Louis Vuitton, Société Européenne | C30: 246.65 | D30: Luxury Goods | F30: =VLOOKUP(B30,Table3[[COMPANY NAME]:[GLOBAL ESG]],14,0) -> 13.8
B31: Hermès International Société en commandite par actions | C31: 213.76 | D31: Luxury Goods | F31: =VLOOKUP(B31,Table3[[COMPANY NAME]:[GLOBAL ESG]],14,0) -> 12.7
B32: Schneider Electric S.E. | C32: 122.95 | D32: Specialty Industrial Machinery | F32: =VLOOKUP(B32,Table3[[COMPANY NAME]:[GLOBAL ESG]],14,0) -> 9.4
B33: EssilorLuxottica Société anonyme | C33: 119.71 | D33: Medical Instruments & Supplies | F33: =VLOOKUP(B33,Table3[[COMPANY NAME]:[GLOBAL ESG]],14,0) -> 16.7
B34: L'Air Liquide S.A. | C34: 101.14 | D34: Specialty Chemicals | F34: =VLOOKUP(B34,Table3[[COMPANY NAME]:[GLOBAL ESG]],14,0) -> 13.8
B35: BNP Paribas SA | C35: 85.54 | D35: Banks - Regional | F35: =VLOOKUP(B35,Table3[[COMPANY NAME]:[GLOBAL ESG]],14,0) -> 17.2
B36: AXA SA | C36: 82.42 | D36: Insurance - Diversified | F36: =VLOOKUP(B36,Table3[[COMPANY NAME]:[GLOBAL ESG]],14,0) -> 16.3
B37: Danone S.A. | C37: 48.5 | D37: Packaged Foods | F37: =VLOOKUP(B37,Table3[[COMPANY NAME]:[GLOBAL ESG]],14,0) -> 17.6
B38: Société Générale Société anonyme | C38: 41.13 | D38: Banks - Regional | F38: =VLOOKUP(B38,Table3[[COMPANY NAME]:[GLOBAL ESG]],14,0) -> 15.4
B39: Dassault Systèmes SE | C39: 35.37 | D39: Software - Application | F39: =VLOOKUP(B39,Table3[[COMPANY NAME]:[GLOBAL ESG]],14,0) -> 12.8
B40: Legrand SA | C40: 34.36 | D40: Electrical Equipment & Parts | F40: =VLOOKUP(B40,Table3[[COMPANY NAME]:[GLOBAL ESG]],14,0) -> 15 | H40: MATRICE CORRELATION RETURN PTF | O40: BETA ANALYSIS
B41: Kering SA | C41: 29.1 | D41: Luxury Goods | F41: =VLOOKUP(B41,Table3[[COMPANY NAME]:[GLOBAL ESG]],14,0) -> 10.7
B42: Compagnie Générale des Établissements Michelin Société en commandite par actions | C42: 21.79 | D42: Automobiles & Auto Parts | F42: =VLOOKUP(B42,Table3[[COMPANY NAME]:[GLOBAL ESG]],14,0) -> 11.5 | I42: AVG PTF 10% | J42: AVG PTF 20% | K42: AVG PTF 50% | L42: AVG PTF 100% | M42: CAC40 | P42: 2020 | Q42: 2021 | R42: 2022 | S42: 2023 | T42: 4 years
B43: Capgemini SE | C43: 21.24 | D43: Information Technology Services | F43: =VLOOKUP(B43,Table3[[COMPANY NAME]:[GLOBAL ESG]],14,0) -> 7.6 | H43: AVG PTF 10% | I43: 1 | O43: PTF 10% | P43: 0.88657356 | Q43: 0.99119506 | R43: 0.95083379 | S43: 0.98441281 | T43: 0.92437413
H44: AVG PTF 20% | I44: 0.74913146 | J44: 1 | O44: PTF 20% | P44: 0.71526424 | Q44: 0.8544547 | R44: 0.90603183 | S44: 0.94530633 | T44: 0.80152073
H45: AVG PTF 50% | I45: 0.86311815 | J45: 0.80542131 | K45: 1 | O45: PTF 50% | P45: 0.73059643 | Q45: 0.85597723 | R45: 0.88756968 | S45: 0.9278718 | T45: 0.8035161
A46: PTF 100% | B46: LVMH Moët Hennessy - Louis Vuitton, Société Européenne | C46: 246.65 | D46: Luxury Goods | F46: =VLOOKUP(B46,Table3[[COMPANY NAME]:[GLOBAL ESG]],14,0) -> 13.8 | H46: AVG PTF 100% | I46: 0.84369373 | J46: 0.74820415 | K46: 0.92464751 | L46: 1 | O46: PTF 100% | P46: 0.77916166 | Q46: 0.84584431 | R46: 0.84060331 | S46: 0.86713662 | T46: 0.81086794
B47: L'Oréal S.A. | C47: 214.69 | D47: Household & Personal Products | F47: =VLOOKUP(B47,Table3[[COMPANY NAME]:[GLOBAL ESG]],14,0) -> 18.4 | H47: CAC40 | I47: 0.69579364 | J47: 0.53845445 | K47: 0.71870142 | L47: 0.74214171 | M47: 1
B48: Hermès International Société en commandite par actions | C48: 213.76 | D48: Luxury Goods | F48: =VLOOKUP(B48,Table3[[COMPANY NAME]:[GLOBAL ESG]],14,0) -> 12.7
B49: Airbus SE | C49: 145.47 | D49: Aerospace & Defense | F49: =VLOOKUP(B49,Table3[[COMPANY NAME]:[GLOBAL ESG]],14,0) -> 24.1
B50: Schneider Electric S.E. | C50: 122.95 | D50: Specialty Industrial Machinery | F50: =VLOOKUP(B50,Table3[[COMPANY NAME]:[GLOBAL ESG]],14,0) -> 9.4
B51: EssilorLuxottica Société anonyme | C51: 119.71 | D51: Medical Instruments & Supplies | F51: =VLOOKUP(B51,Table3[[COMPANY NAME]:[GLOBAL ESG]],14,0) -> 16.7
B52: Safran SA | C52: 116.56 | D52: Aerospace & Defense | F52: =VLOOKUP(B52,Table3[[COMPANY NAME]:[GLOBAL ESG]],14,0) -> 28.7
B53: TotalEnergies SE | C53: 113.08 | D53: Oil & Gas Integrated | F53: =VLOOKUP(B53,Table3[[COMPANY NAME]:[GLOBAL ESG]],14,0) -> 31.7
B54: L'Air Liquide S.A. | C54: 101.14 | D54: Specialty Chemicals | F54: =VLOOKUP(B54,Table3[[COMPANY NAME]:[GLOBAL ESG]],14,0) -> 13.8
B55: Sanofi | C55: 96.95 | D55: Drug Manufacturers - General | F55: =VLOOKUP(B55,Table3[[COMPANY NAME]:[GLOBAL ESG]],14,0) -> 19
B56: BNP Paribas SA | C56: 85.54 | D56: Banks - Regional | F56: =VLOOKUP(B56,Table3[[COMPANY NAME]:[GLOBAL ESG]],14,0) -> 17.2
B57: Christian Dior SE | C57: 85.15 | D57: Luxury Goods | F57: =VLOOKUP(B57,Table3[[COMPANY NAME]:[GLOBAL ESG]],14,0) -> 23.7
B58: AXA SA | C58: 82.42 | D58: Insurance - Diversified | F58: =VLOOKUP(B58,Table3[[COMPANY NAME]:[GLOBAL ESG]],14,0) -> 16.3
B59: Vinci SA | C59: 62.45 | D59: Engineering & Construction | F59: =VLOOKUP(B59,Table3[[COMPANY NAME]:[GLOBAL ESG]],14,0) -> 25.4
... B73: Capgemini SE | C73: 21.24 | D73: Information Technology Services | F73: =VLOOKUP(B73,Table3[[COMPANY NAME]:[GLOBAL ESG]],14,0) -> 7.6
I99: RETURN RISK PER YEAR PER PORTFOLIO
I100: RATIO DE SHARPE
I101: MATRICE DE CORRELATION
I102: BETA
I103: ALPHA
I104: RESISTANCE AU CHOC
I106: GRAPH | J106: VALORISATION RISK
I108: FIRM LOOK UP

Sheet CALCULATION on ptf's return
A1: RETURN OF THE AVG CAP PER TRESHHOLD
A2: year | B2: AVG PTF 10% | C2: AVG PTF 20% | D2: AVG PTF 50% | E2: AVG PTF 100% | F2: CAC40
A3: 2020 | B3: ='CALCULATION of avg returns'!AO3 -> 0.0034409246 | C3: ='CALCULATION of avg returns'!AP3 -> 0.0047264787 | D3: ='CALCULATION of avg returns'!AQ3 -> 0.0024300989 | E3: ='CALCULATION of avg returns'!AR3 -> 0.0022529756 | F3: ='CALCULATION of avg returns'!AS3 -> -0.0027648344 | I3: nb
A4: 2020 | B4: ='CALCULATION of avg returns'!AO4 -> -0.014996211 | C4: ='CALCULATION of avg returns'!AP4 -> -0.011627226 | D4: ='CALCULATION of avg returns'!AQ4 -> -0.0095501567 | E4: ='CALCULATION of avg returns'!AR4 -> -0.0068546499 | F4: ='CALCULATION of avg returns'!AS4 -> -0.0065625839 | H4: 2020 | I4: =COUNTIF(A3:A1028,H4) -> 257 | N4: MATRICE CORRELATION RETURN PTF
A5: 2020 | B5: ='CALCULATION of avg returns'!AO5 -> 0.0065211907 | C5: ='CALCULATION of avg returns'!AP5 -> 0.0091373499 | D5: ='CALCULATION of avg returns'!AQ5 -> 0.006026401 | E5: ='CALCULATION of avg returns'!AR5 -> 0.0022882443 | F5: ='CALCULATION of avg returns'!AS5 -> 0.0075143781 | H5: 2021 | I5: =COUNTIF(A4:A1029,H5) -> 258
A6: 2020 | B6: ='CALCULATION of avg returns'!AO6 -> 0.0011779891 | C6: ='CALCULATION of avg returns'!AP6 -> 0.0051209456 | D6: ='CALCULATION of avg returns'!AQ6 -> 0.0046573057 | E6: ='CALCULATION of avg returns'!AR6 -> 0.0049696546 | F6: ='CALCULATION of avg returns'!AS6 -> -0.0045383333 | H6: 2022 | I6: =COUNTIF(A5:A1030,H6) -> 257 | O6: AVG PTF 10% | P6: AVG PTF 20% | Q6: AVG PTF 50% | R6: AVG PTF 100% | S6: CAC40
A7: 2020 | B7: ='CALCULATION of avg returns'!AO7 -> -0.0027036838 | C7: ='CALCULATION of avg returns'!AP7 -> 0.00075287032 | D7: ='CALCULATION of avg returns'!AQ7 -> 0.0037647384 | E7: ='CALCULATION of avg returns'!AR7 -> 0.0036687709 | F7: ='CALCULATION of avg returns'!AS7 -> 0.010276639 | H7: 2023 | I7: =COUNTIF(A6:A1031,H7) -> 254 | N7: AVG PTF 10% | O7: 1
A8: 2020 | B8: ='CALCULATION of avg returns'!AO8 -> -0.0028365234 | C8: ='CALCULATION of avg returns'!AP8 -> 6.4853787e-05 | D8: ='CALCULATION of avg returns'!AQ8 -> -0.00066091977 | E8: ='CALCULATION of avg returns'!AR8 -> -0.0006751001 | F8: ='CALCULATION of avg returns'!AS8 -> -0.00097113927 | G8: AVG daily RETURN(%) | I8: PTF 10% | J8: PTF 20% | K8: PTF 50% | L8: PTF 100% | M8: CAC40 | N8: AVG PTF 20% | O8: 0.74913146 | P8: 1
A9: 2020 | B9: ='CALCULATION of avg returns'!AO9 -> 0.0038641141 | C9: ='CALCULATION of avg returns'!AP9 -> 0.0024188894 | D9: ='CALCULATION of avg returns'!AQ9 -> 0.0016351339 | E9: ='CALCULATION of avg returns'!AR9 -> 0.0021838888 | F9: ='CALCULATION of avg returns'!AS9 -> -0.0016522098 | H9: 2020 | I9: =AVERAGEIF($A$3:$A$1028,$H9,B$3:B$1028) -> 0.00041374898 | J9: =AVERAGEIF($A$3:$A$1028,$H9,C$3:C$1028) -> 0.00077324801 | K9: =AVERAGEIF($A$3:$A$1028,$H9,D$3:D$1028) -> 0.00061846363 | L9: =AVERAGEIF($A$3:$A$1028,$H9,E$3:E$1028) -> 0.00036325297 | M9: =AVERAGEIF($A$3:$A$1028,$H9,F$3:F$1028) -> -9.0463382e-05 | N9: AVG PTF 50% | O9: 0.86311815 | P9: 0.80542131 | Q9: 1
A10: 2020 | B10: ='CALCULATION of avg returns'!AO10 -> 0.0017678921 | C10: ='CALCULATION of avg returns'!AP10 -> 0.0073361971 | D10: ='CALCULATION of avg returns'!AQ10 -> 0.006793159 | E10: ='CALCULATION of avg returns'!AR10 -> 0.0061206831 | F10: ='CALCULATION of avg returns'!AS10 -> -0.0063605685 | H10: 2021 | I10: =AVERAGEIF($A$3:$A$1028,$H10,B$3:B$1028) -> 0.0011761945 | J10: =AVERAGEIF($A$3:$A$1028,$H10,C$3:C$1028) -> 0.0017493279 | K10: =AVERAGEIF($A$3:$A$1028,$H10,D$3:D$1028) -> 0.0015892455 | L10: =AVERAGEIF($A$3:$A$1028,$H10,E$3:E$1028) -> 0.0013431895 | M10: =AVERAGEIF($A$3:$A$1028,$H10,F$3:F$1028) -> 0.0010372077 | N10: AVG PTF 100% | O10: 0.84369373 | P10: 0.74820415 | Q10: 0.92464751 | R10: 1
A11: 2020 | B11: ='CALCULATION of avg returns'!AO11 -> 0.0035921249 | C11: ='CALCULATION of avg returns'!AP11 -> 0.0074690129 | D11: ='CALCULATION of avg returns'!AQ11 -> 0.0051218501 | E11: ='CALCULATION of avg returns'!AR11 -> 0.0050870004 | F11: ='CALCULATION of avg returns'!AS11 -> 0.0052223644 | H11: 2022 | I11: =AVERAGEIF($A$3:$A$1028,$H11,B$3:B$1028) -> -0.001159725 | J11: =AVERAGEIF($A$3:$A$1028,$H11,C$3:C$1028) -> -0.00044462558 | K11: =AVERAGEIF($A$3:$A$1028,$H11,D$3:D$1028) -> -0.00036148371 | L11: =AVERAGEIF($A$3:$A$1028,$H11,E$3:E$1028) -> -0.00028248958 | M11: =AVERAGEIF($A$3:$A$1028,$H11,F$3:F$1028) -> -0.00029089428 | N11: CAC40 | O11: 0.69579364 | P11: 0.53845445 | Q11: 0.71870142 | R11: 0.74214171 | S11: 1
A12: 2020 | B12: ='CALCULATION of avg returns'!AO12 -> 0.013319365 | C12: ='CALCULATION of avg returns'!AP12 -> 0.0087905503 | D12: ='CALCULATION of avg returns'!AQ12 -> 0.0059603868 | E12: ='CALCULATION of avg returns'!AR12 -> 0.004081969 | F12: ='CALCULATION of avg returns'!AS12 -> 0.0016219507 | H12: 2023 | I12: =AVERAGEIF($A$3:$A$1028,$H12,B$3:B$1028) -> 6.9683905e-05 | J12: =AVERAGEIF($A$3:$A$1028,$H12,C$3:C$1028) -> 0.00080645849 | K12: =AVERAGEIF($A$3:$A$1028,$H12,D$3:D$1028) -> 0.00068572294 | L12: =AVERAGEIF($A$3:$A$1028,$H12,E$3:E$1028) -> 0.00062251281 | M12: =AVERAGEIF($A$3:$A$1028,$H12,F$3:F$1028) -> 0.00060548674
A13: 2020 | B13: ='CALCULATION of avg returns'!AO13 -> 0.010215133 | C13: ='CALCULATION of avg returns'!AP13 -> 0.01447691 | D13: ='CALCULATION of avg returns'!AQ13 -> 0.014464495 | E13: ='CALCULATION of avg returns'!AR13 -> 0.014491949 | F13: ='CALCULATION of avg returns'!AS13 -> 0.0075169863 | H13: 4 | I13: =AVERAGE(B3:B1028) -> 0.00012616186 | J13: =AVERAGE(C3:C1028) -> 0.0007218548 | K13: =AVERAGE(D3:D1028) -> 0.00063376492 | L13: =AVERAGE(E3:E1028) -> 0.00051210266 | M13: =AVERAGE(F3:F1028) -> 0.00031518937 | Q13: PTF 10% | R13: PTF 20% | S13: PTF 50% | T13: PTF 100%
A14: 2020 | B14: ='CALCULATION of avg returns'!AO14 -> -0.013206306 | C14: ='CALCULATION of avg returns'!AP14 -> -0.011828607 | D14: ='CALCULATION of avg returns'!AQ14 -> -0.012465678 | E14: ='CALCULATION of avg returns'!AR14 -> -0.0094590382 | F14: ='CALCULATION of avg returns'!AS14 -> 0.00080444555 | O14: SUM OF RETURN | P14: 2020 | Q14: =SUMIF($A$3:$A$1028,$P14,B$3:B$1028) -> 0.10633349 | R14: =SUMIF($A$3:$A$1028,$P14,C$3:C$1028) -> 0.19872474 | S14: =SUMIF($A$3:$A$1028,$P14,D$3:D$1028) -> 0.15894515 | T14: =SUMIF($A$3:$A$1028,$P14,E$3:E$1028) -> 0.093356015
A15: 2020 | B15: ='CALCULATION of avg returns'!AO15 -> -0.015099138 | C15: ='CALCULATION of avg returns'!AP15 -> -0.012606843 | D15: ='CALCULATION of avg returns'!AQ15 -> -0.010136558 | E15: ='CALCULATION of avg returns'!AR15 -> -0.010591989 | F15: ='CALCULATION of avg returns'!AS15 -> -0.012682893 | P15: 2021 | Q15: =SUMIF($A$3:$A$1028,$P15,B$3:B$1028) -> 0.30345819 | R15: =SUMIF($A$3:$A$1028,$P15,C$3:C$1028) -> 0.4513266 | S15: =SUMIF($A$3:$A$1028,$P15,D$3:D$1028) -> 0.41002534 | T15: =SUMIF($A$3:$A$1028,$P15,E$3:E$1028) -> 0.34654289
A16: 2020 | B16: ='CALCULATION of avg returns'!AO16 -> 0.006430586 | C16: ='CALCULATION of avg returns'!AP16 -> 0.0045325707 | D16: ='CALCULATION of avg returns'!AQ16 -> 0.00071425705 | E16: ='CALCULATION of avg returns'!AR16 -> -0.0019885929 | F16: ='CALCULATION of avg returns'!AS16 -> 0.0019352137 | P16: 2022 | Q16: =SUMIF($A$3:$A$1028,$P16,B$3:B$1028) -> -0.29804932 | R16: =SUMIF($A$3:$A$1028,$P16,C$3:C$1028) -> -0.11426878 | S16: =SUMIF($A$3:$A$1028,$P16,D$3:D$1028) -> -0.092901314 | T16: =SUMIF($A$3:$A$1028,$P16,E$3:E$1028) -> -0.072599823
A17: 2020 | B17: ='CALCULATION of avg returns'!AO17 -> -0.023054504 | C17: ='CALCULATION of avg returns'!AP17 -> -0.016561384 | D17: ='CALCULATION of avg returns'!AQ17 -> -0.015822734 | E17: ='CALCULATION of avg returns'!AR17 -> -0.01352456 | F17: ='CALCULATION of avg returns'!AS17 -> -0.0073096372 | P17: 2023 | Q17: =SUMIF($A$3:$A$1028,$P17,B$3:B$1028) -> 0.017699712 | R17: =SUMIF($A$3:$A$1028,$P17,C$3:C$1028) -> 0.20484046 | S17: =SUMIF($A$3:$A$1028,$P17,D$3:D$1028) -> 0.17417363 | T17: =SUMIF($A$3:$A$1028,$P17,E$3:E$1028) -> 0.15811825
A18: 2020 | B18: ='CALCULATION of avg returns'!AO18 -> 0.0028047988 | C18: ='CALCULATION of avg returns'!AP18 -> 0.0061777858 | D18: ='CALCULATION of avg returns'!AQ18 -> 0.0072359254 | E18: ='CALCULATION of avg returns'!AR18 -> 0.0078106696 | F18: ='CALCULATION of avg returns'!AS18 -> 0.0092085201
A19: 2020 | B19: ='CALCULATION of avg returns'!AO19 -> -0.031020761 | C19: ='CALCULATION of avg returns'!AP19 -> -0.036158352 | D19: ='CALCULATION of avg returns'!AQ19 -> -0.03292236 | E19: ='CALCULATION of avg returns'!AR19 -> -0.032715998 | F19: ='CALCULATION of avg returns'!AS19 -> -0.027551327 | G19: AVERAGE daily RISK | I19: PTF 10% | J19: PTF 20% | K19: PTF 50% | L19: PTF 100% | M19: CAC40
A20: 2020 | B20: ='CALCULATION of avg returns'!AO20 -> 0.011401656 | C20: ='CALCULATION of avg returns'!AP20 -> 0.01015499 | D20: ='CALCULATION of avg returns'!AQ20 -> 0.013108638 | E20: ='CALCULATION of avg returns'!AR20 -> 0.012477579 | F20: ='CALCULATION of avg returns'!AS20 -> 0.0010647753 | H20: 2020 | I20: =_xlfn.STDEV.S(B3:B259) -> 0.023547358 | J20: =_xlfn.STDEV.S(C3:C259) -> 0.019673415 | K20: =_xlfn.STDEV.S(D3:D259) -> 0.019125869 | L20: =_xlfn.STDEV.S(E3:E259) -> 0.019728774 | M20: =_xlfn.STDEV.S(F3:F259) -> 0.020196029
A21: 2020 | B21: ='CALCULATION of avg returns'!AO21 -> 0.0080299925 | C21: ='CALCULATION of avg returns'!AP21 -> 0.0068536524 | D21: ='CALCULATION of avg returns'!AQ21 -> 0.0039675823 | E21: ='CALCULATION of avg returns'!AR21 -> 0.0043003391 | F21: ='CALCULATION of avg returns'!AS21 -> 0.010073021 | H21: 2021 | I21: =_xlfn.STDEV.S(B260:B517) -> 0.014092721 | J21: =_xlfn.STDEV.S(C260:C517) -> 0.013069733 | K21: =_xlfn.STDEV.S(D260:D517) -> 0.012013791 | L21: =_xlfn.STDEV.S(E260:E517) -> 0.011267582 | M21: =_xlfn.STDEV.S(F260:F517) -> 0.0092290634
A22: 2020 | B22: ='CALCULATION of avg returns'!AO22 -> -0.013306737 | C22: ='CALCULATION of avg returns'!AP22 -> -0.015756337 | D22: ='CALCULATION of avg returns'!AQ22 -> -0.01512086 | E22: ='CALCULATION of avg returns'!AR22 -> -0.014726738 | F22: ='CALCULATION of avg returns'!AS22 -> -0.011794673 | H22: 2022 | I22: =_xlfn.STDEV.S(B518:B774) -> 0.019574992 | J22: =_xlfn.STDEV.S(C518:C774) -> 0.020223077 | K22: =_xlfn.STDEV.S(D518:D774) -> 0.018827885 | L22: =_xlfn.STDEV.S(E518:E774) -> 0.017226774 | M22: =_xlfn.STDEV.S(F518:F774) -> 0.01370195
A23: 2020 | B23: ='CALCULATION of avg returns'!AO23 -> -0.011529783 | C23: ='CALCULATION of avg returns'!AP23 -> -0.0068294371 | D23: ='CALCULATION of avg returns'!AQ23 -> -0.0079917494 | E23: ='CALCULATION of avg returns'!AR23 -> -0.0097196233 | F23: ='CALCULATION of avg returns'!AS23 -> -0.0081091945 | H23: 2023 | I23: =_xlfn.STDEV.S(B775:B1028) -> 0.013976509 | J23: =_xlfn.STDEV.S(C775:C1028) -> 0.013868085 | K23: =_xlfn.STDEV.S(D775:D1028) -> 0.012963744 | L23: =_xlfn.STDEV.S(E775:E1028) -> 0.011719348 | M23: =_xlfn.STDEV.S(F775:F1028) -> 0.0085918956
A24: 2020 | B24: ='CALCULATION of avg returns'!AO24 -> 0.0026785596 | C24: ='CALCULATION of avg returns'!AP24 -> 0.0030896881 | D24: ='CALCULATION of avg returns'!AQ24 -> 0.0042511459 | E24: ='CALCULATION of avg returns'!AR24 -> 0.0048705356 | F24: ='CALCULATION of avg returns'!AS24 -> 0.00087945591 | H24: 4 | I24: =_xlfn.STDEV.S(B3:B1028) -> 0.018245886 | J24: =_xlfn.STDEV.S(C3:C1028) -> 0.017021158 | K24: =_xlfn.STDEV.S(D3:D1028) -> 0.016063792 | L24: =_xlfn.STDEV.S(E3:E1028) -> 0.015407881 | M24: =_xlfn.STDEV.S(F3:F1028) -> 0.013734019
A25: 2020 | B25: ='CALCULATION of avg returns'!AO25 -> 0.025253323 | C25: ='CALCULATION of avg returns'!AP25 -> 0.021761644 | D25: ='CALCULATION of avg returns'!AQ25 -> 0.021278914 | E25: ='CALCULATION of avg returns'!AR25 -> 0.020258131 | F25: ='CALCULATION of avg returns'!AS25 -> 0.010110025
A26: 2020 | B26: ='CALCULATION of avg returns'!AO26 -> 0.0080093442 | C26: ='CALCULATION of avg returns'!AP26 -> 0.0098676467 | D26: ='CALCULATION of avg returns'!AQ26 -> 0.0097426848 | E26: ='CALCULATION of avg returns'!AR26 -> 0.0078995739 | F26: ='CALCULATION of avg returns'!AS26 -> 0.0084720322 | I26: PTF 10% | J26: PTF 20% | K26: PTF 50% | L26: PTF 100%
A27: 2020 | B27: ='CALCULATION of avg returns'!AO27 -> 0.00076401003 | C27: ='CALCULATION of avg returns'!AP27 -> -0.004467957 | D27: ='CALCULATION of avg returns'!AQ27 -> -0.001320902 | E27: ='CALCULATION of avg returns'!AR27 -> 0.0022284026 | F27: ='CALCULATION of avg returns'!AS27 -> 0.016246962 | G27: ANNUALISED RISK | H27: 2020 | I27: =I20*SQRT($I4) -> 0.37749286 | J27: =J20*SQRT($I4) -> 0.31538884 | K27: =K20*SQRT($I4) -> 0.306611 | L27: =L20*SQRT($I4) -> 0.31627631
A28: 2020 | B28: ='CALCULATION of avg returns'!AO28 -> -0.010700699 | C28: ='CALCULATION of avg returns'!AP28 -> -0.0044424787 | D28: ='CALCULATION of avg returns'!AQ28 -> -0.0041836407 | E28: ='CALCULATION of avg returns'!AR28 -> -0.0019476714 | F28: ='CALCULATION of avg returns'!AS28 -> -0.0014312937 | H28: 2021 | I28: =I21*SQRT($I5) -> 0.22636262 | J28: =J21*SQRT($I5) -> 0.20993099 | K28: =K21*SQRT($I5) -> 0.19297006 | L28: =L21*SQRT($I5) -> 0.18098417
A29: 2020 | B29: ='CALCULATION of avg returns'!AO29 -> -0.0047844428 | C29: ='CALCULATION of avg returns'!AP29 -> -0.0019600157 | D29: ='CALCULATION of avg returns'!AQ29 -> -0.0013649869 | E29: ='CALCULATION of avg returns'!AR29 -> -0.0017738414 | F29: ='CALCULATION of avg returns'!AS29 -> -0.0010066751 | H29: 2022 | I29: =I22*SQRT($I6) -> 0.31381099 | J29: =J22*SQRT($I6) -> 0.32420058 | K29: =K22*SQRT($I6) -> 0.30183396 | L29: =L22*SQRT($I6) -> 0.27616619
A30: 2020 | B30: ='CALCULATION of avg returns'!AO30 -> 0.00078831739 | C30: ='CALCULATION of avg returns'!AP30 -> 0.00016365541 | D30: ='CALCULATION of avg returns'!AQ30 -> 0.0018661221 | E30: ='CALCULATION of avg returns'!AR30 -> 0.0022663464 | F30: ='CALCULATION of avg returns'!AS30 -> 0.0064865839 | H30: 2023 | I30: =I23*SQRT($I7) -> 0.22274889 | J30: =J23*SQRT($I7) -> 0.2210209 | K30: =K23*SQRT($I7) -> 0.20660807 | L30: =L23*SQRT($I7) -> 0.18677568
A31: 2020 | B31: ='CALCULATION of avg returns'!AO31 -> 0.04850144 | C31: ='CALCULATION of avg returns'!AP31 -> 0.0340413 | D31: ='CALCULATION of avg returns'!AQ31 -> 0.027453607 | E31: ='CALCULATION of avg returns'!AR31 -> 0.018536099 | F31: ='CALCULATION of avg returns'!AS31 -> 0.0050026605 | I31: PTF 10% | J31: PTF 20% | K31: PTF 50% | L31: PTF 100%
A32: 2020 | B32: ='CALCULATION of avg returns'!AO32 -> -0.0058992327 | C32: ='CALCULATION of avg returns'!AP32 -> -0.0022280455 | D32: ='CALCULATION of avg returns'!AQ32 -> -0.001280145 | E32: ='CALCULATION of avg returns'!AR32 -> -0.0016898681 | F32: ='CALCULATION of avg returns'!AS32 -> -0.0057216183 | G32: BETA | H32: 2020 | I32: =_xlfn.COVARIANCE.S(B3:B259,$F$3:$F$259)/_xlfn.VAR.S($F$3:$F$259) -> 0.88657356 | J32: =_xlfn.COVARIANCE.S(C3:C259,$F$3:$F$259)/_xlfn.VAR.S($F$3:$F$259) -> 0.71526424 | K32: =_xlfn.COVARIANCE.S(D3:D259,$F$3:$F$259)/_xlfn.VAR.S($F$3:$F$259) -> 0.73059643 | L32: =_xlfn.COVARIANCE.S(E3:E259,$F$3:$F$259)/_xlfn.VAR.S($F$3:$F$259) -> 0.77916166
A33: 2020 | B33: ='CALCULATION of avg returns'!AO33 -> -0.019611487 | C33: ='CALCULATION of avg returns'!AP33 -> -0.013785097 | D33: ='CALCULATION of avg returns'!AQ33 -> -0.011548015 | E33: ='CALCULATION of avg returns'!AR33 -> -0.01002784 | F33: ='CALCULATION of avg returns'!AS33 -> 0.0064462832 | H33: 2021 | I33: =_xlfn.COVARIANCE.S(B260:B517,$F$260:$F$517)/_xlfn.VAR.S($F$260:$F$517) -> 0.99119506 | J33: =_xlfn.COVARIANCE.S(C260:C517,$F$260:$F$517)/_xlfn.VAR.S($F$260:$F$517) -> 0.8544547 | K33: =_xlfn.COVARIANCE.S(D260:D517,$F$260:$F$517)/_xlfn.VAR.S($F$260:$F$517) -> 0.85597723 | L33: =_xlfn.COVARIANCE.S(E260:E517,$F$260:$F$517)/_xlfn.VAR.S($F$260:$F$517) -> 0.84584431
A34: 2020 | B34: ='CALCULATION of avg returns'!AO34 -> 0.0025020535 | C34: ='CALCULATION of avg returns'!AP34 -> 0.0046506841 | D34: ='CALCULATION of avg returns'!AQ34 -> 0.0041641329 | E34: ='CALCULATION of avg returns'!AR34 -> 0.0031061911 | F34: ='CALCULATION of avg returns'!AS34 -> -0.00036590552 | H34: 2022 | I34: =_xlfn.COVARIANCE.S(B518:B774,$F$518:$F$774)/_xlfn.VAR.S($F$518:$F$774) -> 0.95083379 | J34: =_xlfn.COVARIANCE.S(C518:C774,$F$518:$F$774)/_xlfn.VAR.S($F$518:$F$774) -> 0.90603183 | K34: =_xlfn.COVARIANCE.S(D518:D774,$F$518:$F$774)/_xlfn.VAR.S($F$518:$F$774) -> 0.88756968 | L34: =_xlfn.COVARIANCE.S(E518:E774,$F$518:$F$774)/_xlfn.VAR.S($F$518:$F$774) -> 0.84060331
A35: 2020 | B35: ='CALCULATION of avg returns'!AO35 -> -0.01598326 | C35: ='CALCULATION of avg returns'!AP35 -> -0.014239615 | D35: ='CALCULATION of avg returns'!AQ35 -> -0.012151838 | E35: ='CALCULATION of avg returns'!AR35 -> -0.0095510214 | F35: ='CALCULATION of avg returns'!AS35 -> -0.0041187683 | H35: 2023 | I35: =_xlfn.COVARIANCE.S(B775:B1028,$F$775:$F$1028)/_xlfn.VAR.S($F$775:$F$1028) -> 0.98441281 | J35: =_xlfn.COVARIANCE.S(C775:C1028,$F$775:$F$1028)/_xlfn.VAR.S($F$775:$F$1028) -> 0.94530633 | K35: =_xlfn.COVARIANCE.S(D775:D1028,$F$775:$F$1028)/_xlfn.VAR.S($F$775:$F$1028) -> 0.9278718 | L35: =_xlfn.COVARIANCE.S(E775:E1028,$F$775:$F$1028)/_xlfn.VAR.S($F$775:$F$1028) -> 0.86713662
A36: 2020 | B36: ='CALCULATION of avg returns'!AO36 -> 0.024402741 | C36: ='CALCULATION of avg returns'!AP36 -> 0.020713172 | D36: ='CALCULATION of avg returns'!AQ36 -> 0.018456042 | E36: ='CALCULATION of avg returns'!AR36 -> 0.017099222 | F36: ='CALCULATION of avg returns'!AS36 -> 0.0054172724 | H36: 4 years | I36: =_xlfn.COVARIANCE.S(B3:B1028,$F$3:$F$1028)/_xlfn.VAR.S($F$3:$F$1028) -> 0.92437413 | J36: =_xlfn.COVARIANCE.S(C3:C1028,$F$3:$F$1028)/_xlfn.VAR.S($F$3:$F$1028) -> 0.80152073 | K36: =_xlfn.COVARIANCE.S(D3:D1028,$F$3:$F$1028)/_xlfn.VAR.S($F$3:$F$1028) -> 0.8035161 | L36: =_xlfn.COVARIANCE.S(E3:E1028,$F$3:$F$1028)/_xlfn.VAR.S($F$3:$F$1028) -> 0.81086794
A37: 2020 | B37: ='CALCULATION of avg returns'!AO37 -> -0.021195448 | C37: ='CALCULATION of avg returns'!AP37 -> -0.019217431 | D37: ='CALCULATION of avg returns'!AQ37 -> -0.017535607 | E37: ='CALCULATION of avg returns'!AR37 -> -0.016312371 | F37: ='CALCULATION of avg returns'!AS37 -> -0.0017060069
A38: 2020 | B38: ='CALCULATION of avg returns'!AO38 -> -0.0078569147 | C38: ='CALCULATION of avg returns'!AP38 -> -0.0076364604 | D38: ='CALCULATION of avg returns'!AQ38 -> -0.0068124092 | E38: ='CALCULATION of avg returns'!AR38 -> -0.0063581251 | F38: ='CALCULATION of avg returns'!AS38 -> -0.011078304
A39: 2020 | B39: ='CALCULATION of avg returns'!AO39 -> -0.041810456 | C39: ='CALCULATION of avg returns'!AP39 -> -0.038423819 | D39: ='CALCULATION of avg returns'!AQ39 -> -0.040754464 | E39: ='CALCULATION of avg returns'!AR39 -> -0.041279762 | F39: ='CALCULATION of avg returns'!AS39 -> -0.038359404 | G39: 4 years | H39: PTF 10% | I39: PTF 20% | J39: PTF 50% | K39: PTF 100%
A40: 2020 | B40: ='CALCULATION of avg returns'!AO40 -> -0.020292153 | C40: ='CALCULATION of avg returns'!AP40 -> -0.0154547 | D40: ='CALCULATION of avg returns'!AQ40 -> -0.016255904 | E40: ='CALCULATION of avg returns'!AR40 -> -0.017102309 | F40: ='CALCULATION of avg returns'!AS40 -> -0.016384599 | G40: GLOBAL RETURN | H40: =('CALCULATION of avg returns'!AI1029-'CALCULATION of avg returns'!AI3)/'CALCULATION of avg returns'!AI3 -> -0.04061787 | I40: =('CALCULATION of avg returns'!AJ1029-'CALCULATION of avg returns'!AJ3)/'CALCULATION of avg returns'!AJ3 -> 0.80758721 | J40: =('CALCULATION of avg returns'!AK1029-'CALCULATION of avg returns'!AK3)/'CALCULATION of avg returns'!AK3 -> 0.67829166 | K40: =('CALCULATION of avg returns'!AL1029-'CALCULATION of avg returns'!AL3)/'CALCULATION of avg returns'!AL3 -> 0.49700992
A41: 2020 | B41: ='CALCULATION of avg returns'!AO41 -> 0.0069544463 | C41: ='CALCULATION of avg returns'!AP41 -> 0.0048825292 | D41: ='CALCULATION of avg returns'!AQ41 -> 0.0048876575 | E41: ='CALCULATION of avg returns'!AR41 -> 0.0044111648 | F41: ='CALCULATION of avg returns'!AS41 -> -0.025494162 | G41: GLOB RET ANNUAL | H41: =(1+H40)^(1/4)-1 -> -0.010312908 | I41: =(1+I40)^(1/4)-1 -> 0.15951084 | J41: =(1+J40)^(1/4)-1 -> 0.13819549 | K41: =(1+K40)^(1/4)-1 -> 0.10613
A42: 2020 | B42: ='CALCULATION of avg returns'!AO42 -> -0.035703583 | C42: ='CALCULATION of avg returns'!AP42 -> -0.035922177 | D42: ='CALCULATION of avg returns'!AQ42 -> -0.03686902 | E42: ='CALCULATION of avg returns'!AR42 -> -0.034780581 | F42: ='CALCULATION of avg returns'!AS42 -> -0.018969842 | G42: RISK | H42: =_xlfn.STDEV.S(B3:B1028) -> 0.018245886 | I42: =_xlfn.STDEV.S(C3:C1028) -> 0.017021158 | J42: =_xlfn.STDEV.S(D3:D1028) -> 0.016063792 | K42: =_xlfn.STDEV.S(E3:E1028) -> 0.015407881
A43: 2020 | B43: ='CALCULATION of avg returns'!AO43 -> -0.017474466 | C43: ='CALCULATION of avg returns'!AP43 -> -0.01770719 | D43: ='CALCULATION of avg returns'!AQ43 -> -0.017458322 | E43: ='CALCULATION of avg returns'!AR43 -> -0.023741136 | F43: ='CALCULATION of avg returns'!AS43 -> -0.03536968 | G43: ANNUALIZED RISK | H43: =H42*SQRT(252) -> 0.28964447 | I43: =I42*SQRT(252) -> 0.2702025 | J43: =J42*SQRT(252) -> 0.2550048 | K43: =K42*SQRT(252) -> 0.24459252
A44: 2020 | B44: ='CALCULATION of avg returns'!AO44 -> -0.0045433632 | C44: ='CALCULATION of avg returns'!AP44 -> 0.00094340992 | D44: ='CALCULATION of avg returns'!AQ44 -> 0.0021943203 | E44: ='CALCULATION of avg returns'!AR44 -> 0.0061540087 | F44: ='CALCULATION of avg returns'!AS44 -> -0.0061171494 | G44: SHARPE | H44: =(H41-$O$52)/H43 -> -0.073496684 | I44: =(I41-$O$52)/I43 -> 0.54972047 | J44: =(J41-$O$52)/J43 -> 0.49889449 | K44: =(K41-$O$52)/K43 -> 0.38903477
A45: 2020 | B45: ='CALCULATION of avg returns'!AO45 -> 0.014067826 | C45: ='CALCULATION of avg returns'!AP45 -> 0.013217041 | D45: ='CALCULATION of avg returns'!AQ45 -> 0.011842464 | E45: ='CALCULATION of avg returns'!AR45 -> 0.01013775 | F45: ='CALCULATION of avg returns'!AS45 -> 0.033494498
A46: 2020 | B46: ='CALCULATION of avg returns'!AO46 -> 0.0046432132 | C46: ='CALCULATION of avg returns'!AP46 -> 0.009939106 | D46: ='CALCULATION of avg returns'!AQ46 -> 0.010653342 | E46: ='CALCULATION of avg returns'!AR46 -> 0.012514912 | F46: ='CALCULATION of avg returns'!AS46 -> -0.002663981 | G46: SHARPE base daily | H46: =(I13-O53)/I24 -> 0.00039251903 | I46: =(J13-P53)/J24 -> 0.042409266 | J46: =(K13-Q53)/K24 -> 0.039453007 | K46: =(L13-R53)/L24 -> 0.033236411 | P46: sharpe ratio=5avg daily reurn per year-risk free return)/std e ptf
A47: 2020 | B47: ='CALCULATION of avg returns'!AO47 -> -0.019479415 | C47: ='CALCULATION of avg returns'!AP47 -> -0.014921355 | D47: ='CALCULATION of avg returns'!AQ47 -> -0.018683369 | E47: ='CALCULATION of avg returns'!AR47 -> -0.018529528 | F47: ='CALCULATION of avg returns'!AS47 -> -0.0052469971 | H47: =(I13)/I24 -> 0.0069145371 | I47: =(J13)/J24 -> 0.042409266 | J47: =(K13)/K24 -> 0.039453007 | K47: =(L13)/L24 -> 0.033236411 | N47: Année | O47: Taux OAT 10 ans (%) | P47: Contexte économique
A48: 2020 | B48: ='CALCULATION of avg returns'!AO48 -> -0.038691767 | C48: ='CALCULATION of avg returns'!AP48 -> -0.028978523 | D48: ='CALCULATION of avg returns'!AQ48 -> -0.031912871 | E48: ='CALCULATION of avg returns'!AR48 -> -0.033909598 | F48: ='CALCULATION of avg returns'!AS48 -> -0.039718609 | N48: 2020 | O48: -0.003 | P48: Taux négatifs, politique monétaire très accommodante (Covid)
A49: 2020 | B49: ='CALCULATION of avg returns'!AO49 -> -0.06111061 | C49: ='CALCULATION of avg returns'!AP49 -> -0.053390615 | D49: ='CALCULATION of avg returns'!AQ49 -> -0.058200539 | E49: ='CALCULATION of avg returns'!AR49 -> -0.062875301 | F49: ='CALCULATION of avg returns'!AS49 -> -0.083314933 | I49: 2020 | J49: 2021 | K49: 2022 | L49: 2023 | N49: 2021 | O49: 0 | P49: Taux quasi nuls, reprise lente post-Covid
A50: 2020 | B50: ='CALCULATION of avg returns'!AO50 -> -0.016724605 | C50: ='CALCULATION of avg returns'!AP50 -> -0.016291462 | D50: ='CALCULATION of avg returns'!AQ50 -> -0.016041347 | E50: ='CALCULATION of avg returns'!AR50 -> -0.017340636 | F50: ='CALCULATION of avg returns'!AS50 -> -0.016209072 | H50: PTF 10% | I50: 0.88657356 | J50: 0.99119506 | K50: 0.95083379 | L50: 0.98441281 | N50: 2022 | O50: 0.017 | P50: Inflation forte, hausse des taux BCE
A51: 2020 | B51: ='CALCULATION of avg returns'!AO51 -> -0.01858942 | C51: ='CALCULATION of avg returns'!AP51 -> -0.010356759 | D51: ='CALCULATION of avg returns'!AQ51 -> -0.0073314967 | E51: ='CALCULATION of avg returns'!AR51 -> -0.0092287409 | F51: ='CALCULATION of avg returns'!AS51 -> -0.002623961 | H51: PTF 20% | I51: 0.71526424 | J51: 0.8544547 | K51: 0.90603183 | L51: 0.94530633 | N51: 2023 | O51: 0.0299 | P51: Taux élevés, politique monétaire restrictive
A52: 2020 | B52: ='CALCULATION of avg returns'!AO52 -> -0.12450613 | C52: ='CALCULATION of avg returns'!AP52 -> -0.092265278 | D52: ='CALCULATION of avg returns'!AQ52 -> -0.094544382 | E52: ='CALCULATION of avg returns'!AR52 -> -0.10317393 | F52: ='CALCULATION of avg returns'!AS52 -> -0.12538643 | H52: PTF 50% | I52: 0.73059643 | J52: 0.85597723 | K52: 0.88756968 | L52: 0.9278718 | O52: =SUM(O48:O51)/4 -> 0.010975
A53: 2020 | B53: ='CALCULATION of avg returns'!AO53 -> 0.036747696 | C53: ='CALCULATION of avg returns'!AP53 -> 0.029424266 | D53: ='CALCULATION of avg returns'!AQ53 -> 0.029539726 | E53: ='CALCULATION of avg returns'!AR53 -> 0.022437471 | F53: ='CALCULATION of avg returns'!AS53 -> 0.0072778938 | H53: PTF 100% | I53: 0.77916166 | J53: 0.84584431 | K53: 0.84060331 | L53: 0.86713662 | O53: 0.000119
A54: 2020 | B54: ='CALCULATION of avg returns'!AO54 -> -0.065988734 | C54: ='CALCULATION of avg returns'!AP54 -> -0.055299896 | D54: ='CALCULATION of avg returns'!AQ54 -> -0.054521661 | E54: ='CALCULATION of avg returns'!AR54 -> -0.056971361 | F54: ='CALCULATION of avg returns'!AS54 -> -0.10434283
A55: 2020 | B55: ='CALCULATION of avg returns'!AO55 -> 0.02359599 | C55: ='CALCULATION of avg returns'!AP55 -> 0.021306042 | D55: ='CALCULATION of avg returns'!AQ55 -> 0.030836928 | E55: ='CALCULATION of avg returns'!AR55 -> 0.022736222 | F55: ='CALCULATION of avg returns'!AS55 -> 0.034949863 | M55: 4 years
A56: 2020 | B56: ='CALCULATION of avg returns'!AO56 -> -0.075698735 | C56: ='CALCULATION of avg returns'!AP56 -> -0.064528208 | D56: ='CALCULATION of avg returns'!AQ56 -> -0.057490363 | E56: ='CALCULATION of avg returns'!AR56 -> -0.062001759 | F56: ='CALCULATION of avg returns'!AS56 -> -0.0086592179 | M56: 0.92437413
A57: 2020 | B57: ='CALCULATION of avg returns'!AO57 -> 0.048845103 | C57: ='CALCULATION of avg returns'!AP57 -> 0.055446488 | D57: ='CALCULATION of avg returns'!AQ57 -> 0.044483489 | E57: ='CALCULATION of avg returns'!AR57 -> 0.037195887 | F57: ='CALCULATION of avg returns'!AS57 -> -0.0094916073 | M57: 0.80152073
A58: 2020 | B58: ='CALCULATION of avg returns'!AO58 -> 0.096219118 | C58: ='CALCULATION of avg returns'!AP58 -> 0.088841333 | D58: ='CALCULATION of avg returns'!AQ58 -> 0.068316275 | E58: ='CALCULATION of avg returns'!AR58 -> 0.061613026 | F58: ='CALCULATION of avg returns'!AS58 -> 0.079440164 | M58: 0.8035161
A59: 2020 | B59: ='CALCULATION of avg returns'!AO59 -> -0.031376008 | C59: ='CALCULATION of avg returns'!AP59 -> -0.019214343 | D59: ='CALCULATION of avg returns'!AQ59 -> -0.022268089 | E59: ='CALCULATION of avg returns'!AR59 -> -0.029687158 | F59: ='CALCULATION of avg returns'!AS59 -> -0.033413649 | M59: 0.81086794
A60: 2020 | B60: ='CALCULATION of avg returns'!AO60 -> 0.10801167 | C60: ='CALCULATION of avg returns'!AP60 -> 0.08491587 | D60: ='CALCULATION of avg returns'!AQ60 -> 0.084795099 | E60: ='CALCULATION of avg returns'!AR60 -> 0.092678027 | F60: ='CALCULATION of avg returns'!AS60 -> 0.04852811
A61: 2020 | B61: ='CALCULATION of avg returns'!AO61 -> 0.045504101 | C61: ='CALCULATION of avg returns'!AP61 -> 0.033122131 | D61: ='CALCULATION of avg returns'!AQ61 -> 0.037315491 | E61: ='CALCULATION of avg returns'!AR61 -> 0.050001451 | F61: ='CALCULATION of avg returns'!AS61 -> 0.045383179
A62: 2020 | B62: ='CALCULATION of avg returns'!AO62 -> 0.048111785 | C62: ='CALCULATION of avg returns'!AP62 -> 0.033734903 | D62: ='CALCULATION of avg returns'!AQ62 -> 0.024629994 | E62: ='CALCULATION of avg returns'!AR62 -> 0.028688336 | F62: ='CALCULATION of avg returns'!AS62 -> 0.017705362
A63: 2020 | B63: ='CALCULATION of avg returns'!AO63 -> -0.025025638 | C63: ='CALCULATION of avg returns'!AP63 -> -0.031641551 | D63: ='CALCULATION of avg returns'!AQ63 -> -0.040176486 | E63: ='CALCULATION of avg returns'!AR63 -> -0.045282974 | F63: ='CALCULATION of avg returns'!AS63 -> -0.0017225085
A64: 2020 | B64: ='CALCULATION of avg returns'!AO64 -> 0.0027316399 | C64: ='CALCULATION of avg returns'!AP64 -> -0.002087431 | D64: ='CALCULATION of avg returns'!AQ64 -> 0.0031612431 | E64: ='CALCULATION of avg returns'!AR64 -> 0.00035344752 | F64: ='CALCULATION of avg returns'!AS64 -> -0.016846754
A65: 2020 | B65: ='CALCULATION of avg returns'!AO65 -> -0.01133517 | C65: ='CALCULATION of avg returns'!AP65 -> -0.012588543 | D65: ='CALCULATION of avg returns'!AQ65 -> -0.011757268 | E65: ='CALCULATION of avg returns'!AR65 -> -0.004971531 | F65: ='CALCULATION of avg returns'!AS65 -> 0.022130201
A66: 2020 | B66: ='CALCULATION of avg returns'!AO66 -> -0.046430607 | C66: ='CALCULATION of avg returns'!AP66 -> -0.051194983 | D66: ='CALCULATION of avg returns'!AQ66 -> -0.047305909 | E66: ='CALCULATION of avg returns'!AR66 -> -0.046994165 | F66: ='CALCULATION of avg returns'!AS66 -> -0.028602786
A67: 2020 | B67: ='CALCULATION of avg returns'!AO67 -> -0.0044174306 | C67: ='CALCULATION of avg returns'!AP67 -> 0.0019345322 | D67: ='CALCULATION of avg returns'!AQ67 -> 0.0029046464 | E67: ='CALCULATION of avg returns'!AR67 -> 0.00029016473 | F67: ='CALCULATION of avg returns'!AS67 -> -0.010340503
A68: 2020 | B68: ='CALCULATION of avg returns'!AO68 -> -0.0079733111 | C68: ='CALCULATION of avg returns'!AP68 -> -0.00021721466 | D68: ='CALCULATION of avg returns'!AQ68 -> -0.00049827679 | E68: ='CALCULATION of avg returns'!AR68 -> -0.0076212075 | F68: ='CALCULATION of avg returns'!AS68 -> -0.00021239827
A69: 2020 | B69: ='CALCULATION of avg returns'!AO69 -> 0.041364003 | C69: ='CALCULATION of avg returns'!AP69 -> 0.02144455 | D69: ='CALCULATION of avg returns'!AQ69 -> 0.030067301 | E69: ='CALCULATION of avg returns'!AR69 -> 0.036674727 | F69: ='CALCULATION of avg returns'!AS69 -> 0.03047597
A70: 2020 | B70: ='CALCULATION of avg returns'!AO70 -> 0.024284699 | C70: ='CALCULATION of avg returns'!AP70 -> 0.022073594 | D70: ='CALCULATION of avg returns'!AQ70 -> 0.020150435 | E70: ='CALCULATION of avg returns'!AR70 -> 0.021320568 | F70: ='CALCULATION of avg returns'!AS70 -> 0.025945761
A71: 2020 | B71: ='CALCULATION of avg returns'!AO71 -> 0.00058326502 | C71: ='CALCULATION of avg returns'!AP71 -> 0.016139848 | D71: ='CALCULATION of avg returns'!AQ71 -> 0.0072348101 | E71: ='CALCULATION of avg returns'!AR71 -> 0.0051106363 | F71: ='CALCULATION of avg returns'!AS71 -> -0.010545137
... A500: 2021 | B500: ='CALCULATION of avg returns'!AO500 -> -0.0043877364 | C500: ='CALCULATION of avg returns'!AP500 -> 0.0041127018 | D500: ='CALCULATION of avg returns'!AQ500 -> 0.0032632109 | E500: ='CALCULATION of avg returns'!AR500 -> 0.0021748058 | F500: ='CALCULATION of avg returns'!AS500 -> -0.0044535873
A501: 2021 | B501: ='CALCULATION of avg returns'!AO501 -> -0.010326197 | C501: ='CALCULATION of avg returns'!AP501 -> -0.0042332289 | D501: ='CALCULATION of avg returns'!AQ501 -> -0.004663451 | E501: ='CALCULATION of avg returns'!AR501 -> -0.0049042624 | F501: ='CALCULATION of avg returns'!AS501 -> -0.0032849658 | I501: 07/08/ | J501: 6012.3501 | K501: 122.42579 | L501: 172.75341
A502: 2021 | B502: ='CALCULATION of avg returns'!AO502 -> -0.0071733338 | C502: ='CALCULATION of avg returns'!AP502 -> -0.0066727174 | D502: ='CALCULATION of avg returns'!AQ502 -> -0.0054670087 | E502: ='CALCULATION of avg returns'!AR502 -> -0.0065490134 | F502: ='CALCULATION of avg returns'!AS502 -> -0.0044911277 | I502: 44569 | J502: 6031 | K502: 122.62246 | L502: 173.16483
A503: 2021 | B503: ='CALCULATION of avg returns'!AO503 -> -0.011034793 | C503: ='CALCULATION of avg returns'!AP503 -> -0.013087876 | D503: ='CALCULATION of avg returns'!AQ503 -> -0.012098509 | E503: ='CALCULATION of avg returns'!AR503 -> -0.010927118 | F503: ='CALCULATION of avg returns'!AS503 -> -0.0054537871
A504: 2021 | B504: ='CALCULATION of avg returns'!AO504 -> 0.0092413374 | C504: ='CALCULATION of avg returns'!AP504 -> 0.018605271 | D504: ='CALCULATION of avg returns'!AQ504 -> 0.015968014 | E504: ='CALCULATION of avg returns'!AR504 -> 0.012692035 | F504: ='CALCULATION of avg returns'!AS504 -> 0.0019734914
A505: 2021 | B505: ='CALCULATION of avg returns'!AO505 -> 0.0072576854 | C505: ='CALCULATION of avg returns'!AP505 -> 0.011063242 | D505: ='CALCULATION of avg returns'!AQ505 -> 0.0095387734 | E505: ='CALCULATION of avg returns'!AR505 -> 0.0093394055 | F505: ='CALCULATION of avg returns'!AS505 -> 0.012021828
A506: 2021 | B506: ='CALCULATION of avg returns'!AO506 -> -0.010397417 | C506: ='CALCULATION of avg returns'!AP506 -> -0.039327863 | D506: ='CALCULATION of avg returns'!AQ506 -> -0.032173016 | E506: ='CALCULATION of avg returns'!AR506 -> -0.023208831 | F506: ='CALCULATION of avg returns'!AS506 -> -0.014745383
A507: 2021 | B507: ='CALCULATION of avg returns'!AO507 -> -0.009073075 | C507: ='CALCULATION of avg returns'!AP507 -> 0.0031104839 | D507: ='CALCULATION of avg returns'!AQ507 -> 0.00029929944 | E507: ='CALCULATION of avg returns'!AR507 -> -0.0024863235 | F507: ='CALCULATION of avg returns'!AS507 -> -0.019930544
A508: 2021 | B508: ='CALCULATION of avg returns'!AO508 -> 0.0031218472 | C508: ='CALCULATION of avg returns'!AP508 -> -0.0011642139 | D508: ='CALCULATION of avg returns'!AQ508 -> 0.0016076192 | E508: ='CALCULATION of avg returns'!AR508 -> 0.0043018557 | F508: ='CALCULATION of avg returns'!AS508 -> 0.020870846
A509: 2021 | B509: ='CALCULATION of avg returns'!AO509 -> 0.012809078 | C509: ='CALCULATION of avg returns'!AP509 -> 0.010923491 | D509: ='CALCULATION of avg returns'!AQ509 -> 0.012420065 | E509: ='CALCULATION of avg returns'!AR509 -> 0.013964827 | F509: ='CALCULATION of avg returns'!AS509 -> 0.010915262
A510: 2021 | B510: ='CALCULATION of avg returns'!AO510 -> 0.0052836693 | C510: ='CALCULATION of avg returns'!AP510 -> -0.0042645342 | D510: ='CALCULATION of avg returns'!AQ510 -> -5.7512653e-05 | E510: ='CALCULATION of avg returns'!AR510 -> 0.0030014405 | F510: ='CALCULATION of avg returns'!AS510 -> 0.012379895
A511: 2021 | B511: ='CALCULATION of avg returns'!AO511 -> -0.0028702427 | C511: ='CALCULATION of avg returns'!AP511 -> -0.0020152162 | D511: ='CALCULATION of avg returns'!AQ511 -> -0.0031808827 | E511: ='CALCULATION of avg returns'!AR511 -> -0.0035595915 | F511: ='CALCULATION of avg returns'!AS511 -> 0.005200059
A512: 2021 | B512: ='CALCULATION of avg returns'!AO512 -> 0.01553271 | C512: ='CALCULATION of avg returns'!AP512 -> 0.0092150818 | D512: ='CALCULATION of avg returns'!AQ512 -> 0.0098440358 | E512: ='CALCULATION of avg returns'!AR512 -> 0.0089408125 | F512: ='CALCULATION of avg returns'!AS512 -> -0.0034120831
A513: 2021 | B513: ='CALCULATION of avg returns'!AO513 -> 0.0032762143 | C513: ='CALCULATION of avg returns'!AP513 -> 0.0040606518 | D513: ='CALCULATION of avg returns'!AQ513 -> 0.0048392586 | E513: ='CALCULATION of avg returns'!AR513 -> 0.0060161204 | F513: ='CALCULATION of avg returns'!AS513 -> 0.01122423
A514: 2021 | B514: ='CALCULATION of avg returns'!AO514 -> 0.0011557724 | C514: ='CALCULATION of avg returns'!AP514 -> 0.00074131977 | D514: ='CALCULATION of avg returns'!AQ514 -> -0.00030161512 | E514: ='CALCULATION of avg returns'!AR514 -> -0.00092027575 | F514: ='CALCULATION of avg returns'!AS514 -> -0.00060490053 | M514: 214.72867
A515: 2021 | B515: ='CALCULATION of avg returns'!AO515 -> 0.0044894818 | C515: ='CALCULATION of avg returns'!AP515 -> -0.0015328818 | D515: ='CALCULATION of avg returns'!AQ515 -> -0.00034374714 | E515: ='CALCULATION of avg returns'!AR515 -> 0.0016177437 | F515: ='CALCULATION of avg returns'!AS515 -> 0.0027237 | M515: 215.18581
A516: 2021 | B516: ='CALCULATION of avg returns'!AO516 -> -0.0013499462 | C516: ='CALCULATION of avg returns'!AP516 -> -0.0012854839 | D516: ='CALCULATION of avg returns'!AQ516 -> -0.0018454931 | E516: ='CALCULATION of avg returns'!AR516 -> -0.0016744621 | F516: ='CALCULATION of avg returns'!AS516 -> -0.0024019148
A517: 2021 | B517: ='CALCULATION of avg returns'!AO517 -> 0.0016257786 | C517: ='CALCULATION of avg returns'!AP517 -> 0.0027250562 | D517: ='CALCULATION of avg returns'!AQ517 -> 0.0034995365 | E517: ='CALCULATION of avg returns'!AR517 -> 0.0052266131 | F517: ='CALCULATION of avg returns'!AS517 -> 0.0078743907
A518: 2022 | B518: ='CALCULATION of avg returns'!AO518 -> 0.016012547 | C518: ='CALCULATION of avg returns'!AP518 -> 0.012796063 | D518: ='CALCULATION of avg returns'!AQ518 -> 0.014702614 | E518: ='CALCULATION of avg returns'!AR518 -> 0.0153142 | F518: ='CALCULATION of avg returns'!AS518 -> 0.0075627239
A519: 2022 | B519: ='CALCULATION of avg returns'!AO519 -> 0.015275534 | C519: ='CALCULATION of avg returns'!AP519 -> 0.013387603 | D519: ='CALCULATION of avg returns'!AQ519 -> 0.013433225 | E519: ='CALCULATION of avg returns'!AR519 -> 0.011212529 | F519: ='CALCULATION of avg returns'!AS519 -> 0.0087293662
A520: 2022 | B520: ='CALCULATION of avg returns'!AO520 -> -0.033397571 | C520: ='CALCULATION of avg returns'!AP520 -> -0.040611332 | D520: ='CALCULATION of avg returns'!AQ520 -> -0.037625551 | E520: ='CALCULATION of avg returns'!AR520 -> -0.034381103 | F520: ='CALCULATION of avg returns'!AS520 -> -0.0099336435
A521: 2022 | B521: ='CALCULATION of avg returns'!AO521 -> -0.0059811238 | C521: ='CALCULATION of avg returns'!AP521 -> -0.024116983 | D521: ='CALCULATION of avg returns'!AQ521 -> -0.020134764 | E521: ='CALCULATION of avg returns'!AR521 -> -0.018145525 | F521: ='CALCULATION of avg returns'!AS521 -> -0.0086591685 | R521: 0.0015990547 | S521: 0.0023786087 | T521: 0.0063391873
A522: 2022 | B522: ='CALCULATION of avg returns'!AO522 -> -0.034639801 | C522: ='CALCULATION of avg returns'!AP522 -> -0.042792586 | D522: ='CALCULATION of avg returns'!AQ522 -> -0.033787363 | E522: ='CALCULATION of avg returns'!AR522 -> -0.026184326 | F522: ='CALCULATION of avg returns'!AS522 -> -0.010118164 | O522: 44568 | P522: 2022 | Q522: -0.00020615739 | R522: 0.0016063899 | S522: 0.0023814904 | T522: 0.0021289115
A523: 2022 | B523: ='CALCULATION of avg returns'!AO523 -> 0.024541339 | C523: ='CALCULATION of avg returns'!AP523 -> 0.011331919 | D523: ='CALCULATION of avg returns'!AQ523 -> 0.010195959 | E523: ='CALCULATION of avg returns'!AR523 -> 0.0079209842 | F523: ='CALCULATION of avg returns'!AS523 -> 0.0077249474 | O523: 44569 | P523: 2022 | Q523: 0.0031019321
A524: 2022 | B524: ='CALCULATION of avg returns'!AO524 -> 0.011032558 | C524: ='CALCULATION of avg returns'!AP524 -> 0.0033157492 | D524: ='CALCULATION of avg returns'!AQ524 -> 0.0027737622 | E524: ='CALCULATION of avg returns'!AR524 -> 0.0034068271 | F524: ='CALCULATION of avg returns'!AS524 -> 0.0032037137
A525: 2022 | B525: ='CALCULATION of avg returns'!AO525 -> -0.029074582 | C525: ='CALCULATION of avg returns'!AP525 -> -0.029731333 | D525: ='CALCULATION of avg returns'!AQ525 -> -0.024590356 | E525: ='CALCULATION of avg returns'!AR525 -> -0.021322301 | F525: ='CALCULATION of avg returns'!AS525 -> -0.0022886162
A526: 2022 | B526: ='CALCULATION of avg returns'!AO526 -> -0.026609556 | C526: ='CALCULATION of avg returns'!AP526 -> -0.024004406 | D526: ='CALCULATION of avg returns'!AQ526 -> -0.021456754 | E526: ='CALCULATION of avg returns'!AR526 -> -0.016973331 | F526: ='CALCULATION of avg returns'!AS526 -> -0.0066876519
A527: 2022 | B527: ='CALCULATION of avg returns'!AO527 -> 0.021281567 | C527: ='CALCULATION of avg returns'!AP527 -> 0.028549376 | D527: ='CALCULATION of avg returns'!AQ527 -> 0.022756022 | E527: ='CALCULATION of avg returns'!AR527 -> 0.019981802 | F527: ='CALCULATION of avg returns'!AS527 -> 0.004209855
A528: 2022 | B528: ='CALCULATION of avg returns'!AO528 -> -0.019122245 | C528: ='CALCULATION of avg returns'!AP528 -> -0.011929833 | D528: ='CALCULATION of avg returns'!AQ528 -> -0.012920131 | E528: ='CALCULATION of avg returns'!AR528 -> -0.013195818 | F528: ='CALCULATION of avg returns'!AS528 -> -0.00710451
...

Sheet CALCULATION of avg returns
AG1: AVERAGE CAP PER TRESHHOLD | AN1: RETURN OF THE AVG CAP PER TRESHHOLD | AU1: RETURN OF THE AVG CAP PER TRESHHOLD
A2: série | B2: CAC40 | C2: MC | D2: OR | E2: RMS | F2: AIR | G2: SU | H2: EL | I2: SAF | J2: TTE | K2: AI | L2: SAN | M2: BNP | N2: CDI | O2: CS | P2: DG | Q2: BN | R2: ACA | S2: HO | T2: SGO | U2: ENGI | V2: GLE | W2: GLE2 | X2: ORA | Y2: DSY | Z2: LR | AA2: KER | AB2: RI | AC2: STLAP | AD2: ML | AE2: CAP | AG2: year | AI2: AVG PTF 10% | AJ2: AVG PTF 20% | AK2: AVG PTF 50% | AL2: AVG PTF 100% | AN2: year | AO2: AVG PTF 10% | AP2: AVG PTF 20% | AQ2: AVG PTF 50% | AR2: AVG PTF 100% | AS2: CAC40 | AU2: year | AV2: AVG PTF 10% | AW2: AVG PTF 20% | AX2: AVG PTF 50% | AY2: AVG PTF 100% | AZ2: CAC40
A3: 1 | B3: 6011.21 | C3: 419.15 | D3: 264.2 | E3: 671 | F3: 133.52 | G3: 93.06 | H3: 136.7 | I3: 137.6 | J3: 49.82 | K3: 104.71 | L3: 89.73 | M3: 53.58 | N3: 461.8 | O3: 25.46 | P3: 99.84 | Q3: 73.98 | R3: 13.19 | S3: 92.94 | T3: 36.99 | U3: 14.7 | V3: 31.66 | W3: 31.66 | X3: 13.18 | Y3: 29.46 | Z3: 73.54 | AA3: 598 | AB3: 160.35 | AD3: 27.11 | AE3: 111.05 | AG3: 2020 | AI3: =AVERAGE(G3,AA3,AE3) -> 267.37 | AJ3: =AVERAGE(E3,Y3,AD3,G3,AA3,AE3) -> 254.94667 | AK3: =AVERAGE(Z3,V3,Q3,O3,M3,K3,H3,C3,E3,Y3,AD3,G3,AA3,AE3) -> 174.89 | AL3: =AVERAGE(AC3,AB3,X3,W3,U3,T3,S3,R3,P3,N3,L3,J3,I3,F3,D3,Z3,V3,Q3,O3,M3,K3,H3,C3,E3,Y3,AD3,G3,AA3,AE3) -> 144.57071 | AN3: 2020 | AO3: =(AI4-AI3)/AI3 -> 0.0034409246 | AP3: =(AJ4-AJ3)/AJ3 -> 0.0047264787 | AQ3: =(AK4-AK3)/AK3 -> 0.0024300989 | AR3: =(AL4-AL3)/AL3 -> 0.0022529756 | AS3: =(B4-B3)/B3 -> -0.0027648344 | AU3: 2020
A4: 2 | B4: 5994.59 | C4: 419.1 | D4: 263.9 | E4: 675.4 | F4: 134.04 | G4: 92.82 | H4: 136.25 | I4: 138 | J4: 50.38 | K4: 104.38 | L4: 90.29 | M4: 52.94 | N4: 462.8 | O4: 25.47 | P4: 99.22 | Q4: 74.62 | R4: 13.11 | S4: 94.12 | T4: 36.34 | U4: 14.69 | V4: 31.34 | W4: 31.34 | X4: 13.26 | Y4: 29.69 | Z4: 73.4 | AA4: 600.9 | AB4: 161.2 | AD4: 26.95 | AE4: 111.15 | AG4: 2020 | AI4: =AVERAGE(G4,AA4,AE4) -> 268.29 | AJ4: =AVERAGE(E4,Y4,AD4,G4,AA4,AE4) -> 256.15167 | AK4: =AVERAGE(Z4,V4,Q4,O4,M4,K4,H4,C4,E4,Y4,AD4,G4,AA4,AE4) -> 175.315 | AL4: =AVERAGE(AC4,AB4,X4,W4,U4,T4,S4,R4,P4,N4,L4,J4,I4,F4,D4,Z4,V4,Q4,O4,M4,K4,H4,C4,E4,Y4,AD4,G4,AA4,AE4) -> 144.89643 | AN4: 2020 | AO4: =(AI5-AI4)/AI4 -> -0.014996211 | AP4: =(AJ5-AJ4)/AJ4 -> -0.011627226 | AQ4: =(AK5-AK4)/AK4 -> -0.0095501567 | AR4: =(AL5-AL4)/AL4 -> -0.0068546499 | AS4: =(B5-B4)/B4 -> -0.0065625839 | AU4: 2020 | AV4: =(AI4-AI3)/AI3 -> 0.0034409246 | AW4: =(AJ4-AJ3)/AJ3 -> 0.0047264787 | AX4: =(AK4-AK3)/AK3 -> 0.0024300989 | AY4: =(AL4-AL3)/AL3 -> 0.0022529756 | AZ4: =(B4-B3)/B3 -> -0.0027648344
A5: 3 | B5: 5955.25 | C5: 415.15 | D5: 263 | E5: 669.8 | F5: 133.46 | G5: 92.7 | H5: 136.1 | I5: 136.45 | J5: 50.44 | K5: 103.68 | L5: 90.85 | M5: 52.68 | N5: 461.2 | O5: 25.14 | P5: 98.72 | Q5: 74.76 | R5: 12.98 | S5: 95.04 | T5: 36 | U5: 14.71 | V5: 31.08 | W5: 31.08 | X5: 13.19 | Y5: 29.5 | Z5: 73.34 | AA5: 590.8 | AB5: 161.2 | AD5: 26.94 | AE5: 109.3 | AG5: 2020 | AI5: =AVERAGE(G5,AA5,AE5) -> 264.26667 | AJ5: =AVERAGE(E5,Y5,AD5,G5,AA5,AE5) -> 253.17333 | AK5: =AVERAGE(Z5,V5,Q5,O5,M5,K5,H5,C5,E5,Y5,AD5,G5,AA5,AE5) -> 173.64071 | AL5: =AVERAGE(AC5,AB5,X5,W5,U5,T5,S5,R5,P5,N5,L5,J5,I5,F5,D5,Z5,V5,Q5,O5,M5,K5,H5,C5,E5,Y5,AD5,G5,AA5,AE5) -> 143.90321 | AN5: 2020 | AO5: =(AI6-AI5)/AI5 -> 0.0065211907 | AP5: =(AJ6-AJ5)/AJ5 -> 0.0091373499 | AQ5: =(AK6-AK5)/AK5 -> 0.006026401 | AR5: =(AL6-AL5)/AL5 -> 0.0022882443 | AS5: =(B6-B5)/B5 -> 0.0075143781 | AU5: 2020 | AV5: =(AI5-AI4)/AI4 -> -0.014996211 | AW5: =(AJ5-AJ4)/AJ4 -> -0.011627226 | AX5: =(AK5-AK4)/AK4 -> -0.0095501567 | AY5: =(AL5-AL4)/AL4 -> -0.0068546499 | AZ5: =(B5-B4)/B4 -> -0.0065625839
A6: 4 | B6: 6000 | C6: 416 | D6: 259.6 | E6: 678.2 | F6: 132 | G6: 92.32 | H6: 137.05 | I6: 137.7 | J6: 50.11 | K6: 103.22 | L6: 90.54 | M6: 52.66 | N6: 461.2 | O6: 25.29 | P6: 98.04 | Q6: 74.06 | R6: 12.95 | S6: 94.8 | T6: 35.85 | U6: 14.89 | V6: 31.46 | W6: 31.46 | X6: 13.2 | Y6: 29.74 | Z6: 72.96 | AA6: 596.3 | AB6: 160.55 | AD6: 27.01 | AE6: 109.35 | AG6: 2020 | AI6: =AVERAGE(G6,AA6,AE6) -> 265.99 | AJ6: =AVERAGE(E6,Y6,AD6,G6,AA6,AE6) -> 255.48667 | AK6: =AVERAGE(Z6,V6,Q6,O6,M6,K6,H6,C6,E6,Y6,AD6,G6,AA6,AE6) -> 174.68714 | AL6: =AVERAGE(AC6,AB6,X6,W6,U6,T6,S6,R6,P6,N6,L6,J6,I6,F6,D6,Z6,V6,Q6,O6,M6,K6,H6,C6,E6,Y6,AD6,G6,AA6,AE6) -> 144.2325 | AN6: 2020 | AO6: =(AI7-AI6)/AI6 -> 0.0011779891 | AP6: =(AJ7-AJ6)/AJ6 -> 0.0051209456 | AQ6: =(AK7-AK6)/AK6 -> 0.0046573057 | AR6: =(AL7-AL6)/AL6 -> 0.0049696546 | AS6: =(B7-B6)/B6 -> -0.0045383333 | AU6: 2020 | AV6: =(AI6-AI5)/AI5 -> 0.0065211907 | AW6: =(AJ6-AJ5)/AJ5 -> 0.0091373499 | AX6: =(AK6-AK5)/AK5 -> 0.006026401 | AY6: =(AL6-AL5)/AL5 -> 0.0022882443 | AZ6: =(B6-B5)/B5 -> 0.0075143781
A7: 5 | B7: 5972.77 | C7: 418.8 | D7: 261.2 | E7: 684.2 | F7: 134.38 | G7: 92.56 | H7: 138.9 | I7: 137.5 | J7: 50.24 | K7: 103.31 | L7: 90.84 | M7: 52.78 | N7: 463.2 | O7: 25.28 | P7: 99.92 | Q7: 72.56 | R7: 13.01 | S7: 96.18 | T7: 35.9 | U7: 14.87 | V7: 31.77 | W7: 31.77 | X7: 13.11 | Y7: 30.1 | Z7: 72.84 | AA7: 597.3 | AB7: 159.45 | AD7: 27.56 | AE7: 109.05 | AG7: 2020 | AI7: =AVERAGE(G7,AA7,AE7) -> 266.30333 | AJ7: =AVERAGE(E7,Y7,AD7,G7,AA7,AE7) -> 256.795 | AK7: =AVERAGE(Z7,V7,Q7,O7,M7,K7,H7,C7,E7,Y7,AD7,G7,AA7,AE7) -> 175.50071 | AL7: =AVERAGE(AC7,AB7,X7,W7,U7,T7,S7,R7,P7,N7,L7,J7,I7,F7,D7,Z7,V7,Q7,O7,M7,K7,H7,C7,E7,Y7,AD7,G7,AA7,AE7) -> 144.94929 | AN7: 2020 | AO7: =(AI8-AI7)/AI7 -> -0.0027036838 | AP7: =(AJ8-AJ7)/AJ7 -> 0.00075287032 | AQ7: =(AK8-AK7)/AK7 -> 0.0037647384 | AR7: =(AL8-AL7)/AL7 -> 0.0036687709 | AS7: =(B8-B7)/B7 -> 0.010276639 | AU7: 2020 | AV7: =(AI7-AI6)/AI6 -> 0.0011779891 | AW7: =(AJ7-AJ6)/AJ6 -> 0.0051209456 | AX7: =(AK7-AK6)/AK6 -> 0.0046573057 | AY7: =(AL7-AL6)/AL6 -> 0.0049696546 | AZ7: =(B7-B6)/B6 -> -0.0045383333
A8: 6 | B8: 6034.15 | C8: 424.5 | D8: 262.8 | E8: 687 | F8: 134.92 | G8: 91.8 | H8: 141.15 | I8: 139.45 | J8: 49.96 | K8: 103.72 | L8: 91.5 | M8: 52.4 | N8: 465 | O8: 25.25 | P8: 98.92 | Q8: 72.7 | R8: 13.02 | S8: 96.5 | T8: 35.69 | U8: 14.81 | V8: 31.79 | W8: 31.79 | X8: 13.15 | Y8: 30.49 | Z8: 72.82 | AA8: 595.9 | AB8: 159.7 | AD8: 27.69 | AE8: 109.05 | AG8: 2020 | AI8: =AVERAGE(G8,AA8,AE8) -> 265.58333 | AJ8: =AVERAGE(E8,Y8,AD8,G8,AA8,AE8) -> 256.98833 | AK8: =AVERAGE(Z8,V8,Q8,O8,M8,K8,H8,C8,E8,Y8,AD8,G8,AA8,AE8) -> 176.16143 | AL8: =AVERAGE(AC8,AB8,X8,W8,U8,T8,S8,R8,P8,N8,L8,J8,I8,F8,D8,Z8,V8,Q8,O8,M8,K8,H8,C8,E8,Y8,AD8,G8,AA8,AE8) -> 145.48107 | AN8: 2020 | AO8: =(AI9-AI8)/AI8 -> -0.0028365234 | AP8: =(AJ9-AJ8)/AJ8 -> 6.4853787e-05 | AQ8: =(AK9-AK8)/AK8 -> -0.00066091977 | AR8: =(AL9-AL8)/AL8 -> -0.0006751001 | AS8: =(B9-B8)/B8 -> -0.00097113927 | AU8: 2020 | AV8: =(AI8-AI7)/AI7 -> -0.0027036838 | AW8: =(AJ8-AJ7)/AJ7 -> 0.00075287032 | AX8: =(AK8-AK7)/AK7 -> 0.0037647384 | AY8: =(AL8-AL7)/AL7 -> 0.0036687709 | AZ8: =(B8-B7)/B7 -> 0.010276639
A9: 7 | B9: 6028.29 | C9: 423.65 | D9: 263.9 | E9: 689 | F9: 134.42 | G9: 92.14 | H9: 141 | I9: 138.5 | J9: 49.79 | K9: 103.97 | L9: 92.22 | M9: 52.16 | N9: 465.6 | O9: 25.36 | P9: 99.42 | Q9: 72.6 | R9: 12.88 | S9: 95.92 | T9: 35.22 | U9: 14.76 | V9: 31.44 | W9: 31.44 | X9: 13.12 | Y9: 30.8 | Z9: 72.42 | AA9: 592.1 | AB9: 158.9 | AD9: 27.74 | AE9: 110.25 | AG9: 2020 | AI9: =AVERAGE(G9,AA9,AE9) -> 264.83 | AJ9: =AVERAGE(E9,Y9,AD9,G9,AA9,AE9) -> 257.005 | AK9: =AVERAGE(Z9,V9,Q9,O9,M9,K9,H9,C9,E9,Y9,AD9,G9,AA9,AE9) -> 176.045 | AL9: =AVERAGE(AC9,AB9,X9,W9,U9,T9,S9,R9,P9,N9,L9,J9,I9,F9,D9,Z9,V9,Q9,O9,M9,K9,H9,C9,E9,Y9,AD9,G9,AA9,AE9) -> 145.38286 | AN9: 2020 | AO9: =(AI10-AI9)/AI9 -> 0.0038641141 | AP9: =(AJ10-AJ9)/AJ9 -> 0.0024188894 | AQ9: =(AK10-AK9)/AK9 -> 0.0016351339 | AR9: =(AL10-AL9)/AL9 -> 0.0021838888 | AS9: =(B10-B9)/B9 -> -0.0016522098 | AU9: 2020 | AV9: =(AI9-AI8)/AI8 -> -0.0028365234 | AW9: =(AJ9-AJ8)/AJ8 -> 6.4853787e-05 | AX9: =(AK9-AK8)/AK8 -> -0.00066091977 | AY9: =(AL9-AL8)/AL8 -> -0.0006751001 | AZ9: =(B9-B8)/B8 -> -0.00097113927
A10: 8 | B10: 6018.33 | C10: 426.75 | D10: 262.5 | E10: 689.6 | F10: 135.12 | G10: 91.86 | H10: 138.8 | I10: 137.45 | J10: 49.56 | K10: 104.34 | L10: 91.57 | M10: 51.93 | N10: 467.6 | O10: 25.34 | P10: 99.74 | Q10: 72.26 | R10: 12.86 | S10: 96.78 | T10: 35.67 | U10: 14.8 | V10: 31.44 | W10: 31.44 | X10: 13.06 | Y10: 30.9 | Z10: 72.04 | AA10: 593.8 | AB10: 162.8 | AD10: 27.7 | AE10: 111.9 | AG10: 2020 | AI10: =AVERAGE(G10,AA10,AE10) -> 265.85333 | AJ10: =AVERAGE(E10,Y10,AD10,G10,AA10,AE10) -> 257.62667 | AK10: =AVERAGE(Z10,V10,Q10,O10,M10,K10,H10,C10,E10,Y10,AD10,G10,AA10,AE10) -> 176.33286 | AL10: =AVERAGE(AC10,AB10,X10,W10,U10,T10,S10,R10,P10,N10,L10,J10,I10,F10,D10,Z10,V10,Q10,O10,M10,K10,H10,C10,E10,Y10,AD10,G10,AA10,AE10) -> 145.70036 | AN10: 2020 | AO10: =(AI11-AI10)/AI10 -> 0.0017678921 | AP10: =(AJ11-AJ10)/AJ10 -> 0.0073361971 | AQ10: =(AK11-AK10)/AK10 -> 0.006793159 | AR10: =(AL11-AL10)/AL10 -> 0.0061206831 | AS10: =(B11-B10)/B10 -> -0.0063605685 | AU10: 2020 | AV10: =(AI10-AI9)/AI9 -> 0.0038641141 | AW10: =(AJ10-AJ9)/AJ9 -> 0.0024188894 | AX10: =(AK10-AK9)/AK9 -> 0.0016351339 | AY10: =(AL10-AL9)/AL9 -> 0.0021838888 | AZ10: =(B10-B9)/B9 -> -0.0016522098
A11: 9 | B11: 5980.05 | C11: 431 | D11: 263.8 | E11: 699.6 | F11: 135.1 | G11: 92.62 | H11: 139.85 | I11: 137.6 | J11: 49.16 | K11: 104.96 | L11: 90.77 | M11: 52.17 | N11: 472 | O11: 24.69 | P11: 100.4 | Q11: 71.4 | R11: 12.92 | S11: 96.46 | T11: 35.95 | U11: 14.81 | V11: 31.44 | W11: 31.44 | X11: 13.04 | Y11: 30.8 | Z11: 72.82 | AA11: 592.1 | AB11: 165.7 | AD11: 27.73 | AE11: 114.25 | AG11: 2020 | AI11: =AVERAGE(G11,AA11,AE11) -> 266.32333 | AJ11: =AVERAGE(E11,Y11,AD11,G11,AA11,AE11) -> 259.51667 | AK11: =AVERAGE(Z11,V11,Q11,O11,M11,K11,H11,C11,E11,Y11,AD11,G11,AA11,AE11) -> 177.53071 | AL11: =AVERAGE(AC11,AB11,X11,W11,U11,T11,S11,R11,P11,N11,L11,J11,I11,F11,D11,Z11,V11,Q11,O11,M11,K11,H11,C11,E11,Y11,AD11,G11,AA11,AE11) -> 146.59214 | AN11: 2020 | AO11: =(AI12-AI11)/AI11 -> 0.0035921249 | AP11: =(AJ12-AJ11)/AJ11 -> 0.0074690129 | AQ11: =(AK12-AK11)/AK11 -> 0.0051218501 | AR11: =(AL12-AL11)/AL11 -> 0.0050870004 | AS11: =(B12-B11)/B11 -> 0.0052223644 | AU11: 2020 | AV11: =(AI11-AI10)/AI10 -> 0.0017678921 | AW11: =(AJ11-AJ10)/AJ10 -> 0.0073361971 | AX11: =(AK11-AK10)/AK10 -> 0.006793159 | AY11: =(AL11-AL10)/AL10 -> 0.0061206831 | AZ11: =(B11-B10)/B10 -> -0.0063605685
A12: 10 | B12: 6011.28 | C12: 431.45 | D12: 269.4 | E12: 708.6 | F12: 134.26 | G12: 92.34 | H12: 142.1 | I12: 139.25 | J12: 48.58 | K12: 104.79 | L12: 91.22 | M12: 50.96 | N12: 473.4 | O12: 24.18 | P12: 100.55 | Q12: 72.44 | R12: 12.77 | S12: 96.32 | T12: 35.42 | U12: 14.9 | V12: 30.95 | W12: 30.95 | X12: 13.03 | Y12: 31.21 | Z12: 72.56 | AA12: 594.6 | AB12: 167.25 | AD12: 27.08 | AE12: 114.9 | AG12: 2020 | AI12: =AVERAGE(G12,AA12,AE12) -> 267.28 | AJ12: =AVERAGE(E12,Y12,AD12,G12,AA12,AE12) -> 261.455 | AK12: =AVERAGE(Z12,V12,Q12,O12,M12,K12,H12,C12,E12,Y12,AD12,G12,AA12,AE12) -> 178.44 | AL12: =AVERAGE(AC12,AB12,X12,W12,U12,T12,S12,R12,P12,N12,L12,J12,I12,F12,D12,Z12,V12,Q12,O12,M12,K12,H12,C12,E12,Y12,AD12,G12,AA12,AE12) -> 147.33786 | AN12: 2020 | AO12: =(AI13-AI12)/AI12 -> 0.013319365 | AP12: =(AJ13-AJ12)/AJ12 -> 0.0087905503 | AQ12: =(AK13-AK12)/AK12 -> 0.0059603868 | AR12: =(AL13-AL12)/AL12 -> 0.004081969 | AS12: =(B13-B12)/B12 -> 0.0016219507 | AU12: 2020 | AV12: =(AI12-AI11)/AI11 -> 0.0035921249 | AW12: =(AJ12-AJ11)/AJ11 -> 0.0074690129 | AX12: =(AK12-AK11)/AK11 -> 0.0051218501 | AY12: =(AL12-AL11)/AL11 -> 0.0050870004 | AZ12: =(B12-B11)/B11 -> 0.0052223644
A13: 11 | B13: 6021.03 | C13: 431.9 | D13: 269.8 | E13: 712 | F13: 133.4 | G13: 92.62 | H13: 142.1 | I13: 141 | J13: 48.79 | K13: 105.25 | L13: 91.11 | M13: 50.59 | N13: 473.6 | O13: 24.2 | P13: 100.45 | Q13: 73.5 | R13: 12.78 | S13: 97.3 | T13: 35.07 | U13: 14.98 | V13: 30.61 | W13: 30.61 | X13: 12.86 | Y13: 31.04 | Z13: 72.38 | AA13: 605.1 | AB13: 167.5 | AD13: 26.96 | AE13: 114.8 | AG13: 2020 | AI13: =AVERAGE(G13,AA13,AE13) -> 270.84 | AJ13: =AVERAGE(E13,Y13,AD13,G13,AA13,AE13) -> 263.75333 | AK13: =AVERAGE(Z13,V13,Q13,O13,M13,K13,H13,C13,E13,Y13,AD13,G13,AA13,AE13) -> 179.50357 | AL13: =AVERAGE(AC13,AB13,X13,W13,U13,T13,S13,R13,P13,N13,L13,J13,I13,F13,D13,Z13,V13,Q13,O13,M13,K13,H13,C13,E13,Y13,AD13,G13,AA13,AE13) -> 147.93929 | AN13: 2020 | AO13: =(AI14-AI13)/AI13 -> 0.010215133 | AP13: =(AJ14-AJ13)/AJ13 -> 0.01447691 | AQ13: =(AK14-AK13)/AK13 -> 0.014464495 | AR13: =(AL14-AL13)/AL13 -> 0.014491949 | AS13: =(B14-B13)/B13 -> 0.0075169863 | AU13: 2020 | AV13: =(AI13-AI12)/AI12 -> 0.013319365 | AW13: =(AJ13-AJ12)/AJ12 -> 0.0087905503 | AX13: =(AK13-AK12)/AK12 -> 0.0059603868 | AY13: =(AL13-AL12)/AL12 -> 0.004081969 | AZ13: =(B13-B12)/B12 -> 0.0016219507
A14: 12 | B14: 6066.29 | C14: 439.05 | D14: 275.3 | E14: 725.6 | F14: 136.78 | G14: 94.22 | H14: 144.7 | I14: 142.55 | J14: 48.51 | K14: 106.94 | L14: 91.69 | M14: 50.75 | N14: 479.2 | O14: 24.38 | P14: 102.4 | Q14: 73.7 | R14: 12.87 | S14: 98.78 | T14: 35.37 | U14: 15.2 | V14: 30.65 | W14: 30.65 | X14: 13.03 | Y14: 31.51 | Z14: 73.8 | AA14: 610.2 | AB14: 170.6 | AD14: 27.5 | AE14: 116.4 | AG14: 2020 | AI14: =AVERAGE(G14,AA14,AE14) -> 273.60667 | AJ14: =AVERAGE(E14,Y14,AD14,G14,AA14,AE14) -> 267.57167 | AK14: =AVERAGE(Z14,V14,Q14,O14,M14,K14,H14,C14,E14,Y14,AD14,G14,AA14,AE14) -> 182.1 | AL14: =AVERAGE(AC14,AB14,X14,W14,U14,T14,S14,R14,P14,N14,L14,J14,I14,F14,D14,Z14,V14,Q14,O14,M14,K14,H14,C14,E14,Y14,AD14,G14,AA14,AE14) -> 150.08321 | AN14: 2020 | AO14: =(AI15-AI14)/AI14 -> -0.013206306 | AP14: =(AJ15-AJ14)/AJ14 -> -0.011828607 | AQ14: =(AK15-AK14)/AK14 -> -0.012465678 | AR14: =(AL15-AL14)/AL14 -> -0.0094590382 | AS14: =(B15-B14)/B14 -> 0.00080444555 | AU14: 2020 | AV14: =(AI14-AI13)/AI13 -> 0.010215133 | AW14: =(AJ14-AJ13)/AJ13 -> 0.01447691 | AX14: =(AK14-AK13)/AK13 -> 0.014464495 | AY14: =(AL14-AL13)/AL13 -> 0.014491949 | AZ14: =(B14-B13)/B13 -> 0.0075169863
A15: 13 | B15: 6071.17 | C15: 429.75 | D15: 274.3 | E15: 717 | F15: 137.9 | G15: 93.98 | H15: 142.9 | I15: 142.15 | J15: 48.57 | K15: 106.49 | L15: 91.4 | M15: 50.49 | N15: 472.6 | O15: 24.48 | P15: 102.1 | Q15: 73.22 | R15: 12.81 | S15: 99.9 | T15: 35.13 | U15: 15.3 | V15: 30.59 | W15: 30.59 | X15: 13.06 | Y15: 31.57 | Z15: 73.26 | AA15: 599 | AB15: 169.15 | AD15: 27.89 | AE15: 117 | AG15: 2020 | AI15: =AVERAGE(G15,AA15,AE15) -> 269.99333 | AJ15: =AVERAGE(E15,Y15,AD15,G15,AA15,AE15) -> 264.40667 | AK15: =AVERAGE(Z15,V15,Q15,O15,M15,K15,H15,C15,E15,Y15,AD15,G15,AA15,AE15) -> 179.83 | AL15: =AVERAGE(AC15,AB15,X15,W15,U15,T15,S15,R15,P15,N15,L15,J15,I15,F15,D15,Z15,V15,Q15,O15,M15,K15,H15,C15,E15,Y15,AD15,G15,AA15,AE15) -> 148.66357 | AN15: 2020 | AO15: =(AI16-AI15)/AI15 -> -0.015099138 | AP15: =(AJ16-AJ15)/AJ15 -> -0.012606843 | AQ15: =(AK16-AK15)/AK15 -> -0.010136558 | AR15: =(AL16-AL15)/AL15 -> -0.010591989 | AS15: =(B16-B15)/B15 -> -0.012682893 | AU15: 2020 | AV15: =(AI15-AI14)/AI14 -> -0.013206306 | AW15: =(AJ15-AJ14)/AJ14 -> -0.011828607 | AX15: =(AK15-AK14)/AK14 -> -0.012465678 | AY15: =(AL15-AL14)/AL14 -> -0.0094590382 | AZ15: =(B15-B14)/B14 -> 0.00080444555
... A269: 267 | B269: 5563.74 | C269: 493.95 | D269: 298.4 | E269: 881 | F269: 92.55 | G269: 124.35 | H269: 124.05 | I269: 114.75 | J269: 37.1 | K269: 109.42 | L269: 81.09 | M269: 44.44 | N269: 436 | O269: 19.92 | P269: 84.72 | Q269: 53.62 | R269: 10.18 | S269: 76.44 | T269: 43.12 | U269: 13.62 | V269: 17.33 | W269: 17.33 | X269: 9.75 | Y269: 32.55 | Z269: 80 | AA269: 561.8 | AB269: 155.55 | AD269: 27.21 | AE269: 124.15 | AG269: 2021 | AI269: =AVERAGE(G269,AA269,AE269) -> 270.1 | AJ269: =AVERAGE(E269,Y269,AD269,G269,AA269,AE269) -> 291.84333 | AK269: =AVERAGE(Z269,V269,Q269,O269,M269,K269,H269,C269,E269,Y269,AD269,G269,AA269,AE269) -> 192.41357 | AL269: =AVERAGE(AC269,AB269,X269,W269,U269,T269,S269,R269,P269,N269,L269,J269,I269,F269,D269,Z269,V269,Q269,O269,M269,K269,H269,C269,E269,Y269,AD269,G269,AA269,AE269) -> 148.72821 | AN269: 2021 | AO269: =(AI270-AI269)/AI269 -> 0.0034555103 | AP269: =(AJ270-AJ269)/AJ269 -> 0.0051169006 | AQ269: =(AK270-AK269)/AK269 -> 0.0063924805 | AR269: =(AL270-AL269)/AL269 -> -0.028851102 | AS269: =(B270-B269)/B269 -> 0.0037474792 | AU269: 2021 | AV269: =(AI269-AI268)/AI268 -> -0.010381045 | AW269: =(AJ269-AJ268)/AJ268 -> -0.01407055 | AX269: =(AK269-AK268)/AK268 -> -0.015967123 | AY269: =(AL269-AL268)/AL268 -> -0.014326898 | AZ269: =(B269-B268)/B268 -> -0.016442303
A270: 268 | B270: 5584.59 | C270: 499.65 | D270: 296.9 | E270: 887.6 | F270: 91.19 | G270: 122.75 | H270: 125.05 | I270: 113.7 | J270: 36.98 | K270: 109.83 | L270: 81.19 | M270: 44.81 | N270: 436 | O270: 19.73 | P270: 84.66 | Q270: 54.72 | R270: 10.28 | S270: 75.46 | T270: 42.65 | U270: 13.49 | V270: 17.4 | W270: 17.4 | X270: 9.67 | Y270: 32.08 | Z270: 79.8 | AA270: 565.5 | AB270: 155.35 | AC270: 12.75 | AD270: 27.24 | AE270: 124.85 | AG270: 2021 | AI270: =AVERAGE(G270,AA270,AE270) -> 271.03333 | AJ270: =AVERAGE(E270,Y270,AD270,G270,AA270,AE270) -> 293.33667 | AK270: =AVERAGE(Z270,V270,Q270,O270,M270,K270,H270,C270,E270,Y270,AD270,G270,AA270,AE270) -> 193.64357 | AL270: =AVERAGE(AC270,AB270,X270,W270,U270,T270,S270,R270,P270,N270,L270,J270,I270,F270,D270,Z270,V270,Q270,O270,M270,K270,H270,C270,E270,Y270,AD270,G270,AA270,AE270) -> 144.43724 | AN270: 2021 | AO270: =(AI271-AI270)/AI270 -> -0.021092117 | AP270: =(AJ271-AJ270)/AJ270 -> -0.024232679 | AQ270: =(AK271-AK270)/AK270 -> -0.019745409 | AR270: =(AL271-AL270)/AL270 -> -0.0129277 | AS270: =(B271-B270)/B270 -> 0.0013626784 | AU270: 2021 | AV270: =(AI270-AI269)/AI269 -> 0.0034555103 | AW270: =(AJ270-AJ269)/AJ269 -> 0.0051169006 | AX270: =(AK270-AK269)/AK269 -> 0.0063924805 | AY270: =(AL270-AL269)/AL269 -> -0.028851102 | AZ270: =(B270-B269)/B269 -> 0.0037474792
A271: 269 | B271: 5592.2 | C271: 491.05 | D271: 297.1 | E271: 862.4 | F271: 91.3 | G271: 122.65 | H271: 123.1 | I271: 113.25 | J271: 37.15 | K271: 109.38 | L271: 82.78 | M271: 44.11 | N271: 432.6 | O271: 19.65 | P271: 84.84 | Q271: 56.18 | R271: 10.05 | S271: 75.6 | T271: 42.71 | U271: 13.58 | V271: 16.98 | W271: 16.98 | X271: 9.66 | Y271: 32.12 | Z271: 79.66 | AA271: 547.9 | AB271: 156.3 | AC271: 13.15 | AD271: 26.9 | AE271: 125.4 | AG271: 2021 | AI271: =AVERAGE(G271,AA271,AE271) -> 265.31667 | AJ271: =AVERAGE(E271,Y271,AD271,G271,AA271,AE271) -> 286.22833 | AK271: =AVERAGE(Z271,V271,Q271,O271,M271,K271,H271,C271,E271,Y271,AD271,G271,AA271,AE271) -> 189.82 | AL271: =AVERAGE(AC271,AB271,X271,W271,U271,T271,S271,R271,P271,N271,L271,J271,I271,F271,D271,Z271,V271,Q271,O271,M271,K271,H271,C271,E271,Y271,AD271,G271,AA271,AE271) -> 142.57 | AN271: 2021 | AO271: =(AI272-AI271)/AI271 -> 0.010616245 | AP271: =(AJ272-AJ271)/AJ271 -> 0.0089846684 | AQ271: =(AK272-AK271)/AK271 -> 0.012079113 | AR271: =(AL272-AL271)/AL271 -> 0.0095972214 | AS271: =(B272-B271)/B271 -> 0.0018400629 | AU271: 2021 | AV271: =(AI271-AI270)/AI270 -> -0.021092117 | AW271: =(AJ271-AJ270)/AJ270 -> -0.024232679 | AX271: =(AK271-AK270)/AK270 -> -0.019745409 | AY271: =(AL271-AL270)/AL270 -> -0.0129277 | AZ271: =(B271-B270)/B270 -> 0.0013626784
A272: 270 | B272: 5602.49 | C272: 507.7 | D272: 293.6 | E272: 868.2 | F272: 92.41 | G272: 123.2 | H272: 124.5 | I272: 114.9 | J272: 37.35 | K272: 108.26 | L272: 81.9 | M272: 44.42 | N272: 441.4 | O272: 19.72 | P272: 83.58 | Q272: 55.28 | R272: 10.21 | S272: 78.5 | T272: 43.25 | U272: 13.45 | V272: 17.08 | W272: 17.08 | X272: 9.66 | Y272: 32.45 | Z272: 79.82 | AA272: 556.7 | AB272: 154.15 | AC272: 13.19 | AD272: 27.75 | AE272: 124.5 | AG272: 2021 | AI272: =AVERAGE(G272,AA272,AE272) -> 268.13333 | AJ272: =AVERAGE(E272,Y272,AD272,G272,AA272,AE272) -> 288.8 | AK272: =AVERAGE(Z272,V272,Q272,O272,M272,K272,H272,C272,E272,Y272,AD272,G272,AA272,AE272) -> 192.11286 | AL272: =AVERAGE(AC272,AB272,X272,W272,U272,T272,S272,R272,P272,N272,L272,J272,I272,F272,D272,Z272,V272,Q272,O272,M272,K272,H272,C272,E272,Y272,AD272,G272,AA272,AE272) -> 143.93828 | AN272: 2021 | AO272: =(AI273-AI272)/AI272 -> -0.0059050224 | AP272: =(AJ273-AJ272)/AJ272 -> 0.0019390582 | AQ272: =(AK273-AK272)/AK272 -> 0.00047962879 | AR272: =(AL273-AL272)/AL272 -> -0.0011331485 | AS272: =(B273-B272)/B272 -> -0.0022650643 | AU272: 2021 | AV272: =(AI272-AI271)/AI271 -> 0.010616245 | AW272: =(AJ272-AJ271)/AJ271 -> 0.0089846684 | AX272: =(AK272-AK271)/AK271 -> 0.012079113 | AY272: =(AL272-AL271)/AL271 -> 0.0095972214 | AZ272: =(B272-B271)/B271 -> 0.0018400629
A273: 271 | B273: 5589.8 | C273: 507.6 | D273: 294.6 | E273: 875.6 | F273: 89.36 | G273: 125.15 | H273: 122.6 | I273: 111.95 | J273: 36.48 | K273: 108.39 | L273: 80.98 | M273: 44.34 | N273: 447.4 | O273: 19.52 | P273: 81.52 | Q273: 55.08 | R273: 10.06 | S273: 76.58 | T273: 43.32 | U273: 13.32 | V273: 16.9 | W273: 16.9 | X273: 9.56 | Y273: 32.85 | Z273: 80.28 | AA273: 550.2 | AB273: 153.65 | AC273: 12.93 | AD273: 28.06 | AE273: 124.3 | AG273: 2021 | AI273: =AVERAGE(G273,AA273,AE273) -> 266.55 | AJ273: =AVERAGE(E273,Y273,AD273,G273,AA273,AE273) -> 289.36 | AK273: =AVERAGE(Z273,V273,Q273,O273,M273,K273,H273,C273,E273,Y273,AD273,G273,AA273,AE273) -> 192.205 | AL273: =AVERAGE(AC273,AB273,X273,W273,U273,T273,S273,R273,P273,N273,L273,J273,I273,F273,D273,Z273,V273,Q273,O273,M273,K273,H273,C273,E273,Y273,AD273,G273,AA273,AE273) -> 143.77517 | AN273: 2021 | AO273: =(AI274-AI273)/AI273 -> -0.0086287751 | AP273: =(AJ274-AJ273)/AJ273 -> -0.0040030873 | AQ273: =(AK274-AK273)/AK273 -> -0.0020402323 | AR273: =(AL274-AL273)/AL273 -> -0.0028372843 | AS273: =(B274-B273)/B273 -> -0.014018391 | AU273: 2021 | AV273: =(AI273-AI272)/AI272 -> -0.0059050224 | AW273: =(AJ273-AJ272)/AJ272 -> 0.0019390582 | AX273: =(AK273-AK272)/AK272 -> 0.00047962879 | AY273: =(AL273-AL272)/AL272 -> -0.0011331485 | AZ273: =(B273-B272)/B272 -> -0.0022650643
A274: 272 | B274: 5511.44 | C274: 511.5 | D274: 296.3 | E274: 875.6 | F274: 88.83 | G274: 125.35 | H274: 122.5 | I274: 110.55 | J274: 36.22 | K274: 109.13 | L274: 81.02 | M274: 43.09 | N274: 446.2 | O274: 19.21 | P274: 80.46 | Q274: 54.56 | R274: 9.92 | S274: 75.5 | T274: 42.6 | U274: 13.12 | V274: 16.34 | W274: 16.34 | X274: 9.59 | Y274: 33 | Z274: 79.84 | AA274: 544 | AB274: 153.1 | AC274: 12.52 | AD274: 27.86 | AE274: 123.4 | AG274: 2021 | AI274: =AVERAGE(G274,AA274,AE274) -> 264.25 | AJ274: =AVERAGE(E274,Y274,AD274,G274,AA274,AE274) -> 288.20167 | AK274: =AVERAGE(Z274,V274,Q274,O274,M274,K274,H274,C274,E274,Y274,AD274,G274,AA274,AE274) -> 191.81286 | AL274: =AVERAGE(AC274,AB274,X274,W274,U274,T274,S274,R274,P274,N274,L274,J274,I274,F274,D274,Z274,V274,Q274,O274,M274,K274,H274,C274,E274,Y274,AD274,G274,AA274,AE274) -> 143.36724 | AN274: 2021 | AO274: =(AI275-AI274)/AI274 -> -0.017470829 | AP274: =(AJ275-AJ274)/AJ274 -> -0.011415618 | AQ274: =(AK275-AK274)/AK274 -> -0.013346342 | AR274: =(AL275-AL274)/AL274 -> -0.013377749 | AS274: =(B275-B274)/B274 -> -0.010559854 | AU274: 2021 | AV274: =(AI274-AI273)/AI273 -> -0.0086287751 | AW274: =(AJ274-AJ273)/AJ273 -> -0.0040030873 | AX274: =(AK274-AK273)/AK273 -> -0.0020402323 | AY274: =(AL274-AL273)/AL273 -> -0.0028372843 | AZ274: =(B274-B273)/B273 -> -0.014018391
A275: 273 | B275: 5453.24 | C275: 501.9 | D275: 299 | E275: 869.6 | F275: 84.87 | G275: 124.7 | H275: 120.55 | I275: 106.15 | J275: 35.35 | K275: 108.6 | L275: 81.06 | M275: 41.23 | N275: 440.6 | O275: 18.77 | P275: 78.72 | Q275: 54.7 | R275: 9.5 | S275: 73.2 | T275: 42.03 | U275: 12.93 | V275: 15.62 | W275: 15.62 | X275: 9.55 | Y275: 33.53 | Z275: 78.7 | AA275: 533 | AB275: 151.95 | AC275: 11.96 | AD275: 27.44 | AE275: 121.2 | AG275: 2021 | AI275: =AVERAGE(G275,AA275,AE275) -> 259.63333 | AJ275: =AVERAGE(E275,Y275,AD275,G275,AA275,AE275) -> 284.91167 | AK275: =AVERAGE(Z275,V275,Q275,O275,M275,K275,H275,C275,E275,Y275,AD275,G275,AA275,AE275) -> 189.25286 | AL275: =AVERAGE(AC275,AB275,X275,W275,U275,T275,S275,R275,P275,N275,L275,J275,I275,F275,D275,Z275,V275,Q275,O275,M275,K275,H275,C275,E275,Y275,AD275,G275,AA275,AE275) -> 141.44931 | AN275: 2021 | AO275: =(AI276-AI275)/AI275 -> 0.018102452 | AP275: =(AJ276-AJ275)/AJ275 -> 0.0089267434 | AQ275: =(AK276-AK275)/AK275 -> 0.01028103 | AR275: =(AL276-AL275)/AL275 -> 0.0093514674 | AS275: =(B276-B275)/B275 -> 0.0032732834 | AU275: 2021 | AV275: =(AI275-AI274)/AI274 -> -0.017470829 | AW275: =(AJ275-AJ274)/AJ274 -> -0.011415618 | AX275: =(AK275-AK274)/AK274 -> -0.013346342 | AY275: =(AL275-AL274)/AL274 -> -0.013377749 | AZ275: =(B275-B274)/B274 -> -0.010559854
A276: 274 | B276: 5471.09 | C276: 508 | D276: 301.8 | E276: 870 | F276: 85.29 | G276: 125.6 | H276: 120.7 | I276: 108 | J276: 35.98 | K276: 111.53 | L276: 80.63 | M276: 41.99 | N276: 444.2 | O276: 18.86 | P276: 77.98 | Q276: 55.38 | R276: 9.67 | S276: 73.36 | T276: 41.94 | U276: 12.99 | V276: 15.99 | W276: 15.99 | X276: 9.7 | Y276: 33.94 | Z276: 79.6 | AA276: 545.7 | AB276: 153.9 | AC276: 12.18 | AD276: 27.79 | AE276: 121.7 | AG276: 2021 | AI276: =AVERAGE(G276,AA276,AE276) -> 264.33333 | AJ276: =AVERAGE(E276,Y276,AD276,G276,AA276,AE276) -> 287.455 | AK276: =AVERAGE(Z276,V276,Q276,O276,M276,K276,H276,C276,E276,Y276,AD276,G276,AA276,AE276) -> 191.19857 | AL276: =AVERAGE(AC276,AB276,X276,W276,U276,T276,S276,R276,P276,N276,L276,J276,I276,F276,D276,Z276,V276,Q276,O276,M276,K276,H276,C276,E276,Y276,AD276,G276,AA276,AE276) -> 142.77207 | AN276: 2021 | AO276: =(AI277-AI276)/AI276 -> -0.0110971 | AP276: =(AJ277-AJ276)/AJ276 -> -0.014709549 | AQ276: =(AK277-AK276)/AK276 -> -0.011887417 | AR276: =(AL277-AL276)/AL276 -> -0.012131707 | AS276: =(B277-B276)/B276 -> -0.012732381 | AU276: 2021 | AV276: =(AI276-AI275)/AI275 -> 0.018102452 | AW276: =(AJ276-AJ275)/AJ275 -> 0.0089267434 | AX276: =(AK276-AK275)/AK275 -> 0.01028103 | AY276: =(AL276-AL275)/AL275 -> 0.0093514674 | AZ276: =(B276-B275)/B275 -> 0.0032732834
A277: 275 | B277: 5401.43 | C277: 506.4 | D277: 297.6 | E277: 854.2 | F277: 84.36 | G277: 123.1 | H277: 118.35 | I277: 105.95 | J277: 35.83 | K277: 112.81 | L277: 78.64 | M277: 40.53 | N277: 438.6 | O277: 18.67 | P277: 76.84 | Q277: 55.2 | R277: 9.43 | S277: 74.28 | T277: 40.82 | U277: 12.73 | V277: 15.56 | W277: 15.56 | X277: 9.85 | Y277: 33.83 | Z277: 78.08 | AA277: 541.6 | AB277: 152.95 | AC277: 11.76 | AD277: 27.13 | AE277: 119.5 | AG277: 2021 | AI277: =AVERAGE(G277,AA277,AE277) -> 261.4 | AJ277: =AVERAGE(E277,Y277,AD277,G277,AA277,AE277) -> 283.22667 | AK277: =AVERAGE(Z277,V277,Q277,O277,M277,K277,H277,C277,E277,Y277,AD277,G277,AA277,AE277) -> 188.92571 | AL277: =AVERAGE(AC277,AB277,X277,W277,U277,T277,S277,R277,P277,N277,L277,J277,I277,F277,D277,Z277,V277,Q277,O277,M277,K277,H277,C277,E277,Y277,AD277,G277,AA277,AE277) -> 141.04 | AN277: 2021 | AO277: =(AI278-AI277)/AI277 -> 0.019127774 | AP277: =(AJ278-AJ277)/AJ277 -> 0.013134356 | AQ277: =(AK278-AK277)/AK277 -> 0.012540832 | AR277: =(AL278-AL277)/AL277 -> 0.011627907 | AS277: =(B278-B277)/B277 -> -0.0041118741 | AU277: 2021 | AV277: =(AI277-AI276)/AI276 -> -0.0110971 | AW277: =(AJ277-AJ276)/AJ276 -> -0.014709549 | AX277: =(AK277-AK276)/AK276 -> -0.011887417 | AY277: =(AL277-AL276)/AL276 -> -0.012131707 | AZ277: =(B277-B276)/B276 -> -0.012732381
A278: 276 | B278: 5379.22 | C278: 517 | D278: 297.4 | E278: 861.6 | F278: 85.15 | G278: 123.8 | H278: 117.9 | I278: 106.3 | J278: 35.82 | K278: 112.73 | L278: 78.66 | M278: 41.21 | N278: 444 | O278: 18.8 | P278: 78.68 | Q278: 55.28 | R278: 9.57 | S278: 73.98 | T278: 41.61 | U278: 12.96 | V278: 15.77 | W278: 15.77 | X278: 9.8 | Y278: 33.17 | Z278: 77.76 | AA278: 555.9 | AB278: 157.85 | AC278: 12.04 | AD278: 27.71 | AE278: 119.5 | AG278: 2021 | AI278: =AVERAGE(G278,AA278,AE278) -> 266.4 | AJ278: =AVERAGE(E278,Y278,AD278,G278,AA278,AE278) -> 286.94667 | AK278: =AVERAGE(Z278,V278,Q278,O278,M278,K278,H278,C278,E278,Y278,AD278,G278,AA278,AE278) -> 191.295 | AL278: =AVERAGE(AC278,AB278,X278,W278,U278,T278,S278,R278,P278,N278,L278,J278,I278,F278,D278,Z278,V278,Q278,O278,M278,K278,H278,C278,E278,Y278,AD278,G278,AA278,AE278) -> 142.68 | AN278: 2021 | AO278: =(AI279-AI278)/AI278 -> -0.021458959 | AP278: =(AJ279-AJ278)/AJ278 -> -0.020677478 | AQ278: =(AK279-AK278)/AK278 -> -0.022702408 | AR278: =(AL279-AL278)/AL278 -> -0.02262357 | AS278: =(B279-B278)/B278 -> 0.0037161522 | AU278: 2021 | AV278: =(AI278-AI277)/AI277 -> 0.019127774 | AW278: =(AJ278-AJ277)/AJ277 -> 0.013134356 | AX278: =(AK278-AK277)/AK277 -> 0.012540832 | AY278: =(AL278-AL277)/AL277 -> 0.011627907 | AZ278: =(B278-B277)/B277 -> -0.0041118741
A279: 277 | B279: 5399.21 | C279: 498.3 | D279: 290.1 | E279: 842.6 | F279: 83.2 | G279: 120.95 | H279: 117 | I279: 104.1 | J279: 34.9 | K279: 111.57 | L279: 76.73 | M279: 39.78 | N279: 431 | O279: 18.3 | P279: 76.58 | Q279: 54.96 | R279: 9.38 | S279: 74.18 | T279: 41.08 | U279: 12.82 | V279: 15.44 | W279: 15.44 | X279: 9.7 | Y279: 32.95 | Z279: 75.9 | AA279: 541.6 | AB279: 155.7 | AC279: 11.87 | AD279: 28.48 | AE279: 119.5 | AG279: 2021 | AI279: =AVERAGE(G279,AA279,AE279) -> 260.68333 | AJ279: =AVERAGE(E279,Y279,AD279,G279,AA279,AE279) -> 281.01333 | AK279: =AVERAGE(Z279,V279,Q279,O279,M279,K279,H279,C279,E279,Y279,AD279,G279,AA279,AE279) -> 186.95214 | AL279: =AVERAGE(AC279,AB279,X279,W279,U279,T279,S279,R279,P279,N279,L279,J279,I279,F279,D279,Z279,V279,Q279,O279,M279,K279,H279,C279,E279,Y279,AD279,G279,AA279,AE279) -> 139.45207 | AN279: 2021 | AO279: =(AI280-AI279)/AI279 -> 0.0084393581 | AP279: =(AJ280-AJ279)/AJ279 -> 0.01119164 | AQ279: =(AK280-AK279)/AK279 -> 0.013276889 | AR279: =(AL280-AL279)/AL279 -> 0.014230572 | AS279: =(B280-B279)/B279 -> 0.0056619394 | AU279: 2021 | AV279: =(AI279-AI278)/AI278 -> -0.021458959 | AW279: =(AJ279-AJ278)/AJ278 -> -0.020677478 | AX279: =(AK279-AK278)/AK278 -> -0.022702408 | AY279: =(AL279-AL278)/AL278 -> -0.02262357 | AZ279: =(B279-B278)/B278 -> 0.0037161522
A280: 278 | B280: 5429.78 | C280: 507.7 | D280: 296.5 | E280: 854.2 | F280: 83.11 | G280: 123.4 | H280: 120.5 | I280: 102.95 | J280: 34.56 | K280: 112.48 | L280: 77.79 | M280: 40.18 | N280: 443.8 | O280: 18.45 | P280: 77.92 | Q280: 55.6 | R280: 9.52 | S280: 74.6 | T280: 41.64 | U280: 12.98 | V280: 15.58 | W280: 15.58 | X280: 9.73 | Y280: 33.55 | Z280: 76.64 | AA280: 543 | AB280: 156.95 | AC280: 11.95 | AD280: 28.55 | AE280: 122.25 | AG280: 2021 | AI280: =AVERAGE(G280,AA280,AE280) -> 262.88333 | AJ280: =AVERAGE(E280,Y280,AD280,G280,AA280,AE280) -> 284.15833 | AK280: =AVERAGE(Z280,V280,Q280,O280,M280,K280,H280,C280,E280,Y280,AD280,G280,AA280,AE280) -> 189.43429 | AL280: =AVERAGE(AC280,AB280,X280,W280,U280,T280,S280,R280,P280,N280,L280,J280,I280,F280,D280,Z280,V280,Q280,O280,M280,K280,H280,C280,E280,Y280,AD280,G280,AA280,AE280) -> 141.43655 | AN280: 2021 | AO280: =(AI281-AI280)/AI280 -> 0.014201484 | AP280: =(AJ281-AJ280)/AJ280 -> 0.024962609 | AQ280: =(AK281-AK280)/AK280 -> 0.024305451 | AR280: =(AL281-AL280)/AL280 -> 0.023285694 | AS280: =(B281-B280)/B280 -> 0.01463411 | AU280: 2021 | AV280: =(AI280-AI279)/AI279 -> 0.0084393581 | AW280: =(AJ280-AJ279)/AJ279 -> 0.01119164 | AX280: =(AK280-AK279)/AK279 -> 0.013276889 | AY280: =(AL280-AL279)/AL279 -> 0.014230572 | AZ280: =(B280-B279)/B279 -> 0.0056619394
A281: 279 | B281: 5509.24 | C281: 524.9 | D281: 298.4 | E281: 884.8 | F281: 88.59 | G281: 125.9 | H281: 123.05 | I281: 107.85 | J281: 34.87 | K281: 112.27 | L281: 78.17 | M281: 41.61 | N281: 453 | O281: 18.82 | P281: 80.16 | Q281: 54.68 | R281: 9.8 | S281: 76.84 | T281: 42.05 | U281: 13.04 | V281: 16.14 | W281: 16.14 | X281: 9.72 | Y281: 34.25 | Z281: 77.56 | AA281: 549.2 | AB281: 159.7 | AC281: 12.3 | AD281: 28.61 | AE281: 124.75 | AG281: 2021 | AI281: =AVERAGE(G281,AA281,AE281) -> 266.61667 | AJ281: =AVERAGE(E281,Y281,AD281,G281,AA281,AE281) -> 291.25167 | AK281: =AVERAGE(Z281,V281,Q281,O281,M281,K281,H281,C281,E281,Y281,AD281,G281,AA281,AE281) -> 194.03857 | AL281: =AVERAGE(AC281,AB281,X281,W281,U281,T281,S281,R281,P281,N281,L281,J281,I281,F281,D281,Z281,V281,Q281,O281,M281,K281,H281,C281,E281,Y281,AD281,G281,AA281,AE281) -> 144.73 | AN281: 2021 | AO281: =(AI282-AI281)/AI281 -> -0.0081890354 | AP281: =(AJ282-AJ281)/AJ281 -> -0.0002460644 | AQ281: =(AK282-AK281)/AK281 -> -0.00053008607 | AR281: =(AL282-AL281)/AL281 -> -0.0017893009 | AS281: =(B282-B281)/B281 -> 0.0081408688 | AU281: 2021 | AV281: =(AI281-AI280)/AI280 -> 0.014201484 | AW281: =(AJ281-AJ280)/AJ280 -> 0.024962609 | AX281: =(AK281-AK280)/AK280 -> 0.024305451 | AY281: =(AL281-AL280)/AL280 -> 0.023285694 | AZ281: =(B281-B280)/B280 -> 0.01463411
... A1028: 1026 | B1028: 7531.71 | C1028: 731 | D1028: 451.3 | E1028: 1910.8 | F1028: 139.68 | G1028: 181.36 | H1028: 180.96 | I1028: 159.62 | J1028: 61.41 | K1028: 160.18 | L1028: 89.26 | M1028: 62.45 | N1028: 705 | O1028: 29.43 | P1028: 113.56 | Q1028: 58.51 | R1028: 12.86 | S1028: 134.1 | T1028: 66.39 | U1028: 15.96 | V1028: 24.04 | W1028: 24.04 | X1028: 10.31 | Y1028: 44.26 | Z1028: 94.2 | AA1028: 398.25 | AB1028: 160.3 | AC1028: 21.18 | AD1028: 32.36 | AE1028: 189.8 | AG1028: 2023 | AI1028: =AVERAGE(G1028,AA1028,AE1028) -> 256.47 | AJ1028: =AVERAGE(E1028,Y1028,AD1028,G1028,AA1028,AE1028) -> 459.47167 | AK1028: =AVERAGE(Z1028,V1028,Q1028,O1028,M1028,K1028,H1028,C1028,E1028,Y1028,AD1028,G1028,AA1028,AE1028) -> 292.68571 | AL1028: =AVERAGE(AC1028,AB1028,X1028,W1028,U1028,T1028,S1028,R1028,P1028,N1028,L1028,J1028,I1028,F1028,D1028,Z1028,V1028,Q1028,O1028,M1028,K1028,H1028,C1028,E1028,Y1028,AD1028,G1028,AA1028,AE1028) -> 215.95069 | AN1028: 2023 | AO1028: =(AI1029-AI1028)/AI1028 -> 0.00015596366 | AP1028: =(AJ1029-AJ1028)/AJ1028 -> 0.0029744308 | AQ1028: =(AK1029-AK1028)/AK1028 -> 0.0028382468 | AR1028: =(AL1029-AL1028)/AL1028 -> 0.0021907939 | AS1028: =(B1029-B1028)/B1028 -> -0.00010356214 | AU1028: 2023 | AV1028: =(AI1028-AI1027)/AI1027 -> -0.0082366589 | AW1028: =(AJ1028-AJ1027)/AJ1027 -> -0.0092361987 | AX1028: =(AK1028-AK1027)/AK1027 -> -0.0077945852 | AY1028: =(AL1028-AL1027)/AL1027 -> -0.0050347459 | AZ1028: =(B1028-B1027)/B1027 -> -0.0038132197
A1029: 1027 | B1029: 7530.93 | C1029: 733.6 | D1029: 450.65 | E1029: 1918.8 | F1029: 139.78 | G1029: 181.78 | H1029: 181.6 | I1029: 159.46 | J1029: 61.6 | K1029: 160.11 | L1029: 89.76 | M1029: 62.59 | N1029: 707.5 | O1029: 29.49 | P1029: 113.7 | Q1029: 58.68 | R1029: 12.85 | S1029: 133.95 | T1029: 66.66 | U1029: 15.92 | V1029: 24.03 | W1029: 24.03 | X1029: 10.3 | Y1029: 44.24 | Z1029: 94.1 | AA1029: 399 | AB1029: 159.75 | AC1029: 21.15 | AD1029: 32.46 | AE1029: 188.75 | AG1029: 2023 | AI1029: =AVERAGE(G1029,AA1029,AE1029) -> 256.51 | AJ1029: =AVERAGE(E1029,Y1029,AD1029,G1029,AA1029,AE1029) -> 460.83833 | AK1029: =AVERAGE(Z1029,V1029,Q1029,O1029,M1029,K1029,H1029,C1029,E1029,Y1029,AD1029,G1029,AA1029,AE1029) -> 293.51643 | AL1029: =AVERAGE(AC1029,AB1029,X1029,W1029,U1029,T1029,S1029,R1029,P1029,N1029,L1029,J1029,I1029,F1029,D1029,Z1029,V1029,Q1029,O1029,M1029,K1029,H1029,C1029,E1029,Y1029,AD1029,G1029,AA1029,AE1029) -> 216.42379 | AV1029: =(AI1029-AI1028)/AI1028 -> 0.00015596366 | AW1029: =(AJ1029-AJ1028)/AJ1028 -> 0.0029744308 | AX1029: =(AK1029-AK1028)/AK1028 -> 0.0028382468 | AY1029: =(AL1029-AL1028)/AL1028 -> 0.0021907939 | AZ1029: =(B1029-B1028)/B1028 -> -0.00010356214

Sheet Liste et Treshold
A1: SYMBOL | B1: COMPANY NAME | C1: TRESHOLD | D1: MARKET CAP | E1: STROCK PRICE | F1: % CHANGE | G1: INDUSTRY | H1: VOLUME | I1: PE RATIO | J1: EMPLOYEES | K1: ROA | L1: TOTAL DEBT | M1: ASSETS | N1: REVENUE | O1: GLOBAL ESG | P1: RISQUE E | Q1: RISQUE S | R1: RISQUE G | S1: Threshold PF 50% | T1: Threshold PF 20% | U1: Threshold PF 10% | W1: Threshold PF 50% | X1: Threshold PF 20% | Y1: Threshold PF 10%
A2: MC | B2: LVMH Moët Hennessy - Louis Vuitton, Société Européenne | C2: {=_xlfn.IFS( AND(S2="inclusion",T2="-",U2="-"),"50%", AND(S2="inclusion",T2="inclusion",U2="-"),"20%", AND(S2="inclusion",T2="inclusion",U2="inclusion"),"10%", AND(S2="-",T2="-",U2="-")," ")} -> 50% | D2: 246.65B | E2: 494.90 | F2: -0.27% | G2: Luxury Goods | H2: 96.451 | I2: 22.56 | J2: 200.52 | K2: 7.83% | L2: 39.71B | M2: 141.58B | N2: 82.82B | O2: 13.8 | P2: 0.8 | Q2: 7.1 | R2: 5.9 | S2: =IF($O2<=PERCENTILE($O$2:$O$29,0.5),"inclusion","-") -> inclusion | T2: =IF($O2<=PERCENTILE($O$2:$O$29,0.2),"inclusion","-") -> - | U2: =IF($O2<=PERCENTILE($O$2:$O$29,0.1),"inclusion","-") -> - | W2: =IF($P2<=PERCENTILE($P$2:$P$29,0.6),"inclusion","-") -> inclusion | X2: =IF($P2<=PERCENTILE($P$2:$P$29,0.3),"inclusion","-") -> inclusion | Y2: =IF($P2<=PERCENTILE($P$2:$P$29,0.2),"inclusion","-") -> inclusion
A3: OR | B3: L'Oréal S.A. | C3: {=_xlfn.IFS( AND(S3="inclusion",T3="-",U3="-"),"50%", AND(S3="inclusion",T3="inclusion",U3="-"),"20%", AND(S3="inclusion",T3="inclusion",U3="inclusion"),"10%", AND(S3="-",T3="-",U3="-")," ")} | D3: 214.69B | E3: 402.65 | F3: 0.01% | G3: Household & Personal Products | H3: 51.239 | I3: 35.26 | J3: 94.397 | K3: 10.25% | L3: 8.83B | M3: 54.60B | N3: 43.84B | O3: 18.4 | P3: 6.5 | Q3: 6.5 | R3: 5.4 | S3: =IF($O3<=PERCENTILE($O$2:$O$29,0.5),"inclusion","-") -> - | T3: =IF($O3<=PERCENTILE($O$2:$O$29,0.2),"inclusion","-") -> - | U3: =IF($O3<=PERCENTILE($O$2:$O$29,0.1),"inclusion","-") -> - | W3: =IF($P3<=PERCENTILE($P$2:$P$29,0.6),"inclusion","-") -> inclusion | X3: =IF($P3<=PERCENTILE($P$2:$P$29,0.3),"inclusion","-") -> - | Y3: =IF($P3<=PERCENTILE($P$2:$P$29,0.2),"inclusion","-") -> -
A4: RMS | B4: Hermès International Société en commandite par actions | C4: {=_xlfn.IFS( AND(S4="inclusion",T4="-",U4="-"),"50%", AND(S4="inclusion",T4="inclusion",U4="-"),"20%", AND(S4="inclusion",T4="inclusion",U4="inclusion"),"10%", AND(S4="-",T4="-",U4="-")," ")} -> 20% | D4: 213.76B | E4: 2,045.00 | F4: 0.29% | G4: Luxury Goods | H4: 8.415 | I4: 47.77 | J4: 25.185 | K4: 19.09% | L4: 2.06B | M4: 21.83B | N4: 15.70B | O4: 12.7 | P4: 3.2 | Q4: 4.8 | R4: 4.8 | S4: =IF($O4<=PERCENTILE($O$2:$O$29,0.5),"inclusion","-") -> inclusion | T4: =IF($O4<=PERCENTILE($O$2:$O$29,0.2),"inclusion","-") -> inclusion | U4: =IF($O4<=PERCENTILE($O$2:$O$29,0.1),"inclusion","-") -> - | W4: =IF($P4<=PERCENTILE($P$2:$P$29,0.6),"inclusion","-") -> inclusion | X4: =IF($P4<=PERCENTILE($P$2:$P$29,0.3),"inclusion","-") -> - | Y4: =IF($P4<=PERCENTILE($P$2:$P$29,0.2),"inclusion","-") -> -
A5: AIR | B5: Airbus SE | C5: {=_xlfn.IFS( AND(S5="inclusion",T5="-",U5="-"),"50%", AND(S5="inclusion",T5="inclusion",U5="-"),"20%", AND(S5="inclusion",T5="inclusion",U5="inclusion"),"10%", AND(S5="-",T5="-",U5="-")," ")} | D5: 145.47B | E5: 186.58 | F5: 1.49% | G5: Aerospace & Defense | H5: 257.544 | I5: 29.46 | J5: 156.92 | K5: 2.53% | L5: 13.36B | M5: 129.04B | N5: 70.02B | O5: 24.1 | P5: 5.7 | Q5: 12.6 | R5: 5.7 | S5: =IF($O5<=PERCENTILE($O$2:$O$29,0.5),"inclusion","-") -> - | T5: =IF($O5<=PERCENTILE($O$2:$O$29,0.2),"inclusion","-") -> - | U5: =IF($O5<=PERCENTILE($O$2:$O$29,0.1),"inclusion","-") -> - | W5: =IF($P5<=PERCENTILE($P$2:$P$29,0.6),"inclusion","-") -> inclusion | X5: =IF($P5<=PERCENTILE($P$2:$P$29,0.3),"inclusion","-") -> - | Y5: =IF($P5<=PERCENTILE($P$2:$P$29,0.2),"inclusion","-") -> -
A6: SU | B6: Schneider Electric S.E. | C6: {=_xlfn.IFS( AND(S6="inclusion",T6="-",U6="-"),"50%", AND(S6="inclusion",T6="inclusion",U6="-"),"20%", AND(S6="inclusion",T6="inclusion",U6="inclusion"),"10%", AND(S6="-",T6="-",U6="-")," ")} -> 10% | D6: 122.95B | E6: 224.80 | F6: 2.98% | G6: Specialty Industrial Machinery | H6: 232.016 | I6: 28.76 | J6: 159 | K6: 6.95% | L6: 17.07B | M6: 61.97B | N6: 39.32B | O6: 9.4 | P6: 3.4 | Q6: 3.6 | R6: 2.4 | S6: =IF($O6<=PERCENTILE($O$2:$O$29,0.5),"inclusion","-") -> inclusion | T6: =IF($O6<=PERCENTILE($O$2:$O$29,0.2),"inclusion","-") -> inclusion | U6: =IF($O6<=PERCENTILE($O$2:$O$29,0.1),"inclusion","-") -> inclusion | W6: =IF($P6<=PERCENTILE($P$2:$P$29,0.6),"inclusion","-") -> inclusion | X6: =IF($P6<=PERCENTILE($P$2:$P$29,0.3),"inclusion","-") -> - | Y6: =IF($P6<=PERCENTILE($P$2:$P$29,0.2),"inclusion","-") -> -
A7: EL | B7: EssilorLuxottica Société anonyme | C7: {=_xlfn.IFS( AND(S7="inclusion",T7="-",U7="-"),"50%", AND(S7="inclusion",T7="inclusion",U7="-"),"20%", AND(S7="inclusion",T7="inclusion",U7="inclusion"),"10%", AND(S7="-",T7="-",U7="-")," ")} -> 50% | D7: 119.71B | E7: 259.10 | F7: -0.19% | G7: Medical Instruments & Supplies | H7: 41.731 | I7: 50.38 | J7: 153.5 | K7: 3.58% | L7: 14.05B | M7: 61.93B | N7: 27.24B | O7: 16.7 | P7: 1.5 | Q7: 9.2 | R7: 6 | S7: =IF($O7<=PERCENTILE($O$2:$O$29,0.5),"inclusion","-") -> inclusion | T7: =IF($O7<=PERCENTILE($O$2:$O$29,0.2),"inclusion","-") -> - | U7: =IF($O7<=PERCENTILE($O$2:$O$29,0.1),"inclusion","-") -> - | W7: =IF($P7<=PERCENTILE($P$2:$P$29,0.6),"inclusion","-") -> inclusion | X7: =IF($P7<=PERCENTILE($P$2:$P$29,0.3),"inclusion","-") -> inclusion | Y7: =IF($P7<=PERCENTILE($P$2:$P$29,0.2),"inclusion","-") -> inclusion
A8: SAF | B8: Safran SA | C8: {=_xlfn.IFS( AND(S8="inclusion",T8="-",U8="-"),"50%", AND(S8="inclusion",T8="inclusion",U8="-"),"20%", AND(S8="inclusion",T8="inclusion",U8="inclusion"),"10%", AND(S8="-",T8="-",U8="-")," ")} | D8: 116.56B | E8: 278.00 | F8: -0.07% | G8: Aerospace & Defense | H8: 68.409 | I8: 26.57 | J8: 96.39 | K8: 5.19% | L8: 5.12B | M8: 56.09B | N8: 29.38B | O8: 28.7 | P8: 11 | Q8: 12.7 | R8: 5.1 | S8: =IF($O8<=PERCENTILE($O$2:$O$29,0.5),"inclusion","-") -> - | T8: =IF($O8<=PERCENTILE($O$2:$O$29,0.2),"inclusion","-") -> - | U8: =IF($O8<=PERCENTILE($O$2:$O$29,0.1),"inclusion","-") -> - | W8: =IF($P8<=PERCENTILE($P$2:$P$29,0.6),"inclusion","-") -> - | X8: =IF($P8<=PERCENTILE($P$2:$P$29,0.3),"inclusion","-") -> - | Y8: =IF($P8<=PERCENTILE($P$2:$P$29,0.2),"inclusion","-") -> -
A9: TTE | B9: TotalEnergies SE | C9: {=_xlfn.IFS( AND(S9="inclusion",T9="-",U9="-"),"50%", AND(S9="inclusion",T9="inclusion",U9="-"),"20%", AND(S9="inclusion",T9="inclusion",U9="inclusion"),"10%", AND(S9="-",T9="-",U9="-")," ")} | D9: 113.08B | E9: 52.26 | F9: 0.85% | G9: Oil & Gas Integrated | H9: 803.539 | I9: 11.08 | J9: 95.393 | K9: 4.89% | L9: 53.71B | M9: 249.33B | N9: 159.33B | O9: 31.7 | P9: 15.5 | Q9: 9 | R9: 7.3 | S9: =IF($O9<=PERCENTILE($O$2:$O$29,0.5),"inclusion","-") -> - | T9: =IF($O9<=PERCENTILE($O$2:$O$29,0.2),"inclusion","-") -> - | U9: =IF($O9<=PERCENTILE($O$2:$O$29,0.1),"inclusion","-") -> - | W9: =IF($P9<=PERCENTILE($P$2:$P$29,0.6),"inclusion","-") -> - | X9: =IF($P9<=PERCENTILE($P$2:$P$29,0.3),"inclusion","-") -> - | Y9: =IF($P9<=PERCENTILE($P$2:$P$29,0.2),"inclusion","-") -> -
A10: AI | B10: L'Air Liquide S.A. | C10: {=_xlfn.IFS( AND(S10="inclusion",T10="-",U10="-"),"50%", AND(S10="inclusion",T10="inclusion",U10="-"),"20%", AND(S10="inclusion",T10="inclusion",U10="inclusion"),"10%", AND(S10="-",T10="-",U10="-")," ")} -> 50% | D10: 101.14B | E10: 175.98 | F10: 0.34% | G10: Specialty Chemicals | H10: 63.421 | I10: 29.58 | J10: 64.124 | K10: 6.70% | L10: 12.70B | M10: 49.34B | N10: 27.40B | O10: 13.8 | P10: 9.2 | Q10: 3.4 | R10: 1.2 | S10: =IF($O10<=PERCENTILE($O$2:$O$29,0.5),"inclusion","-") -> inclusion | T10: =IF($O10<=PERCENTILE($O$2:$O$29,0.2),"inclusion","-") -> - | U10: =IF($O10<=PERCENTILE($O$2:$O$29,0.1),"inclusion","-") -> - | W10: =IF($P10<=PERCENTILE($P$2:$P$29,0.6),"inclusion","-") -> - | X10: =IF($P10<=PERCENTILE($P$2:$P$29,0.3),"inclusion","-") -> - | Y10: =IF($P10<=PERCENTILE($P$2:$P$29,0.2),"inclusion","-") -> -
A11: SAN | B11: Sanofi | C11: {=_xlfn.IFS( AND(S11="inclusion",T11="-",U11="-"),"50%", AND(S11="inclusion",T11="inclusion",U11="-"),"20%", AND(S11="inclusion",T11="inclusion",U11="inclusion"),"10%", AND(S11="-",T11="-",U11="-")," ")} | D11: 96.95B | E11: 79.32 | F11: -0.23% | G11: Drug Manufacturers - General | H11: 443.468 | I11: 15.44 | J11: 82.878 | K11: 4.60% | L11: 22.29B | M11: 124.96B | N11: 45.74B | O11: 19 | P11: 2 | Q11: 11.2 | R11: 5.9 | S11: =IF($O11<=PERCENTILE($O$2:$O$29,0.5),"inclusion","-") -> - | T11: =IF($O11<=PERCENTILE($O$2:$O$29,0.2),"inclusion","-") -> - | U11: =IF($O11<=PERCENTILE($O$2:$O$29,0.1),"inclusion","-") -> - | W11: =IF($P11<=PERCENTILE($P$2:$P$29,0.6),"inclusion","-") -> inclusion | X11: =IF($P11<=PERCENTILE($P$2:$P$29,0.3),"inclusion","-") -> inclusion | Y11: =IF($P11<=PERCENTILE($P$2:$P$29,0.2),"inclusion","-") -> -
A12: BNP | B12: BNP Paribas SA | C12: {=_xlfn.IFS( AND(S12="inclusion",T12="-",U12="-"),"50%", AND(S12="inclusion",T12="inclusion",U12="-"),"20%", AND(S12="inclusion",T12="inclusion",U12="inclusion"),"10%", AND(S12="-",T12="-",U12="-")," ")} -> 50% | D12: 85.54B | E12: 76.92 | F12: 0.52% | G12: Banks - Regional | H12: 414.178 | I12: 8.12 | J12: 178 | K12: 0.43% | L12: 756.41B | M12: 2,849.38B | N12: 46.29B | O12: 17.2 | P12: 1.1 | Q12: 9.4 | R12: 6.8 | S12: =IF($O12<=PERCENTILE($O$2:$O$29,0.5),"inclusion","-") -> inclusion | T12: =IF($O12<=PERCENTILE($O$2:$O$29,0.2),"inclusion","-") -> - | U12: =IF($O12<=PERCENTILE($O$2:$O$29,0.1),"inclusion","-") -> - | W12: =IF($P12<=PERCENTILE($P$2:$P$29,0.6),"inclusion","-") -> inclusion | X12: =IF($P12<=PERCENTILE($P$2:$P$29,0.3),"inclusion","-") -> inclusion | Y12: =IF($P12<=PERCENTILE($P$2:$P$29,0.2),"inclusion","-") -> inclusion
A13: CDI | B13: Christian Dior SE | C13: {=_xlfn.IFS( AND(S13="inclusion",T13="-",U13="-"),"50%", AND(S13="inclusion",T13="inclusion",U13="-"),"20%", AND(S13="inclusion",T13="inclusion",U13="inclusion"),"10%", AND(S13="-",T13="-",U13="-")," ")} | D13: 85.15B | E13: 472.80 | F13: 0.17% | G13: Luxury Goods | H13: 886 | I13: 18.70 | J13: 195.83 | K13: 7.80% | L13: 39.72B | M13: 138.72B | N13: 82.82B | O13: 23.7 | P13: 4.2 | Q13: 10.3 | R13: 9.2 | S13: =IF($O13<=PERCENTILE($O$2:$O$29,0.5),"inclusion","-") -> - | T13: =IF($O13<=PERCENTILE($O$2:$O$29,0.2),"inclusion","-") -> - | U13: =IF($O13<=PERCENTILE($O$2:$O$29,0.1),"inclusion","-") -> - | W13: =IF($P13<=PERCENTILE($P$2:$P$29,0.6),"inclusion","-") -> inclusion | X13: =IF($P13<=PERCENTILE($P$2:$P$29,0.3),"inclusion","-") -> - | Y13: =IF($P13<=PERCENTILE($P$2:$P$29,0.2),"inclusion","-") -> -
... A29: CAP | B29: Capgemini SE | C29: {=_xlfn.IFS( AND(S29="inclusion",T29="-",U29="-"),"50%", AND(S29="inclusion",T29="inclusion",U29="-"),"20%", AND(S29="inclusion",T29="inclusion",U29="inclusion"),"10%", AND(S29="-",T29="-",U29="-")," ")} -> 10% | D29: 21.24B | E29: 126.50 | F29: 1.20% | G29: Information Technology Services | H29: 89.185 | I29: 14.09 | J29: 341.12 | K29: 6.23% | L29: 6.07B | M29: 24.38B | N29: 22.07B | O29: 7.6 | P29: 1.7 | Q29: 4.5 | R29: 1.4 | S29: =IF($O29<=PERCENTILE($O$2:$O$29,0.5),"inclusion","-") -> inclusion | T29: =IF($O29<=PERCENTILE($O$2:$O$29,0.2),"inclusion","-") -> inclusion | U29: =IF($O29<=PERCENTILE($O$2:$O$29,0.1),"inclusion","-") -> inclusion | W29: =IF($P29<=PERCENTILE($P$2:$P$29,0.6),"inclusion","-") -> inclusion | X29: =IF($P29<=PERCENTILE($P$2:$P$29,0.3),"inclusion","-") -> inclusion | Y29: =IF($P29<=PERCENTILE($P$2:$P$29,0.2),"inclusion","-") -> -
R32: =PERCENTILE($P$2:$P$29,0.1) -> 1.1
A33: SECTOR INVOBELD
R35: =_xlfn.PERCENTILE.EXC(P2:P29,0.1) -> 1.07

Sheet sector breakdown graph
B3: MC | C3: LVMH Moët Hennessy - Louis Vuitton, Société Européenne | D3: Luxury Goods | H3: Luxury Goods | I3: Specialty Industrial Machinery | J3: Medical Instruments & Supplies | K3: Specialty Chemicals | L3: Banks - Regional | M3: Insurance - Diversified | N3: Packaged Foods | O3: Software - Application | P3: Electrical Equipment & Parts | Q3: Automobiles & Auto Parts | R3: Information Technology Services
B4: RMS | C4: Hermès International Société en commandite par actions | D4: Luxury Goods | H4: =3/14 -> 0.21428571 | I4: =1/14 -> 0.071428571 | J4: =1/14 -> 0.071428571 | K4: =1/14 -> 0.071428571 | L4: =2/14 -> 0.14285714 | M4: =1/14 -> 0.071428571 | N4: =1/14 -> 0.071428571 | O4: =1/14 -> 0.071428571 | P4: =1/14 -> 0.071428571 | Q4: =1/14 -> 0.071428571 | R4: =1/14 -> 0.071428571
B5: SU | C5: Schneider Electric S.E. | D5: Specialty Industrial Machinery
B6: EL | C6: EssilorLuxottica Société anonyme | D6: Medical Instruments & Supplies
B7: AI | C7: L'Air Liquide S.A. | D7: Specialty Chemicals
B8: BNP | C8: BNP Paribas SA | D8: Banks - Regional
B9: CS | C9: AXA SA | D9: Insurance - Diversified
B10: BN | C10: Danone S.A. | D10: Packaged Foods
B11: GLE | C11: Société Générale Société anonyme | D11: Banks - Regional
B12: DSY | C12: Dassault Systèmes SE | D12: Software - Application
B13: LR | C13: Legrand SA | D13: Electrical Equipment & Parts
B14: KER | C14: Kering SA | D14: Luxury Goods
B15: ML | C15: Compagnie Générale des Établissements Michelin Société en commandite par actions | D15: Automobiles & Auto Parts
B16: CAP | C16: Capgemini SE | D16: Information Technology Services

Sheet market cap-color per treshhold
A2: série | B2: Date | D2: CAC40 | E2: MC | F2: OR | G2: RMS | H2: AIR | I2: SU | J2: EL | K2: SAF | L2: TTE | M2: AI | N2: SAN | O2: BNP | P2: CDI | Q2: CS | R2: DG | S2: BN | T2: ACA | U2: HO | V2: SGO | W2: ENGI | X2: GLE | Y2: GLE | Z2: ORA | AA2: DSY | AB2: LR | AC2: KER | AD2: RI | AE2: STLAP | AF2: ML | AG2: CAP | AI2: Date | AJ2: AVG PTF 10% | AK2: AVG PTF 20% | AL2: AVG PTF 50%
A3: 1027 | B3: 12/29/23 | C3: 2023 | D3: 7530.93 | E3: 733.6 | F3: 450.65 | G3: 1918.8 | H3: 139.78 | I3: 181.78 | J3: 181.6 | K3: 159.46 | L3: 61.6 | M3: 160.11 | N3: 89.76 | O3: 62.59 | P3: 707.5 | Q3: 29.49 | R3: 113.7 | S3: 58.68 | T3: 12.85 | U3: 133.95 | V3: 66.66 | W3: 15.92 | X3: 24.03 | Y3: 24.03 | Z3: 10.3 | AA3: 44.24 | AB3: 94.1 | AC3: 399 | AD3: 159.75 | AE3: 21.15 | AF3: 32.46 | AG3: 188.75 | AI3: 12/29/23 | AJ3: =AVERAGE(I3,AC3,AG3) -> 256.51 | AK3: =AVERAGE(G3,AA3,AF3,) -> 498.875 | AL3: =AVERAGE(AB3,X3,S3,Q3,O3,M3,J3,E3,) -> 149.35556 | AQ3: =(AJ1029-AJ3)/AJ3 -> 0.042337531 | AR3: =(AK1029-AK3)/AK3 -> -0.63539464 | AS3: =(AL1029-AL3)/AL3 -> -0.31648564
A4: 1026 | B4: 12/28/23 | C4: 2023 | D4: 7531.71 | E4: 731 | F4: 451.3 | G4: 1910.8 | H4: 139.68 | I4: 181.36 | J4: 180.96 | K4: 159.62 | L4: 61.41 | M4: 160.18 | N4: 89.26 | O4: 62.45 | P4: 705 | Q4: 29.43 | R4: 113.56 | S4: 58.51 | T4: 12.86 | U4: 134.1 | V4: 66.39 | W4: 15.96 | X4: 24.04 | Y4: 24.04 | Z4: 10.31 | AA4: 44.26 | AB4: 94.2 | AC4: 398.25 | AD4: 160.3 | AE4: 21.18 | AF4: 32.36 | AG4: 189.8 | AI4: 12/28/23 | AJ4: =AVERAGE(I4,AC4,AG4) -> 256.47 | AK4: =AVERAGE(G4,AA4,AF4,) -> 496.855 | AL4: =AVERAGE(AB4,X4,S4,Q4,O4,M4,J4,E4,) -> 148.97444
A5: 1025 | B5: 12/27/23 | C5: 2023 | D5: 7560.54 | E5: 735.4 | F5: 448.7 | G5: 1929.6 | H5: 139.42 | I5: 181.9 | J5: 181.2 | K5: 159.96 | L5: 62.47 | M5: 160.75 | N5: 89.17 | O5: 62.99 | P5: 703 | Q5: 29.58 | R5: 114.44 | S5: 58.41 | T5: 12.91 | U5: 134.3 | V5: 66.7 | W5: 16.17 | X5: 24.31 | Y5: 24.31 | Z5: 10.38 | AA5: 44.78 | AB5: 94.62 | AC5: 402.8 | AD5: 161.3 | AE5: 21.24 | AF5: 32.35 | AG5: 191.1 | AI5: 12/27/23 | AJ5: =AVERAGE(I5,AC5,AG5) -> 258.6 | AK5: =AVERAGE(G5,AA5,AF5,) -> 501.6825 | AL5: =AVERAGE(AB5,X5,S5,Q5,O5,M5,J5,E5,) -> 149.69556
A6: 1024 | B6: 12/22/23 | C6: 2023 | D6: 7557.58 | E6: 737.7 | F6: 447.55 | G6: 1941.2 | H6: 139.44 | I6: 180.96 | J6: 181.74 | K6: 159.84 | L6: 62.3 | M6: 161.24 | N6: 89.34 | O6: 63.01 | P6: 707.5 | Q6: 29.64 | R6: 114.38 | S6: 58.32 | T6: 12.85 | U6: 134.4 | V6: 66.63 | W6: 16.16 | X6: 24.08 | Y6: 24.08 | Z6: 10.47 | AA6: 44.64 | AB6: 94.6 | AC6: 397.8 | AD6: 160.8 | AE6: 21.21 | AF6: 32.41 | AG6: 188.45 | AI6: 12/22/23 | AJ6: =AVERAGE(I6,AC6,AG6) -> 255.73667 | AK6: =AVERAGE(G6,AA6,AF6,) -> 504.5625 | AL6: =AVERAGE(AB6,X6,S6,Q6,O6,M6,J6,E6,) -> 150.03667
A7: 1023 | B7: 12/21/23 | C7: 2023 | D7: 7537.81 | E7: 743.4 | F7: 448.2 | G7: 1992.2 | H7: 138.52 | I7: 180.44 | J7: 181.26 | K7: 159.34 | L7: 62 | M7: 160.67 | N7: 88.96 | O7: 62.88 | P7: 715 | Q7: 29.53 | R7: 113.64 | S7: 58.3 | T7: 12.8 | U7: 134.95 | V7: 66.11 | W7: 16.24 | X7: 24.04 | Y7: 24.04 | Z7: 10.45 | AA7: 44.68 | AB7: 95.16 | AC7: 401.65 | AD7: 160.8 | AE7: 21.23 | AF7: 32.52 | AG7: 189.1 | AI7: 12/21/23 | AJ7: =AVERAGE(I7,AC7,AG7) -> 257.06333 | AK7: =AVERAGE(G7,AA7,AF7,) -> 517.35 | AL7: =AVERAGE(AB7,X7,S7,Q7,O7,M7,J7,E7,) -> 150.58222
A8: 1022 | B8: 12/20/23 | C8: 2023 | D8: 7552.29 | E8: 746.9 | F8: 449.25 | G8: 1999 | H8: 137.88 | I8: 181.02 | J8: 181.74 | K8: 158.12 | L8: 62.15 | M8: 161.33 | N8: 89.17 | O8: 62.86 | P8: 715 | Q8: 29.38 | R8: 113.62 | S8: 58.12 | T8: 12.87 | U8: 133.85 | V8: 66.37 | W8: 16.22 | X8: 24.05 | Y8: 24.05 | Z8: 10.46 | AA8: 44.73 | AB8: 94.86 | AC8: 406.45 | AD8: 161.65 | AE8: 21.22 | AF8: 32.45 | AG8: 190.05 | AI8: 12/20/23 | AJ8: =AVERAGE(I8,AC8,AG8) -> 259.17333 | AK8: =AVERAGE(G8,AA8,AF8,) -> 519.045 | AL8: =AVERAGE(AB8,X8,S8,Q8,O8,M8,J8,E8,) -> 151.02667
A9: 1021 | B9: 12/19/23 | C9: 2023 | D9: 7553.08 | E9: 745.5 | F9: 450.75 | G9: 1996.6 | H9: 139.88 | I9: 180.44 | J9: 183.18 | K9: 160.2 | L9: 61.99 | M9: 160.47 | N9: 88.93 | O9: 62.29 | P9: 716 | Q9: 29.33 | R9: 113.3 | S9: 57.88 | T9: 12.78 | U9: 134.8 | V9: 65.62 | W9: 16.05 | X9: 23.97 | Y9: 23.97 | Z9: 10.38 | AA9: 44.39 | AB9: 94.5 | AC9: 405.95 | AD9: 162.1 | AE9: 21.29 | AF9: 32.16 | AG9: 191 | AI9: 12/19/23 | AJ9: =AVERAGE(I9,AC9,AG9) -> 259.13 | AK9: =AVERAGE(G9,AA9,AF9,) -> 518.2875 | AL9: =AVERAGE(AB9,X9,S9,Q9,O9,M9,J9,E9,) -> 150.79111
A10: 1020 | B10: 12/18/23 | C10: 2023 | D10: 7548.18 | E10: 741.8 | F10: 447.45 | G10: 1996.8 | H10: 139.18 | I10: 181.02 | J10: 183.76 | K10: 160.76 | L10: 62.35 | M10: 159.98 | N10: 88.61 | O10: 62.39 | P10: 714.5 | Q10: 29.11 | R10: 112.96 | S10: 58.27 | T10: 12.83 | U10: 135.3 | V10: 65.02 | W10: 16.09 | X10: 24.19 | Y10: 24.19 | Z10: 10.45 | AA10: 44.19 | AB10: 96.18 | AC10: 407.35 | AD10: 162.05 | AE10: 21.5 | AF10: 32.17 | AG10: 192.45 | AI10: 12/18/23 | AJ10: =AVERAGE(I10,AC10,AG10) -> 260.27333 | AK10: =AVERAGE(G10,AA10,AF10,) -> 518.29 | AL10: =AVERAGE(AB10,X10,S10,Q10,O10,M10,J10,E10,) -> 150.63111
A11: 1019 | B11: 12/15/23 | C11: 2023 | D11: 7587.68 | E11: 748.4 | F11: 446.55 | G11: 2023.5 | H11: 139.52 | I11: 181.14 | J11: 185.24 | K11: 160.16 | L11: 61.63 | M11: 159.98 | N11: 87.7 | O11: 63.09 | P11: 717.5 | Q11: 29.17 | R11: 115.58 | S11: 57.98 | T11: 12.93 | U11: 134.9 | V11: 66.61 | W11: 16.21 | X11: 24.43 | Y11: 24.43 | Z11: 10.56 | AA11: 44.29 | AB11: 96.9 | AC11: 417.85 | AD11: 163.05 | AE11: 21.53 | AF11: 32.26 | AG11: 195.9 | AI11: 12/15/23 | AJ11: =AVERAGE(I11,AC11,AG11) -> 264.96333 | AK11: =AVERAGE(G11,AA11,AF11,) -> 525.0125 | AL11: =AVERAGE(AB11,X11,S11,Q11,O11,M11,J11,E11,) -> 151.68778
A12: 1018 | B12: 12/14/23 | C12: 2023 | D12: 7547 | E12: 746.8 | F12: 443.55 | G12: 2017 | H12: 140.06 | I12: 179 | J12: 185.08 | K12: 160.78 | L12: 61.41 | M12: 159.18 | N12: 88.02 | O12: 62.88 | P12: 722 | Q12: 29.26 | R12: 116.02 | S12: 58.2 | T12: 12.9 | U12: 134.55 | V12: 66.1 | W12: 16.27 | X12: 24.49 | Y12: 24.49 | Z12: 10.67 | AA12: 43.82 | AB12: 96.5 | AC12: 427.05 | AD12: 162.65 | AE12: 21.25 | AF12: 32.04 | AG12: 193.15 | AI12: 12/14/23 | AJ12: =AVERAGE(I12,AC12,AG12) -> 266.4 | AK12: =AVERAGE(G12,AA12,AF12,) -> 523.215 | AL12: =AVERAGE(AB12,X12,S12,Q12,O12,M12,J12,E12,) -> 151.37667
A13: 1017 | B13: 12/13/23 | C13: 2023 | D13: 7529.11 | E13: 734.5 | F13: 445.45 | G13: 2027 | H13: 142.3 | I13: 176.56 | J13: 185.42 | K13: 165.72 | L13: 61.36 | M13: 162.76 | N13: 88.54 | O13: 60.31 | P13: 709 | Q13: 29.76 | R13: 114.78 | S13: 59.31 | T13: 12.6 | U13: 138.7 | V13: 62.57 | W13: 16.16 | X13: 23.66 | Y13: 23.66 | Z13: 10.8 | AA13: 44.42 | AB13: 94.46 | AC13: 409 | AD13: 155.7 | AE13: 20.91 | AF13: 31.72 | AG13: 191.9 | AI13: 12/13/23 | AJ13: =AVERAGE(I13,AC13,AG13) -> 259.15333 | AK13: =AVERAGE(G13,AA13,AF13,) -> 525.785 | AL13: =AVERAGE(AB13,X13,S13,Q13,O13,M13,J13,E13,) -> 150.02
A14: 1016 | B14: 45272 | C14: 2023 | D14: 7542.53 | E14: 733.6 | F14: 444.7 | G14: 2009.5 | H14: 142.68 | I14: 176.96 | J14: 183.56 | K14: 167.48 | L14: 61.31 | M14: 162.09 | N14: 87.87 | O14: 60.82 | P14: 707.5 | Q14: 30.07 | R14: 115.4 | S14: 59.55 | T14: 12.66 | U14: 137.45 | V14: 63.01 | W14: 15.99 | X14: 23.71 | Y14: 23.71 | Z14: 11.16 | AA14: 44.84 | AB14: 94.8 | AC14: 410.45 | AD14: 155.95 | AE14: 20.98 | AF14: 31.88 | AG14: 193.05 | AI14: 45272 | AJ14: =AVERAGE(I14,AC14,AG14) -> 260.15333 | AK14: =AVERAGE(G14,AA14,AF14,) -> 521.555 | AL14: =AVERAGE(AB14,X14,S14,Q14,O14,M14,J14,E14,) -> 149.8
A15: 1015 | B15: 45242 | C15: 2023 | D15: 7527.58 | E15: 740 | F15: 443.85 | G15: 1997.8 | H15: 142.3 | I15: 176.56 | J15: 183.22 | K15: 165.48 | L15: 61.97 | M15: 160.56 | N15: 87.8 | O15: 61.18 | P15: 710.5 | Q15: 30.06 | R15: 116.1 | S15: 59.48 | T15: 12.65 | U15: 137.4 | V15: 62.47 | W15: 16.13 | X15: 23.82 | Y15: 23.82 | Z15: 11.1 | AA15: 44.4 | AB15: 94.94 | AC15: 409.5 | AD15: 157.05 | AE15: 21.01 | AF15: 32.2 | AG15: 192.9 | AI15: 45242 | AJ15: =AVERAGE(I15,AC15,AG15) -> 259.65333 | AK15: =AVERAGE(G15,AA15,AF15,) -> 518.6 | AL15: =AVERAGE(AB15,X15,S15,Q15,O15,M15,J15,E15,) -> 150.36222
A16: 1014 | B16: 45150 | C16: 2023 | D16: 7437.97 | E16: 739.1 | F16: 441.95 | G16: 1982.4 | H16: 141.82 | I16: 174.94 | J16: 182.7 | K16: 164.6 | L16: 61.9 | M16: 159.38 | N16: 86.13 | O16: 61.85 | P16: 710 | Q16: 30 | R16: 115.84 | S16: 59.22 | T16: 12.61 | U16: 138.95 | V16: 61.86 | W16: 16.23 | X16: 24.04 | Y16: 24.04 | Z16: 11.09 | AA16: 44.22 | AB16: 93.88 | AC16: 413.8 | AD16: 159.25 | AE16: 21.02 | AF16: 31.92 | AG16: 192.15 | AI16: 45150 | AJ16: =AVERAGE(I16,AC16,AG16) -> 260.29667 | AK16: =AVERAGE(G16,AA16,AF16,) -> 514.635 | AL16: =AVERAGE(AB16,X16,S16,Q16,O16,M16,J16,E16,) -> 150.01889
A17: 1013 | B17: 45119 | C17: 2023 | D17: 7415.66 | E17: 715.6 | F17: 438.75 | G17: 1953.4 | H17: 138.36 | I17: 172.7 | J17: 181.06 | K17: 164.12 | L17: 60.67 | M17: 158.09 | N17: 85.1 | O17: 61.11 | P17: 687.5 | Q17: 29.9 | R17: 115.68 | S17: 59.14 | T17: 12.45 | U17: 135.5 | V17: 61.21 | W17: 16.17 | X17: 23.7 | Y17: 23.7 | Z17: 11.14 | AA17: 43.83 | AB17: 92 | AC17: 403.4 | AD17: 157.55 | AE17: 20.92 | AF17: 31.83 | AG17: 190.5 | AI17: 45119 | AJ17: =AVERAGE(I17,AC17,AG17) -> 255.53333 | AK17: =AVERAGE(G17,AA17,AF17,) -> 507.265 | AL17: =AVERAGE(AB17,X17,S17,Q17,O17,M17,J17,E17,) -> 146.73333
A18: 1012 | B18: 45089 | C18: 2023 | D18: 7384.99 | E18: 718.6 | F18: 441.4 | G18: 1957.2 | H18: 138.3 | I18: 172.6 | J18: 180.46 | K18: 163.98 | L18: 60.65 | M18: 157.69 | N18: 86.13 | O18: 60.66 | P18: 690 | Q18: 29.67 | R18: 115.68 | S18: 58.72 | T18: 12.37 | U18: 136.2 | V18: 61.2 | W18: 16.09 | X18: 23.57 | Y18: 23.57 | Z18: 11.13 | AA18: 43.99 | AB18: 91.6 | AC18: 404.3 | AD18: 158.3 | AE18: 21.04 | AF18: 31.6 | AG18: 190.35 | AI18: 45089 | AJ18: =AVERAGE(I18,AC18,AG18) -> 255.75 | AK18: =AVERAGE(G18,AA18,AF18,) -> 508.1975 | AL18: =AVERAGE(AB18,X18,S18,Q18,O18,M18,J18,E18,) -> 146.77444
A19: 1011 | B19: 45058 | C19: 2023 | D19: 7320.49 | E19: 713.2 | F19: 439.75 | G19: 1933.2 | H19: 136.56 | I19: 170.02 | J19: 179.66 | K19: 160.48 | L19: 61.37 | M19: 158.58 | N19: 86.4 | O19: 59.76 | P19: 684.5 | Q19: 29.27 | R19: 115.3 | S19: 58.62 | T19: 12.17 | U19: 135.4 | V19: 60.6 | W19: 15.99 | X19: 23.32 | Y19: 23.32 | Z19: 11.17 | AA19: 43.54 | AB19: 89.78 | AC19: 398.6 | AD19: 159.2 | AE19: 20.45 | AF19: 31.4 | AG19: 189.05 | AI19: 45058 | AJ19: =AVERAGE(I19,AC19,AG19) -> 252.55667 | AK19: =AVERAGE(G19,AA19,AF19,) -> 502.035 | AL19: =AVERAGE(AB19,X19,S19,Q19,O19,M19,J19,E19,) -> 145.79889
A20: 1010 | B20: 45028 | C20: 2023 | D20: 7313.71 | E20: 698.7 | F20: 436.9 | G20: 1917.4 | H20: 137.02 | I20: 168.08 | J20: 178.06 | K20: 161.26 | L20: 61.39 | M20: 156.62 | N20: 86.59 | O20: 58.47 | P20: 672.5 | Q20: 29.05 | R20: 113.38 | S20: 58.79 | T20: 12.13 | U20: 136.6 | V20: 59.54 | W20: 16.05 | X20: 23.08 | Y20: 23.08 | Z20: 11.12 | AA20: 43.13 | AB20: 88.64 | AC20: 400.05 | AD20: 158.5 | AE20: 20.3 | AF20: 31.02 | AG20: 186.9 | AI20: 45028 | AJ20: =AVERAGE(I20,AC20,AG20) -> 251.67667 | AK20: =AVERAGE(G20,AA20,AF20,) -> 497.8875 | AL20: =AVERAGE(AB20,X20,S20,Q20,O20,M20,J20,E20,) -> 143.49
A21: 1009 | B21: 44938 | C21: 2023 | D21: 7313.19 | E21: 699.2 | F21: 436.15 | G21: 1915.2 | H21: 138.08 | I21: 169.8 | J21: 178.12 | K21: 163.14 | L21: 62.36 | M21: 157.45 | N21: 85.78 | O21: 57.8 | P21: 676 | Q21: 28.9 | R21: 113.32 | S21: 58.59 | T21: 12.07 | U21: 139.15 | V21: 59.83 | W21: 16.05 | X21: 22.9 | Y21: 22.9 | Z21: 11.38 | AA21: 43.31 | AB21: 89.42 | AC21: 392.9 | AD21: 158.15 | AE21: 20.09 | AF21: 31.05 | AG21: 187 | AI21: 44938 | AJ21: =AVERAGE(I21,AC21,AG21) -> 249.9 | AK21: =AVERAGE(G21,AA21,AF21,) -> 497.39 | AL21: =AVERAGE(AB21,X21,S21,Q21,O21,M21,J21,E21,) -> 143.59778
A22: 1008 | B22: 11/30/23 | C22: 2023 | D22: 7255.04 | E22: 702.7 | F22: 431.05 | G22: 1904.2 | H22: 136.2 | I22: 168.62 | J22: 175.12 | K22: 161.02 | L22: 62.26 | M22: 158 | N22: 85.46 | O22: 57.77 | P22: 676.5 | Q22: 28.6 | R22: 112.3 | S22: 58.97 | T22: 12.02 | U22: 136.95 | V22: 59.81 | W22: 15.92 | X22: 23.08 | Y22: 23.08 | Z22: 11.3 | AA22: 42.97 | AB22: 88.42 | AC22: 393.7 | AD22: 158.55 | AE22: 19.91 | AF22: 30.81 | AG22: 188 | AI22: 11/30/23 | AJ22: =AVERAGE(I22,AC22,AG22) -> 250.10667 | AK22: =AVERAGE(G22,AA22,AF22,) -> 494.495 | AL22: =AVERAGE(AB22,X22,S22,Q22,O22,M22,J22,E22,) -> 143.62889
A23: 1007 | B23: 11/29/23 | C23: 2023 | D23: 7241.41 | E23: 690.5 | F23: 431.85 | G23: 1897 | H23: 135.56 | I23: 167.2 | J23: 177.24 | K23: 160.14 | L23: 61.68 | M23: 157.96 | N23: 84.87 | O23: 56.92 | P23: 670 | Q23: 28.44 | R23: 112.12 | S23: 59.15 | T23: 11.8 | U23: 138.65 | V23: 59.42 | W23: 15.87 | X23: 22.74 | Y23: 22.74 | Z23: 11.26 | AA23: 43.13 | AB23: 88.16 | AC23: 391 | AD23: 155.75 | AE23: 19.7 | AF23: 30.84 | AG23: 188.55 | AI23: 11/29/23 | AJ23: =AVERAGE(I23,AC23,AG23) -> 248.91667 | AK23: =AVERAGE(G23,AA23,AF23,) -> 492.7425 | AL23: =AVERAGE(AB23,X23,S23,Q23,O23,M23,J23,E23,) -> 142.34556
A24: 1006 | B24: 11/28/23 | C24: 2023 | D24: 7213.74 | E24: 684.5 | F24: 430.7 | G24: 1911.8 | H24: 134.56 | I24: 166.04 | J24: 176.58 | K24: 161.2 | L24: 63.19 | M24: 158.51 | N24: 85.76 | O24: 56.48 | P24: 664.5 | Q24: 28.48 | R24: 111.12 | S24: 59.05 | T24: 11.75 | U24: 138.35 | V24: 58.51 | W24: 15.92 | X24: 22.52 | Y24: 22.52 | Z24: 11.3 | AA24: 42.82 | AB24: 88.76 | AC24: 394.05 | AD24: 158.05 | AE24: 18.72 | AF24: 30.11 | AG24: 182.6 | AI24: 11/28/23 | AJ24: =AVERAGE(I24,AC24,AG24) -> 247.56333 | AK24: =AVERAGE(G24,AA24,AF24,) -> 496.1825 | AL24: =AVERAGE(AB24,X24,S24,Q24,O24,M24,J24,E24,) -> 141.65333
A25: 1005 | B25: 11/27/23 | C25: 2023 | D25: 7265.49 | E25: 697.3 | F25: 432.95 | G25: 1951 | H25: 133.6 | I25: 165.7 | J25: 177 | K25: 159.78 | L25: 62.86 | M25: 157.98 | N25: 86.63 | O25: 56.42 | P25: 680 | Q25: 28.36 | R25: 110.54 | S25: 59.08 | T25: 11.73 | U25: 137.45 | V25: 58.02 | W25: 15.84 | X25: 22.49 | Y25: 22.49 | Z25: 11.24 | AA25: 42.64 | AB25: 88.74 | AC25: 404.5 | AD25: 162.35 | AE25: 18.73 | AF25: 29.81 | AG25: 181.2 | AI25: 11/27/23 | AJ25: =AVERAGE(I25,AC25,AG25) -> 250.46667 | AK25: =AVERAGE(G25,AA25,AF25,) -> 505.8625 | AL25: =AVERAGE(AB25,X25,S25,Q25,O25,M25,J25,E25,) -> 143.04111
A26: 1004 | B26: 11/24/23 | C26: 2023 | D26: 7268.58 | E26: 706.9 | F26: 431.45 | G26: 1951.2 | H26: 134.66 | I26: 166.28 | J26: 178.04 | K26: 161.02 | L26: 63.14 | M26: 157.87 | N26: 86.38 | O26: 57.03 | P26: 686 | Q26: 28.46 | R26: 110.48 | S26: 59.12 | T26: 11.75 | U26: 140.55 | V26: 58.23 | W26: 15.75 | X26: 22.69 | Y26: 22.69 | Z26: 11.17 | AA26: 42.63 | AB26: 88.92 | AC26: 406.45 | AD26: 163.95 | AE26: 18.79 | AF26: 29.9 | AG26: 182.05 | AI26: 11/24/23 | AJ26: =AVERAGE(I26,AC26,AG26) -> 251.59333 | AK26: =AVERAGE(G26,AA26,AF26,) -> 505.9325 | AL26: =AVERAGE(AB26,X26,S26,Q26,O26,M26,J26,E26,) -> 144.33667
A27: 1003 | B27: 11/23/23 | C27: 2023 | D27: 7263.67 | E27: 711.6 | F27: 429.25 | G27: 1959.8 | H27: 134.58 | I27: 164.7 | J27: 177.74 | K27: 160.9 | L27: 62.81 | M27: 157.22 | N27: 86.24 | O27: 56.9 | P27: 691 | Q27: 28.24 | R27: 109.98 | S27: 58.66 | T27: 11.7 | U27: 140.5 | V27: 57.86 | W27: 15.72 | X27: 22.58 | Y27: 22.58 | Z27: 11.12 | AA27: 42.84 | AB27: 88.08 | AC27: 405.95 | AD27: 167.3 | AE27: 18.67 | AF27: 29.85 | AG27: 182.55 | AI27: 11/23/23 | AJ27: =AVERAGE(I27,AC27,AG27) -> 251.06667 | AK27: =AVERAGE(G27,AA27,AF27,) -> 508.1225 | AL27: =AVERAGE(AB27,X27,S27,Q27,O27,M27,J27,E27,) -> 144.55778
A28: 1002 | B28: 11/22/23 | C28: 2023 | D28: 7243.83 | E28: 712.3 | F28: 429.65 | G28: 1974 | H28: 134 | I28: 165.24 | J28: 178.92 | K28: 160.9 | L28: 61.85 | M28: 157.13 | N28: 84.92 | O28: 56.58 | P28: 688.5 | Q28: 28.24 | R28: 109.72 | S28: 58.55 | T28: 11.73 | U28: 140.65 | V28: 58.25 | W28: 15.59 | X28: 22.42 | Y28: 22.42 | Z28: 11.08 | AA28: 42.78 | AB28: 88.14 | AC28: 403.8 | AD28: 168.3 | AE28: 18.56 | AF28: 29.82 | AG28: 183.2 | AI28: 11/22/23 | AJ28: =AVERAGE(I28,AC28,AG28) -> 250.74667 | AK28: =AVERAGE(G28,AA28,AF28,) -> 511.65 | AL28: =AVERAGE(AB28,X28,S28,Q28,O28,M28,J28,E28,) -> 144.69778
A29: 1001 | B29: 11/21/23 | C29: 2023 | D29: 7214.39 | E29: 704.1 | F29: 425.65 | G29: 1950.2 | H29: 133.76 | I29: 163.88 | J29: 176.98 | K29: 160.96 | L29: 62.95 | M29: 155.98 | N29: 85.34 | O29: 56.46 | P29: 682.5 | Q29: 28.2 | R29: 109 | S29: 58.19 | T29: 11.75 | U29: 140.1 | V29: 57.82 | W29: 15.54 | X29: 22.41 | Y29: 22.41 | Z29: 11.04 | AA29: 42.46 | AB29: 87.58 | AC29: 399.45 | AD29: 165.95 | AE29: 18.53 | AF29: 29.48 | AG29: 177.75 | AI29: 11/21/23 | AJ29: =AVERAGE(I29,AC29,AG29) -> 247.02667 | AK29: =AVERAGE(G29,AA29,AF29,) -> 505.535 | AL29: =AVERAGE(AB29,X29,S29,Q29,O29,M29,J29,E29,) -> 143.32222
A30: 1000 | B30: 11/20/23 | C30: 2023 | D30: 7236.02 | E30: 717.7 | F30: 421.75 | G30: 1941.6 | H30: 133.04 | I30: 163.3 | J30: 176.58 | K30: 160.7 | L30: 63 | M30: 154.96 | N30: 85.42 | O30: 56.8 | P30: 692 | Q30: 28.34 | R30: 108.96 | S30: 57.43 | T30: 11.8 | U30: 138.35 | V30: 57.8 | W30: 15.61 | X30: 22.62 | Y30: 22.62 | Z30: 11.03 | AA30: 42.55 | AB30: 87.32 | AC30: 403.2 | AD30: 165.65 | AE30: 18.89 | AF30: 29.73 | AG30: 179.3 | AI30: 11/20/23 | AJ30: =AVERAGE(I30,AC30,AG30) -> 248.6 | AK30: =AVERAGE(G30,AA30,AF30,) -> 503.47 | AL30: =AVERAGE(AB30,X30,S30,Q30,O30,M30,J30,E30,) -> 144.63889
A31: 999 | B31: 11/17/23 | C31: 2023 | D31: 7196.69 | E31: 711.6 | F31: 423.95 | G31: 1924.6 | H31: 132.26 | I31: 166.02 | J31: 179.38 | K31: 160.56 | L31: 61.81 | M31: 154.78 | N31: 85.89 | O31: 56.73 | P31: 687 | Q31: 28.39 | R31: 109.38 | S31: 57.54 | T31: 11.77 | U31: 138.15 | V31: 58.37 | W31: 15.6 | X31: 22.61 | Y31: 22.61 | Z31: 11.08 | AA31: 42.05 | AB31: 87.56 | AC31: 404.3 | AD31: 167.35 | AE31: 18.46 | AF31: 29.65 | AG31: 177.9 | AI31: 11/17/23 | AJ31: =AVERAGE(I31,AC31,AG31) -> 249.40667 | AK31: =AVERAGE(G31,AA31,AF31,) -> 499.075 | AL31: =AVERAGE(AB31,X31,S31,Q31,O31,M31,J31,E31,) -> 144.28778
A32: 998 | B32: 11/16/23 | C32: 2023 | D32: 7168.4 | E32: 706.1 | F32: 421 | G32: 1923 | H32: 131.46 | I32: 164.06 | J32: 177.88 | K32: 159.02 | L32: 60.96 | M32: 153.55 | N32: 84.82 | O32: 56.09 | P32: 679 | Q32: 27.98 | R32: 108.36 | S32: 57.4 | T32: 11.66 | U32: 136.85 | V32: 57.35 | W32: 15.52 | X32: 22.28 | Y32: 22.28 | Z32: 10.99 | AA32: 41.66 | AB32: 86.9 | AC32: 399.1 | AD32: 166.55 | AE32: 18.5 | AF32: 29.25 | AG32: 177.75 | AI32: 11/16/23 | AJ32: =AVERAGE(I32,AC32,AG32) -> 246.97 | AK32: =AVERAGE(G32,AA32,AF32,) -> 498.4775 | AL32: =AVERAGE(AB32,X32,S32,Q32,O32,M32,J32,E32,) -> 143.13111
A33: 997 | B33: 11/15/23 | C33: 2023 | D33: 7198.91 | E33: 719 | F33: 423.9 | G33: 1931 | H33: 131.2 | I33: 164.46 | J33: 178.18 | K33: 157.7 | L33: 62.61 | M33: 152.75 | N33: 83.65 | O33: 56.37 | P33: 696.5 | Q33: 27.87 | R33: 109.04 | S33: 57.53 | T33: 11.69 | U33: 137.2 | V33: 57.73 | W33: 15.32 | X33: 22.25 | Y33: 22.25 | Z33: 10.91 | AA33: 41.94 | AB33: 86.54 | AC33: 410.15 | AD33: 168.35 | AE33: 18.88 | AF33: 29.57 | AG33: 175 | AI33: 11/15/23 | AJ33: =AVERAGE(I33,AC33,AG33) -> 249.87 | AK33: =AVERAGE(G33,AA33,AF33,) -> 500.6275 | AL33: =AVERAGE(AB33,X33,S33,Q33,O33,M33,J33,E33,) -> 144.49889
... A35: 995 | B35: 11/13/23 | C35: 2023 | D35: 7056.09 | E35: 688.5 | F35: 414.65 | G35: 1858 | H35: 130.24 | I35: 160.74 | J35: 176.76 | K35: 155.1 | L35: 62.79 | M35: 152.42 | N35: 85.29 | O35: 55.79 | P35: 669.5 | Q35: 28.05 | R35: 107.1 | S35: 58.03 | T35: 11.74 | U35: 141.1 | V35: 54.47 | W35: 15.32 | X35: 21.66 | Y35: 21.66 | Z35: 11.09 | AA35: 40.69 | AB35: 83.48 | AC35: 393.75 | AD35: 164.4 | AE35: 18.32 | AF35: 28.69 | AG35: 172.45 | AI35: 11/13/23 | AJ35: =AVERAGE(I35,AC35,AG35) -> 242.31333 | AK35: =AVERAGE(G35,AA35,AF35,) -> 481.845 | AL35: =AVERAGE(AB35,X35,S35,Q35,O35,M35,J35,E35,) -> 140.52111
A36: 994 | B36: 45210 | C36: 2023 | D36: 7006.09 | E36: 687.1 | F36: 414.25 | G36: 1845.4 | H36: 128.48 | I36: 160.8 | J36: 174.9 | K36: 153.08 | L36: 62.04 | M36: 151.45 | N36: 85.14 | O36: 55.61 | P36: 670 | Q36: 27.73 | R36: 106.56 | S36: 57.37 | T36: 11.71 | U36: 138.6 | V36: 54.23 | W36: 15.3 | X36: 21.26 | Y36: 21.26 | Z36: 11.05 | AA36: 40.49 | AB36: 83.6 | AC36: 393.1 | AD36: 164.3 | AE36: 17.99 | AF36: 28.48 | AG36: 171.85 | AI36: 45210 | AJ36: =AVERAGE(I36,AC36,AG36) -> 241.91667 | AK36: =AVERAGE(G36,AA36,AF36,) -> 478.5925 | AL36: =AVERAGE(AB36,X36,S36,Q36,O36,M36,J36,E36,) -> 139.89111
A37: 993 | B37: 45180 | C37: 2023 | D37: 7025.61 | E37: 714.4 | F37: 419 | G37: 1874.6 | H37: 127.86 | I37: 163.36 | J37: 175.44 | K37: 153.5 | L37: 61.36 | M37: 151.02 | N37: 86.08 | O37: 56.09 | P37: 692.5 | Q37: 27.68 | R37: 106.56 | S37: 57.38 | T37: 11.72 | U37: 137.1 | V37: 54.49 | W37: 15.31 | X37: 21.39 | Y37: 21.39 | Z37: 11.03 | AA37: 40.68 | AB37: 84.8 | AC37: 406.65 | AD37: 174.35 | AE37: 18.14 | AF37: 28.57 | AG37: 173.25 | AI37: 45180 | AJ37: =AVERAGE(I37,AC37,AG37) -> 247.75333 | AK37: =AVERAGE(G37,AA37,AF37,) -> 485.9625 | AL37: =AVERAGE(AB37,X37,S37,Q37,O37,M37,J37,E37,) -> 143.13333
A38: 992 | B38: 45149 | C38: 2023 | D38: 6950.95 | E38: 703.5 | F38: 415.45 | G38: 1851 | H38: 130.38 | I38: 150.9 | J38: 174 | K38: 152.38 | L38: 60.78 | M38: 148.56 | N38: 86.13 | O38: 56.1 | P38: 687.5 | Q38: 27.72 | R38: 105.66 | S38: 56.91 | T38: 11.72 | U38: 137.4 | V38: 53.13 | W38: 15.14 | X38: 21.42 | Y38: 21.42 | Z38: 10.97 | AA38: 40.05 | AB38: 82.24 | AC38: 403.25 | AD38: 172.2 | AE38: 18.32 | AF38: 28.34 | AG38: 171.6 | AI38: 45149 | AJ38: =AVERAGE(I38,AC38,AG38) -> 241.91667 | AK38: =AVERAGE(G38,AA38,AF38,) -> 479.8475 | AL38: =AVERAGE(AB38,X38,S38,Q38,O38,M38,J38,E38,) -> 141.16111
A39: 991 | B39: 45118 | C39: 2023 | D39: 6963.88 | E39: 697.5 | F39: 405.45 | G39: 1814.6 | H39: 129.2 | I39: 149.42 | J39: 172.9 | K39: 150.2 | L39: 61.24 | M39: 147.82 | N39: 84.42 | O39: 55.95 | P39: 678.5 | Q39: 27.43 | R39: 105.2 | S39: 56.85 | T39: 11.59 | U39: 136 | V39: 53.04 | W39: 15.3 | X39: 21.48 | Y39: 21.48 | Z39: 10.97 | AA39: 39.99 | AB39: 83.34 | AC39: 400.05 | AD39: 171.1 | AE39: 18.09 | AF39: 27.95 | AG39: 173 | AI39: 45118 | AJ39: =AVERAGE(I39,AC39,AG39) -> 240.82333 | AK39: =AVERAGE(G39,AA39,AF39,) -> 470.635 | AL39: =AVERAGE(AB39,X39,S39,Q39,O39,M39,J39,E39,) -> 140.36333
A40: 990 | B40: 45088 | C40: 2023 | D40: 7006.53 | E40: 697.2 | F40: 403.15 | G40: 1812.4 | H40: 128.42 | I40: 149.24 | J40: 172.66 | K40: 150 | L40: 62.66 | M40: 148.58 | N40: 84.94 | O40: 56.81 | P40: 677.5 | Q40: 27.83 | R40: 105.5 | S40: 56.84 | T40: 11.67 | U40: 136.75 | V40: 53.33 | W40: 15.14 | X40: 21.67 | Y40: 21.67 | Z40: 11.1 | AA40: 39.92 | AB40: 82.92 | AC40: 398.7 | AD40: 172.35 | AE40: 18.34 | AF40: 28.22 | AG40: 168.75 | AI40: 45088 | AJ40: =AVERAGE(I40,AC40,AG40) -> 238.89667 | AK40: =AVERAGE(G40,AA40,AF40,) -> 470.135 | AL40: =AVERAGE(AB40,X40,S40,Q40,O40,M40,J40,E40,) -> 140.50111
A41: 989 | B41: 44996 | C41: 2023 | D41: 7046.86 | E41: 702.8 | F41: 403.7 | G41: 1814.6 | H41: 129.06 | I41: 150.7 | J41: 174.24 | K41: 150.06 | L41: 62.33 | M41: 148.35 | N41: 85.35 | O41: 56.64 | P41: 680.5 | Q41: 28.17 | R41: 106.38 | S41: 57.05 | T41: 11.68 | U41: 135.1 | V41: 54.27 | W41: 15.15 | X41: 21.8 | Y41: 21.8 | Z41: 11.14 | AA41: 39.44 | AB41: 83.5 | AC41: 407.25 | AD41: 173.45 | AE41: 18.7 | AF41: 28.24 | AG41: 173.55 | AI41: 44996 | AJ41: =AVERAGE(I41,AC41,AG41) -> 243.83333 | AK41: =AVERAGE(G41,AA41,AF41,) -> 470.57 | AL41: =AVERAGE(AB41,X41,S41,Q41,O41,M41,J41,E41,) -> 141.39444
A42: 988 | B42: 44968 | C42: 2023 | D42: 6982.04 | E42: 701.1 | F42: 403.25 | G42: 1819.2 | H42: 129.06 | I42: 149.48 | J42: 175.58 | K42: 151.86 | L42: 64.59 | M42: 150 | N42: 87.2 | O42: 55.56 | P42: 676 | Q42: 28.52 | R42: 106.18 | S42: 57.11 | T42: 11.55 | U42: 137.45 | V42: 53.26 | W42: 15.16 | X42: 21.62 | Y42: 21.62 | Z42: 11.2 | AA42: 39.05 | AB42: 83.24 | AC42: 395.8 | AD42: 172.05 | AE42: 18.35 | AF42: 28.29 | AG42: 171.5 | AI42: 44968 | AJ42: =AVERAGE(I42,AC42,AG42) -> 238.92667 | AK42: =AVERAGE(G42,AA42,AF42,) -> 471.635 | AL42: =AVERAGE(AB42,X42,S42,Q42,O42,M42,J42,E42,) -> 141.41444
A43: 987 | B43: 44937 | C43: 2023 | D43: 6873.55 | E43: 675.3 | F43: 397 | G43: 1773.8 | H43: 127.94 | I43: 145.22 | J43: 171.42 | K43: 149.78 | L43: 63.63 | M43: 148.05 | N43: 86.85 | O43: 54.4 | P43: 651.5 | Q43: 28.29 | R43: 105.36 | S43: 57.17 | T43: 11.42 | U43: 138.35 | V43: 51.51 | W43: 15.35 | X43: 21.22 | Y43: 21.22 | Z43: 11.19 | AA43: 39 | AB43: 81.9 | AC43: 382 | AD43: 168.1 | AE43: 17.93 | AF43: 27.92 | AG43: 167.65 | AI43: 44937 | AJ43: =AVERAGE(I43,AC43,AG43) -> 231.62333 | AK43: =AVERAGE(G43,AA43,AF43,) -> 460.18 | AL43: =AVERAGE(AB43,X43,S43,Q43,O43,M43,J43,E43,) -> 137.52778
A44: 986 | B44: 10/31/23 | C44: 2023 | D44: 6831.67 | E44: 674.5 | F44: 396.15 | G44: 1759.6 | H44: 126.28 | I44: 144.98 | J44: 170.64 | K44: 147.02 | L44: 63.2 | M44: 146.98 | N44: 85.7 | O44: 54.29 | P44: 652 | Q44: 27.96 | R44: 104.48 | S44: 56.15 | T44: 11.38 | U44: 139.15 | V44: 51.4 | W44: 15 | X44: 21.15 | Y44: 21.15 | Z44: 11.11 | AA44: 38.82 | AB44: 81.48 | AC44: 383.2 | AD44: 167.5 | AE44: 17.61 | AF44: 28.02 | AG44: 166.5 | AI44: 10/31/23 | AJ44: =AVERAGE(I44,AC44,AG44) -> 231.56 | AK44: =AVERAGE(G44,AA44,AF44,) -> 456.61 | AL44: =AVERAGE(AB44,X44,S44,Q44,O44,M44,J44,E44,) -> 137.01667
A45: 985 | B45: 10/30/23 | C45: 2023 | D45: 6809.84 | E45: 671 | F45: 392.05 | G45: 1752.4 | H45: 126.2 | I45: 142.84 | J45: 168.28 | K45: 148.1 | L45: 62.99 | M45: 145.25 | N45: 84.14 | O45: 53.72 | P45: 647.5 | Q45: 27.84 | R45: 103.08 | S45: 55.7 | T45: 11.23 | U45: 141.1 | V45: 51.3 | W45: 14.99 | X45: 20.81 | Y45: 20.81 | Z45: 11.06 | AA45: 38.72 | AB45: 81.54 | AC45: 383 | AD45: 166.2 | AE45: 17.05 | AF45: 28 | AG45: 161.7 | AI45: 10/30/23 | AJ45: =AVERAGE(I45,AC45,AG45) -> 229.18 | AK45: =AVERAGE(G45,AA45,AF45,) -> 454.78 | AL45: =AVERAGE(AB45,X45,S45,Q45,O45,M45,J45,E45,) -> 136.01556
A46: 984 | B46: 10/27/23 | C46: 2023 | D46: 6784.62 | E46: 661.4 | F46: 390.55 | G46: 1748.8 | H46: 124.96 | I46: 143.06 | J46: 168.02 | K46: 146.66 | L46: 63 | M46: 145.67 | N46: 81.44 | O46: 54.67 | P46: 636.5 | Q46: 27.46 | R46: 102 | S46: 55.17 | T46: 11.17 | U46: 141.05 | V46: 51.44 | W46: 14.92 | X46: 20.73 | Y46: 20.73 | Z46: 11.01 | AA46: 37.86 | AB46: 81.22 | AC46: 383.5 | AD46: 165 | AE46: 17.32 | AF46: 27.75 | AG46: 160.7 | AI46: 10/27/23 | AJ46: =AVERAGE(I46,AC46,AG46) -> 229.08667 | AK46: =AVERAGE(G46,AA46,AF46,) -> 453.6025 | AL46: =AVERAGE(AB46,X46,S46,Q46,O46,M46,J46,E46,) -> 134.92667
A47: 983 | B47: 10/26/23 | C47: 2023 | D47: 6825.59 | E47: 668.4 | F47: 393.15 | G47: 1738.8 | H47: 126.44 | I47: 140.02 | J47: 165.7 | K47: 147.74 | L47: 62.48 | M47: 144.16 | N47: 100.46 | O47: 54.72 | P47: 642 | Q47: 27.52 | R47: 100.48 | S47: 56.2 | T47: 11.21 | U47: 142 | V47: 49.91 | W47: 14.9 | X47: 20.74 | Y47: 20.74 | Z47: 10.93 | AA47: 38 | AB47: 80.34 | AC47: 384.4 | AD47: 168.25 | AE47: 17.66 | AF47: 27.68 | AG47: 163.35 | AI47: 10/26/23 | AJ47: =AVERAGE(I47,AC47,AG47) -> 229.25667 | AK47: =AVERAGE(G47,AA47,AF47,) -> 451.12 | AL47: =AVERAGE(AB47,X47,S47,Q47,O47,M47,J47,E47,) -> 135.30889
A48: 982 | B48: 10/25/23 | C48: 2023 | D48: 6846.51 | E48: 679.1 | F48: 399.2 | G48: 1776.4 | H48: 125.04 | I48: 139.98 | J48: 168.58 | K48: 148.48 | L48: 62.2 | M48: 142.49 | N48: 101.02 | O48: 56.18 | P48: 647.5 | Q48: 27.59 | R48: 100.76 | S48: 54.87 | T48: 11.26 | U48: 142.05 | V48: 49.91 | W48: 14.85 | X48: 20.91 | Y48: 20.91 | Z48: 10.88 | AA48: 37.77 | AB48: 81.02 | AC48: 393.3 | AD48: 169.7 | AE48: 17.79 | AF48: 27.28 | AG48: 165.05 | AI48: 10/25/23 | AJ48: =AVERAGE(I48,AC48,AG48) -> 232.77667 | AK48: =AVERAGE(G48,AA48,AF48,) -> 460.3625 | AL48: =AVERAGE(AB48,X48,S48,Q48,O48,M48,J48,E48,) -> 136.74889
A49: 981 | B49: 10/24/23 | C49: 2023 | D49: 6833.91 | E49: 681 | F49: 394.1 | G49: 1728 | H49: 125.16 | I49: 139.42 | J49: 167.44 | K49: 148.62 | L49: 62.03 | M49: 139.84 | N49: 98.94 | O49: 55.91 | P49: 652.5 | Q49: 27.34 | R49: 101.08 | S49: 54.26 | T49: 11.2 | U49: 141.6 | V49: 50.06 | W49: 14.73 | X49: 20.87 | Y49: 20.87 | Z49: 10.84 | AA49: 34.98 | AB49: 80.64 | AC49: 407.45 | AD49: 170 | AE49: 17.72 | AF49: 27.58 | AG49: 165.2 | AI49: 10/24/23 | AJ49: =AVERAGE(I49,AC49,AG49) -> 237.35667 | AK49: =AVERAGE(G49,AA49,AF49,) -> 447.64 | AL49: =AVERAGE(AB49,X49,S49,Q49,O49,M49,J49,E49,) -> 136.36667
A50: 980 | B50: 10/23/23 | C50: 2023 | D50: 6773.82 | E50: 669.4 | F50: 386.85 | G50: 1681.2 | H50: 122.5 | I50: 141.92 | J50: 165.5 | K50: 146.66 | L50: 62.3 | M50: 139.02 | N50: 98.31 | O50: 56.13 | P50: 635 | Q50: 27.25 | R50: 99.9 | S50: 53.9 | T50: 11.32 | U50: 139.3 | V50: 50.17 | W50: 14.5 | X50: 21.05 | Y50: 21.05 | Z50: 10.76 | AA50: 34.07 | AB50: 81.4 | AC50: 403.5 | AD50: 167.2 | AE50: 18.02 | AF50: 27.85 | AG50: 164.1 | AI50: 10/23/23 | AJ50: =AVERAGE(I50,AC50,AG50) -> 236.50667 | AK50: =AVERAGE(G50,AA50,AF50,) -> 435.78 | AL50: =AVERAGE(AB50,X50,S50,Q50,O50,M50,J50,E50,) -> 134.85
A51: 979 | B51: 10/20/23 | C51: 2023 | D51: 6816.17 | E51: 664 | F51: 380.25 | G51: 1654.2 | H51: 121.26 | I51: 141.44 | J51: 163.06 | K51: 144.94 | L51: 62.57 | M51: 138.75 | N51: 98.83 | O51: 55.56 | P51: 632.5 | Q51: 27.16 | R51: 99.62 | S51: 54.1 | T51: 11.22 | U51: 137.85 | V51: 49.76 | W51: 14.69 | X51: 20.98 | Y51: 20.98 | Z51: 10.84 | AA51: 33.96 | AB51: 80.86 | AC51: 402.8 | AD51: 165.95 | AE51: 17.65 | AF51: 27.78 | AG51: 163.2 | AI51: 10/20/23 | AJ51: =AVERAGE(I51,AC51,AG51) -> 235.81333 | AK51: =AVERAGE(G51,AA51,AF51,) -> 428.985 | AL51: =AVERAGE(AB51,X51,S51,Q51,O51,M51,J51,E51,) -> 133.83
A52: 978 | B52: 10/19/23 | C52: 2023 | D52: 6875.77 | E52: 670.6 | F52: 386.2 | G52: 1680 | H52: 123.9 | I52: 145.74 | J52: 162.14 | K52: 148.46 | L52: 63.33 | M52: 142.76 | N52: 98.81 | O52: 56.71 | P52: 642.5 | Q52: 27.88 | R52: 100.6 | S52: 54.08 | T52: 11.38 | U52: 138.3 | V52: 50.24 | W52: 14.87 | X52: 21.4 | Y52: 21.4 | Z52: 10.91 | AA52: 34.85 | AB52: 83.12 | AC52: 410.65 | AD52: 166.15 | AE52: 18.1 | AF52: 28.45 | AG52: 164.4 | AI52: 10/19/23 | AJ52: =AVERAGE(I52,AC52,AG52) -> 240.26333 | AK52: =AVERAGE(G52,AA52,AF52,) -> 435.825 | AL52: =AVERAGE(AB52,X52,S52,Q52,O52,M52,J52,E52,) -> 135.41
A53: 977 | B53: 10/18/23 | C53: 2023 | D53: 6954.1 | E53: 667.7 | F53: 383.1 | G53: 1686 | H53: 124.72 | I53: 147.1 | J53: 163.62 | K53: 149.6 | L53: 63.78 | M53: 143.02 | N53: 101.36 | O53: 57.31 | P53: 640.5 | Q53: 28.16 | R53: 100.82 | S53: 54.58 | T53: 11.44 | U53: 141.55 | V53: 51.23 | W53: 14.72 | X53: 21.63 | Y53: 21.63 | Z53: 11 | AA53: 35.31 | AB53: 83.98 | AC53: 409.45 | AD53: 158.6 | AE53: 18.78 | AF53: 28.77 | AG53: 164.3 | AI53: 10/18/23 | AJ53: =AVERAGE(I53,AC53,AG53) -> 240.28333 | AK53: =AVERAGE(G53,AA53,AF53,) -> 437.52 | AL53: =AVERAGE(AB53,X53,S53,Q53,O53,M53,J53,E53,) -> 135.55556
A54: 976 | B54: 10/17/23 | C54: 2023 | D54: 6969.07 | E54: 668.4 | F54: 387.4 | G54: 1689 | H54: 127.3 | I54: 151.9 | J54: 164.44 | K54: 151.96 | L54: 63.18 | M54: 144.85 | N54: 102.94 | O54: 57.68 | P54: 645 | Q54: 28.28 | R54: 102.76 | S54: 54.44 | T54: 11.54 | U54: 142.25 | V54: 53.37 | W54: 14.89 | X54: 21.8 | Y54: 21.8 | Z54: 10.94 | AA54: 35.41 | AB54: 85.58 | AC54: 409.5 | AD54: 160.15 | AE54: 18.88 | AF54: 29.18 | AG54: 164.55 | AI54: 10/17/23 | AJ54: =AVERAGE(I54,AC54,AG54) -> 241.98333 | AK54: =AVERAGE(G54,AA54,AF54,) -> 438.3975 | AL54: =AVERAGE(AB54,X54,S54,Q54,O54,M54,J54,E54,) -> 136.16333
A55: 975 | B55: 10/16/23 | C55: 2023 | D55: 6963.02 | E55: 667.1 | F55: 386.75 | G55: 1703.8 | H55: 122.94 | I55: 152.16 | J55: 165.62 | K55: 150.46 | L55: 63.06 | M55: 146 | N55: 103.88 | O55: 57.83 | P55: 644 | Q55: 28.02 | R55: 102.38 | S55: 54.13 | T55: 11.54 | U55: 143.2 | V55: 53.64 | W55: 14.81 | X55: 21.95 | Y55: 21.95 | Z55: 10.93 | AA55: 35.84 | AB55: 85.62 | AC55: 410 | AD55: 159.2 | AE55: 18.69 | AF55: 29.35 | AG55: 166.15 | AI55: 10/16/23 | AJ55: =AVERAGE(I55,AC55,AG55) -> 242.77 | AK55: =AVERAGE(G55,AA55,AF55,) -> 442.2475 | AL55: =AVERAGE(AB55,X55,S55,Q55,O55,M55,J55,E55,) -> 136.25222
A56: 974 | B56: 10/13/23 | C56: 2023 | D56: 6997.48 | E56: 660.6 | F56: 384.65 | G56: 1705.8 | H56: 121.96 | I56: 153.12 | J56: 164.1 | K56: 149.08 | L56: 63.17 | M56: 146.69 | N56: 103.38 | O56: 57.64 | P56: 640 | Q56: 28.01 | R56: 102.92 | S56: 54 | T56: 11.4 | U56: 144.4 | V56: 53.21 | W56: 14.78 | X56: 21.81 | Y56: 21.81 | Z56: 11.04 | AA56: 35.91 | AB56: 85.62 | AC56: 406.8 | AD56: 157.1 | AE56: 18.82 | AF56: 29.03 | AG56: 165.7 | AI56: 10/13/23 | AJ56: =AVERAGE(I56,AC56,AG56) -> 241.87333 | AK56: =AVERAGE(G56,AA56,AF56,) -> 442.685 | AL56: =AVERAGE(AB56,X56,S56,Q56,O56,M56,J56,E56,) -> 135.38556
A57: 973 | B57: 45270 | C57: 2023 | D57: 7097.53 | E57: 675 | F57: 393.2 | G57: 1725.8 | H57: 125.76 | I57: 156.3 | J57: 166.44 | K57: 152.16 | L57: 62.17 | M57: 148.71 | N57: 103.98 | O57: 59.44 | P57: 652 | Q57: 28.36 | R57: 104.78 | S57: 54.19 | T57: 11.68 | U57: 142.8 | V57: 54.5 | W57: 14.68 | X57: 22.47 | Y57: 22.47 | Z57: 10.94 | AA57: 36.94 | AB57: 88.18 | AC57: 416.8 | AD57: 159.25 | AE57: 18.92 | AF57: 29.65 | AG57: 169.6 | AI57: 45270 | AJ57: =AVERAGE(I57,AC57,AG57) -> 247.56667 | AK57: =AVERAGE(G57,AA57,AF57,) -> 448.0975 | AL57: =AVERAGE(AB57,X57,S57,Q57,O57,M57,J57,E57,) -> 138.08778
A58: 972 | B58: 45240 | C58: 2023 | D58: 7080.01 | E58: 686.1 | F58: 396.8 | G58: 1751 | H58: 126.32 | I58: 157.26 | J58: 166.52 | K58: 152.06 | L58: 61.69 | M58: 148.45 | N58: 103.32 | O58: 60.24 | P58: 671.5 | Q58: 28.56 | R58: 105.5 | S58: 54.65 | T58: 11.68 | U58: 139 | V58: 55.04 | W58: 14.73 | X58: 22.6 | Y58: 22.6 | Z58: 11.01 | AA58: 37.05 | AB58: 87.6 | AC58: 427.95 | AD58: 160.3 | AE58: 18.93 | AF58: 29.48 | AG58: 170.05 | AI58: 45240 | AJ58: =AVERAGE(I58,AC58,AG58) -> 251.75333 | AK58: =AVERAGE(G58,AA58,AF58,) -> 454.3825 | AL58: =AVERAGE(AB58,X58,S58,Q58,O58,M58,J58,E58,) -> 139.41333
A59: 971 | B59: 45209 | C59: 2023 | D59: 7085.13 | E59: 733.5 | F59: 397.75 | G59: 1777.6 | H59: 125.6 | I59: 156.7 | J59: 166 | K59: 150.4 | L59: 61.89 | M59: 147.04 | N59: 102.68 | O59: 59.83 | P59: 704.5 | Q59: 28.32 | R59: 104.12 | S59: 54.12 | T59: 11.63 | U59: 135.4 | V59: 55.14 | W59: 14.57 | X59: 22.61 | Y59: 22.61 | Z59: 11 | AA59: 36.79 | AB59: 86.98 | AC59: 434.1 | AD59: 160 | AE59: 18.53 | AF59: 29.57 | AG59: 168.5 | AI59: 45209 | AJ59: =AVERAGE(I59,AC59,AG59) -> 253.1 | AK59: =AVERAGE(G59,AA59,AF59,) -> 460.99 | AL59: =AVERAGE(AB59,X59,S59,Q59,O59,M59,J59,E59,) -> 144.26667
A60: 970 | B60: 45179 | C60: 2023 | D60: 6980.33 | E60: 710.7 | F60: 387.05 | G60: 1727.8 | H60: 123.08 | I60: 152.6 | J60: 163.3 | K60: 145.86 | L60: 61.39 | M60: 143.91 | N60: 102.58 | O60: 59.03 | P60: 687 | Q60: 27.88 | R60: 102.22 | S60: 52.71 | T60: 11.46 | U60: 134 | V60: 54.06 | W60: 14.28 | X60: 22.36 | Y60: 22.36 | Z60: 11 | AA60: 35.82 | AB60: 85.64 | AC60: 419.65 | AD60: 157.15 | AE60: 18 | AF60: 29.14 | AG60: 164.05 | AI60: 45179 | AJ60: =AVERAGE(I60,AC60,AG60) -> 245.43333 | AK60: =AVERAGE(G60,AA60,AF60,) -> 448.19 | AL60: =AVERAGE(AB60,X60,S60,Q60,O60,M60,J60,E60,) -> 140.61444
A61: 969 | B61: 45087 | C61: 2023 | D61: 6981.49 | E61: 729.7 | F61: 394.2 | G61: 1756.4 | H61: 124.28 | I61: 155.58 | J61: 164.06 | K61: 144.78 | L61: 60.34 | M61: 143.49 | N61: 102.2 | O61: 59.98 | P61: 703.5 | Q61: 27.97 | R61: 102.32 | S61: 51.31 | T61: 11.68 | U61: 128 | V61: 54.47 | W61: 14.13 | X61: 22.7 | Y61: 22.7 | Z61: 10.98 | AA61: 36.33 | AB61: 86.32 | AC61: 425.35 | AD61: 158.6 | AE61: 17.99 | AF61: 29.18 | AG61: 165.3 | AI61: 45087 | AJ61: =AVERAGE(I61,AC61,AG61) -> 248.74333 | AK61: =AVERAGE(G61,AA61,AF61,) -> 455.4775 | AL61: =AVERAGE(AB61,X61,S61,Q61,O61,M61,J61,E61,) -> 142.83667
A62: 968 | B62: 45056 | C62: 2023 | D62: 6970.59 | E62: 720.6 | F62: 391.35 | G62: 1731.8 | H62: 123.52 | I62: 154.14 | J62: 163 | K62: 143.22 | L62: 59.77 | M62: 142.4 | N62: 102.86 | O62: 59.2 | P62: 696 | Q62: 27.32 | R62: 101.58 | S62: 51.91 | T62: 11.42 | U62: 128.1 | V62: 53.52 | W62: 14.14 | X62: 22.42 | Y62: 22.42 | Z62: 10.99 | AA62: 35.24 | AB62: 85.76 | AC62: 421.45 | AD62: 159.95 | AE62: 17.84 | AF62: 28.73 | AG62: 162.7 | AI62: 45056 | AJ62: =AVERAGE(I62,AC62,AG62) -> 246.09667 | AK62: =AVERAGE(G62,AA62,AF62,) -> 448.9425 | AL62: =AVERAGE(AB62,X62,S62,Q62,O62,M62,J62,E62,) -> 141.40111
A63: 967 | B63: 45026 | C63: 2023 | D63: 6948.03 | E63: 712.5 | F63: 392.05 | G63: 1731 | H63: 123.54 | I63: 153.82 | J63: 163.12 | K63: 143.76 | L63: 60.09 | M63: 142.35 | N63: 101.82 | O63: 58.64 | P63: 690 | Q63: 27.21 | R63: 101.9 | S63: 51.61 | T63: 11.35 | U63: 128.6 | V63: 54.11 | W63: 14.03 | X63: 22.43 | Y63: 22.43 | Z63: 10.99 | AA63: 35.23 | AB63: 85.76 | AC63: 421.45 | AD63: 159.7 | AE63: 17.72 | AF63: 28.5 | AG63: 164.6 | AI63: 45026 | AJ63: =AVERAGE(I63,AC63,AG63) -> 246.62333 | AK63: =AVERAGE(G63,AA63,AF63,) -> 448.6825 | AL63: =AVERAGE(AB63,X63,S63,Q63,O63,M63,J63,E63,) -> 140.40222
A64: 966 | B64: 44995 | C64: 2023 | D64: 6989.77 | E64: 705.3 | F64: 391.85 | G64: 1705.6 | H64: 124.32 | I64: 154.66 | J64: 162.42 | K64: 144.8 | L64: 61.28 | M64: 141.96 | N64: 101.56 | O64: 58.8 | P64: 685 | Q64: 27.31 | R64: 101.16 | S64: 51.89 | T64: 11.39 | U64: 131.1 | V64: 54.12 | W64: 14 | X64: 22.43 | Y64: 22.43 | Z64: 10.78 | AA64: 35.19 | AB64: 87.18 | AC64: 421.65 | AD64: 158.9 | AE64: 17.81 | AF64: 28.59 | AG64: 160.9 | AI64: 44995 | AJ64: =AVERAGE(I64,AC64,AG64) -> 245.73667 | AK64: =AVERAGE(G64,AA64,AF64,) -> 442.345 | AL64: =AVERAGE(AB64,X64,S64,Q64,O64,M64,J64,E64,) -> 139.69889
A65: 965 | B65: 44967 | C65: 2023 | D65: 7035.65 | E65: 714.9 | F65: 393.7 | G65: 1725.8 | H65: 125.56 | I65: 154.78 | J65: 163.66 | K65: 146.28 | L65: 61.55 | M65: 142.98 | N65: 101.82 | O65: 59.69 | P65: 694 | Q65: 27.69 | R65: 103.72 | S65: 51.57 | T65: 11.54 | U65: 131.85 | V65: 54.71 | W65: 14.28 | X65: 22.86 | Y65: 22.86 | Z65: 10.9 | AA65: 35.71 | AB65: 87.24 | AC65: 429.3 | AD65: 157 | AE65: 18.1 | AF65: 29.15 | AG65: 164.7 | AI65: 44967 | AJ65: =AVERAGE(I65,AC65,AG65) -> 249.59333 | AK65: =AVERAGE(G65,AA65,AF65,) -> 447.665 | AL65: =AVERAGE(AB65,X65,S65,Q65,O65,M65,J65,E65,) -> 141.17667
A66: 964 | B66: 09/29/23 | C66: 2023 | D66: 7135.06 | E66: 716.4 | F66: 393.2 | G66: 1729.8 | H66: 126.98 | I66: 156.98 | J66: 165.16 | K66: 148.64 | L66: 62.31 | M66: 145.31 | N66: 101.48 | O66: 60.43 | P66: 697 | Q66: 28.18 | R66: 105.02 | S66: 52.26 | T66: 11.69 | U66: 133.1 | V66: 56.88 | W66: 14.53 | X66: 23.05 | Y66: 23.05 | Z66: 10.86 | AA66: 35.3 | AB66: 87.3 | AC66: 431.9 | AD66: 157.85 | AE66: 18.2 | AF66: 29.07 | AG66: 165.8 | AI66: 09/29/23 | AJ66: =AVERAGE(I66,AC66,AG66) -> 251.56 | AK66: =AVERAGE(G66,AA66,AF66,) -> 448.5425 | AL66: =AVERAGE(AB66,X66,S66,Q66,O66,M66,J66,E66,) -> 142.01
A67: 963 | B67: 09/28/23 | C67: 2023 | D67: 7042.74 | E67: 706 | F67: 390.3 | G67: 1719.8 | H67: 126.74 | I67: 156.5 | J67: 164.16 | K67: 149.86 | L67: 63.62 | M67: 145.4 | N67: 100.76 | O67: 60.47 | P67: 681.5 | Q67: 28.35 | R67: 105.22 | S67: 51.45 | T67: 11.65 | U67: 133.6 | V67: 56.87 | W67: 14.39 | X67: 22.93 | Y67: 22.93 | Z67: 10.8 | AA67: 34.64 | AB67: 85.5 | AC67: 429.45 | AD67: 158.35 | AE67: 18.16 | AF67: 29.02 | AG67: 164.15 | AI67: 09/28/23 | AJ67: =AVERAGE(I67,AC67,AG67) -> 250.03333 | AK67: =AVERAGE(G67,AA67,AF67,) -> 445.865 | AL67: =AVERAGE(AB67,X67,S67,Q67,O67,M67,J67,E67,) -> 140.47333
A68: 962 | B68: 09/27/23 | C68: 2023 | D68: 7053.11 | E68: 698.7 | F68: 386.7 | G68: 1696.6 | H68: 124 | I68: 155.32 | J68: 162.64 | K68: 149.48 | L68: 62.93 | M68: 144.07 | N68: 101.68 | O68: 60.11 | P68: 673.5 | Q68: 28.3 | R68: 104.42 | S68: 51.66 | T68: 11.5 | U68: 133.2 | V68: 56.23 | W68: 14.51 | X68: 22.89 | Y68: 22.89 | Z68: 10.82 | AA68: 34.68 | AB68: 85.04 | AC68: 427.25 | AD68: 159.45 | AE68: 17.85 | AF68: 28.92 | AG68: 165.45 | AI68: 09/27/23 | AJ68: =AVERAGE(I68,AC68,AG68) -> 249.34 | AK68: =AVERAGE(G68,AA68,AF68,) -> 440.05 | AL68: =AVERAGE(AB68,X68,S68,Q68,O68,M68,J68,E68,) -> 139.26778
A69: 961 | B69: 09/26/23 | C69: 2023 | D69: 7033.83 | E69: 703 | F69: 387.55 | G69: 1707 | H69: 123.58 | I69: 152.92 | J69: 163.22 | K69: 147.24 | L69: 61.91 | M69: 144.64 | N69: 102.78 | O69: 60.23 | P69: 668 | Q69: 28.65 | R69: 104.06 | S69: 52.5 | T69: 11.44 | U69: 132.65 | V69: 56.35 | W69: 14.74 | X69: 22.62 | Y69: 22.62 | Z69: 10.99 | AA69: 34.39 | AB69: 84.82 | AC69: 429.95 | AD69: 161 | AE69: 17.99 | AF69: 29.05 | AG69: 164.05 | AI69: 09/26/23 | AJ69: =AVERAGE(I69,AC69,AG69) -> 248.97333 | AK69: =AVERAGE(G69,AA69,AF69,) -> 442.61 | AL69: =AVERAGE(AB69,X69,S69,Q69,O69,M69,J69,E69,) -> 139.96444
A70: 960 | B70: 09/25/23 | C70: 2023 | D70: 7087.63 | E70: 713.3 | F70: 391.5 | G70: 1732.8 | H70: 122.96 | I70: 155.38 | J70: 165.78 | K70: 147.14 | L70: 62.13 | M70: 145.69 | N70: 102.64 | O70: 60.42 | P70: 678 | Q70: 28.62 | R70: 104.54 | S70: 52.41 | T70: 11.45 | U70: 132.75 | V70: 56.23 | W70: 14.84 | X70: 22.97 | Y70: 22.97 | Z70: 10.99 | AA70: 34.95 | AB70: 85.02 | AC70: 439.55 | AD70: 162.2 | AE70: 18.06 | AF70: 29.43 | AG70: 165.65 | AI70: 09/25/23 | AJ70: =AVERAGE(I70,AC70,AG70) -> 253.52667 | AK70: =AVERAGE(G70,AA70,AF70,) -> 449.295 | AL70: =AVERAGE(AB70,X70,S70,Q70,O70,M70,J70,E70,) -> 141.57889
A71: 959 | B71: 09/22/23 | C71: 2023 | D71: 7133.65 | E71: 732.3 | F71: 398.35 | G71: 1793 | H71: 123.88 | I71: 154.14 | J71: 167.96 | K71: 147.2 | L71: 61.91 | M71: 145.95 | N71: 102.1 | O71: 60.74 | P71: 699 | Q71: 28.82 | R71: 105.34 | S71: 53.02 | T71: 11.5 | U71: 132.7 | V71: 56.13 | W71: 14.96 | X71: 23.12 | Y71: 23.12 | Z71: 11.09 | AA71: 35.01 | AB71: 84.44 | AC71: 460.45 | AD71: 166.3 | AE71: 18.28 | AF71: 29.5 | AG71: 166.75 | AI71: 09/22/23 | AJ71: =AVERAGE(I71,AC71,AG71) -> 260.44667 | AK71: =AVERAGE(G71,AA71,AF71,) -> 464.3775 | AL71: =AVERAGE(AB71,X71,S71,Q71,O71,M71,J71,E71,) -> 144.03889
A72: 958 | B72: 09/21/23 | C72: 2023 | D72: 7199.11 | E72: 729.3 | F72: 399.7 | G72: 1766.6 | H72: 125.52 | I72: 155 | J72: 169.42 | K72: 148.04 | L72: 61.88 | M72: 146 | N72: 102.5 | O72: 61.65 | P72: 694.5 | Q72: 29.15 | R72: 106.18 | S72: 53.56 | T72: 11.68 | U72: 134.5 | V72: 56.93 | W72: 14.94 | X72: 23.49 | Y72: 23.49 | Z72: 11.29 | AA72: 34.51 | AB72: 86 | AC72: 453.6 | AD72: 166.45 | AE72: 18.16 | AF72: 30.16 | AG72: 168.05 | AI72: 09/21/23 | AJ72: =AVERAGE(I72,AC72,AG72) -> 258.88333 | AK72: =AVERAGE(G72,AA72,AF72,) -> 457.8175 | AL72: =AVERAGE(AB72,X72,S72,Q72,O72,M72,J72,E72,) -> 144.28556
A73: 957 | B73: 09/20/23 | C73: 2023 | D73: 7272.68 | E73: 736.7 | F73: 410 | G73: 1876.4 | H73: 129.64 | I73: 157.96 | J73: 175.34 | K73: 152.04 | L73: 62.29 | M73: 147.42 | N73: 103.8 | O73: 62.07 | P73: 702 | Q73: 29.35 | R73: 107.68 | S73: 54.08 | T73: 11.8 | U73: 137.3 | V73: 57.94 | W73: 15.17 | X73: 23.83 | Y73: 23.83 | Z73: 11.25 | AA73: 35.22 | AB73: 87.68 | AC73: 457.6 | AD73: 168.7 | AE73: 18.61 | AF73: 30.29 | AG73: 168.9 | AI73: 09/20/23 | AJ73: =AVERAGE(I73,AC73,AG73) -> 261.48667 | AK73: =AVERAGE(G73,AA73,AF73,) -> 485.4775 | AL73: =AVERAGE(AB73,X73,S73,Q73,O73,M73,J73,E73,) -> 146.27444
A74: 956 | B74: 09/19/23 | C74: 2023 | D74: 7247.02 | E74: 736.8 | F74: 400.35 | G74: 1845.6 | H74: 129.28 | I74: 155.64 | J74: 171.86 | K74: 151.74 | L74: 63.04 | M74: 149.84 | N74: 102.1 | O74: 61.11 | P74: 698.5 | Q74: 29.31 | R74: 106.24 | S74: 53.56 | T74: 11.65 | U74: 139.55 | V74: 57.23 | W74: 15.29 | X74: 23.14 | Y74: 23.14 | Z74: 11.17 | AA74: 34.67 | AB74: 87.5 | AC74: 456.85 | AD74: 168.45 | AE74: 18.05 | AF74: 30.36 | AG74: 166.5 | AI74: 09/19/23 | AJ74: =AVERAGE(I74,AC74,AG74) -> 259.66333 | AK74: =AVERAGE(G74,AA74,AF74,) -> 477.6575 | AL74: =AVERAGE(AB74,X74,S74,Q74,O74,M74,J74,E74,) -> 145.90222
A75: 955 | B75: 09/18/23 | C75: 2023 | D75: 7255.03 | E75: 742.5 | F75: 404.4 | G75: 1874.4 | H75: 130.04 | I75: 156.92 | J75: 173.42 | K75: 151.7 | L75: 61.99 | M75: 149.4 | N75: 101.68 | O75: 60.11 | P75: 707 | Q75: 29.07 | R75: 106.24 | S75: 53.81 | T75: 11.55 | U75: 138.95 | V75: 56.95 | W75: 15.1 | X75: 23.28 | Y75: 23.28 | Z75: 11.1 | AA75: 35.27 | AB75: 88.24 | AC75: 459.45 | AD75: 169.25 | AE75: 17.79 | AF75: 30.11 | AG75: 165.95 | AI75: 09/18/23 | AJ75: =AVERAGE(I75,AC75,AG75) -> 260.77333 | AK75: =AVERAGE(G75,AA75,AF75,) -> 484.945 | AL75: =AVERAGE(AB75,X75,S75,Q75,O75,M75,J75,E75,) -> 146.64778
A76: 954 | B76: 09/15/23 | C76: 2023 | D76: 7366.21 | E76: 761.2 | F76: 410 | G76: 1903.6 | H76: 131.32 | I76: 157.44 | J76: 175.32 | K76: 152.42 | L76: 62.37 | M76: 152.78 | N76: 102.8 | O76: 61.46 | P76: 720.5 | Q76: 29.39 | R76: 107.48 | S76: 53.79 | T76: 11.84 | U76: 139.5 | V76: 57.24 | W76: 15.2 | X76: 26.47 | Y76: 26.47 | Z76: 11.06 | AA76: 35.34 | AB76: 88.38 | AC76: 469.1 | AD76: 171.9 | AE76: 17.88 | AF76: 30.27 | AG76: 170.1 | AI76: 09/15/23 | AJ76: =AVERAGE(I76,AC76,AG76) -> 265.54667 | AK76: =AVERAGE(G76,AA76,AF76,) -> 492.3025 | AL76: =AVERAGE(AB76,X76,S76,Q76,O76,M76,J76,E76,) -> 149.86556
A77: 953 | B77: 09/14/23 | C77: 2023 | D77: 7184.25 | E77: 742.6 | F77: 402 | G77: 1876 | H77: 130.4 | I77: 155.78 | J77: 176.24 | K77: 150.6 | L77: 62.28 | M77: 150.91 | N77: 102.42 | O77: 61.3 | P77: 713.5 | Q77: 29.15 | R77: 106.24 | S77: 53.49 | T77: 11.71 | U77: 138.05 | V77: 56.57 | W77: 15.15 | X77: 26.56 | Y77: 26.56 | Z77: 10.98 | AA77: 35.24 | AB77: 86.96 | AC77: 461 | AD77: 171.4 | AE77: 17.58 | AF77: 29.8 | AG77: 167.85 | AI77: 09/14/23 | AJ77: =AVERAGE(I77,AC77,AG77) -> 261.54333 | AK77: =AVERAGE(G77,AA77,AF77,) -> 485.26 | AL77: =AVERAGE(AB77,X77,S77,Q77,O77,M77,J77,E77,) -> 147.46778
A78: 952 | B78: 09/13/23 | C78: 2023 | D78: 7184.56 | E78: 729.6 | F78: 397.5 | G78: 1836.2 | H78: 130.52 | I78: 153.38 | J78: 173.92 | K78: 148.5 | L78: 61.23 | M78: 149.42 | N78: 101.5 | O78: 59.89 | P78: 697 | Q78: 28.58 | R78: 104.02 | S78: 53.2 | T78: 11.54 | U78: 139.85 | V78: 56.21 | W78: 14.9 | X78: 26.2 | Y78: 26.2 | Z78: 10.92 | AA78: 35.25 | AB78: 86.56 | AC78: 461.85 | AD78: 171.85 | AE78: 17.76 | AF78: 29.7 | AG78: 167.05 | AI78: 09/13/23 | AJ78: =AVERAGE(I78,AC78,AG78) -> 260.76 | AK78: =AVERAGE(G78,AA78,AF78,) -> 475.2875 | AL78: =AVERAGE(AB78,X78,S78,Q78,O78,M78,J78,E78,) -> 145.26333
A79: 951 | B79: 45269 | C79: 2023 | D79: 7241.99 | E79: 734.4 | F79: 401.3 | G79: 1836.2 | H79: 130.48 | I79: 156.64 | J79: 173.8 | K79: 149.12 | L79: 61.29 | M79: 150.09 | N79: 101.68 | O79: 59.87 | P79: 700.5 | Q79: 28.15 | R79: 105.16 | S79: 53.53 | T79: 11.45 | U79: 139.85 | V79: 56.99 | W79: 14.88 | X79: 25.95 | Y79: 25.95 | Z79: 10.97 | AA79: 35.64 | AB79: 88.14 | AC79: 463.7 | AD79: 171.55 | AE79: 17.82 | AF79: 29.84 | AG79: 169.25 | AI79: 45269 | AJ79: =AVERAGE(I79,AC79,AG79) -> 263.19667 | AK79: =AVERAGE(G79,AA79,AF79,) -> 475.42 | AL79: =AVERAGE(AB79,X79,S79,Q79,O79,M79,J79,E79,) -> 145.99222
A80: 950 | B80: 45239 | C80: 2023 | D80: 7253.65 | E80: 742.2 | F80: 407.15 | G80: 1855.6 | H80: 133.66 | I80: 157.4 | J80: 174.24 | K80: 150.08 | L80: 60.74 | M80: 151.6 | N80: 101.82 | O80: 59.51 | P80: 711 | Q80: 27.96 | R80: 103.58 | S80: 54.2 | T80: 11.3 | U80: 139.35 | V80: 57.37 | W80: 14.89 | X80: 25.72 | Y80: 25.72 | Z80: 10.92 | AA80: 36.37 | AB80: 88.14 | AC80: 468.15 | AD80: 173.4 | AE80: 17.37 | AF80: 29.89 | AG80: 170.4 | AI80: 45239 | AJ80: =AVERAGE(I80,AC80,AG80) -> 265.31667 | AK80: =AVERAGE(G80,AA80,AF80,) -> 480.465 | AL80: =AVERAGE(AB80,X80,S80,Q80,O80,M80,J80,E80,) -> 147.06333
A81: 949 | B81: 45147 | C81: 2023 | D81: 7136.56 | E81: 740 | F81: 404.25 | G81: 1849.4 | H81: 135.44 | I81: 157.12 | J81: 173.34 | K81: 148.54 | L81: 60.38 | M81: 150.44 | N81: 100.34 | O81: 58.43 | P81: 714 | Q81: 27.71 | R81: 102.96 | S81: 53.57 | T81: 11.16 | U81: 138.7 | V81: 57.37 | W81: 14.83 | X81: 25.28 | Y81: 25.28 | Z81: 10.79 | AA81: 36.45 | AB81: 90.76 | AC81: 469.7 | AD81: 174.5 | AE81: 16.99 | AF81: 29.52 | AG81: 170.3 | AI81: 45147 | AJ81: =AVERAGE(I81,AC81,AG81) -> 265.70667 | AK81: =AVERAGE(G81,AA81,AF81,) -> 478.8425 | AL81: =AVERAGE(AB81,X81,S81,Q81,O81,M81,J81,E81,) -> 146.61444
A82: 948 | B82: 45116 | C82: 2023 | D82: 7165.98 | E82: 724.1 | F82: 398.4 | G82: 1834.4 | H82: 136.42 | I82: 156.98 | J82: 173.36 | K82: 148.46 | L82: 59.88 | M82: 150.56 | N82: 99.68 | O82: 58.57 | P82: 701.5 | Q82: 27.53 | R82: 102.5 | S82: 53.22 | T82: 11.21 | U82: 137.3 | V82: 57.28 | W82: 14.66 | X82: 25.42 | Y82: 25.42 | Z82: 10.78 | AA82: 36.41 | AB82: 90.86 | AC82: 462.85 | AD82: 174.45 | AE82: 16.95 | AF82: 29.95 | AG82: 168.2 | AI82: 45116 | AJ82: =AVERAGE(I82,AC82,AG82) -> 262.67667 | AK82: =AVERAGE(G82,AA82,AF82,) -> 475.19 | AL82: =AVERAGE(AB82,X82,S82,Q82,O82,M82,J82,E82,) -> 144.84667
A83: 947 | B83: 45086 | C83: 2023 | D83: 7168.84 | E83: 731.5 | F83: 398.2 | G83: 1833.4 | H83: 133.94 | I83: 157.74 | J83: 172.22 | K83: 146.04 | L83: 59.51 | M83: 149.69 | N83: 98.24 | O83: 58.6 | P83: 710 | Q83: 27.59 | R83: 102.36 | S83: 52.73 | T83: 11.26 | U83: 136.7 | V83: 57.71 | W83: 14.5 | X83: 25.53 | Y83: 25.53 | Z83: 10.55 | AA83: 36.57 | AB83: 91.36 | AC83: 468.7 | AD83: 176.6 | AE83: 16.92 | AF83: 30.09 | AG83: 170.45 | AI83: 45086 | AJ83: =AVERAGE(I83,AC83,AG83) -> 265.63 | AK83: =AVERAGE(G83,AA83,AF83,) -> 475.015 | AL83: =AVERAGE(AB83,X83,S83,Q83,O83,M83,J83,E83,) -> 145.46889
A84: 946 | B84: 45055 | C84: 2023 | D84: 7183.8 | E84: 759.1 | F84: 403.85 | G84: 1868.2 | H84: 134.1 | I84: 156.72 | J84: 174.2 | K84: 145.7 | L84: 59.9 | M84: 148.89 | N84: 99.03 | O84: 59.39 | P84: 728 | Q84: 27.84 | R84: 102.1 | S84: 52.79 | T84: 11.36 | U84: 137.15 | V84: 57.59 | W84: 14.58 | X84: 25.68 | Y84: 25.68 | Z84: 10.38 | AA84: 36.66 | AB84: 90.26 | AC84: 479.8 | AD84: 179.1 | AE84: 16.91 | AF84: 29.78 | AG84: 172.35 | AI84: 45055 | AJ84: =AVERAGE(I84,AC84,AG84) -> 269.62333 | AK84: =AVERAGE(G84,AA84,AF84,) -> 483.66 | AL84: =AVERAGE(AB84,X84,S84,Q84,O84,M84,J84,E84,) -> 148.68333
A85: 945 | B85: 45025 | C85: 2023 | D85: 7267.25 | E85: 772.6 | F85: 405.75 | G85: 1882.4 | H85: 134.18 | I85: 157.26 | J85: 175.32 | K85: 146.08 | L85: 58.72 | M85: 151.33 | N85: 98.03 | O85: 59.44 | P85: 751.5 | Q85: 27.73 | R85: 102.78 | S85: 53.37 | T85: 11.59 | U85: 136.7 | V85: 58.36 | W85: 14.75 | X85: 25.84 | Y85: 25.84 | Z85: 10.38 | AA85: 36.68 | AB85: 90.76 | AC85: 490.55 | AD85: 181 | AE85: 16.81 | AF85: 29.2 | AG85: 171.3 | AI85: 45025 | AJ85: =AVERAGE(I85,AC85,AG85) -> 273.03667 | AK85: =AVERAGE(G85,AA85,AF85,) -> 487.07 | AL85: =AVERAGE(AB85,X85,S85,Q85,O85,M85,J85,E85,) -> 150.71
A86: 944 | B86: 44935 | C86: 2023 | D86: 7294.49 | E86: 775.8 | F86: 405.2 | G86: 1885.8 | H86: 133.86 | I86: 157.44 | J86: 174.18 | K86: 146.06 | L86: 58.89 | M86: 152.02 | N86: 98.61 | O86: 59.59 | P86: 750 | Q86: 27.85 | R86: 102.72 | S86: 53.76 | T86: 11.65 | U86: 135.25 | V86: 60.25 | W86: 14.82 | X86: 26.28 | Y86: 26.28 | Z86: 10.43 | AA86: 36.47 | AB86: 90.84 | AC86: 488.8 | AD86: 181.4 | AE86: 16.79 | AF86: 29.01 | AG86: 172 | AI86: 44935 | AJ86: =AVERAGE(I86,AC86,AG86) -> 272.74667 | AK86: =AVERAGE(G86,AA86,AF86,) -> 487.82 | AL86: =AVERAGE(AB86,X86,S86,Q86,O86,M86,J86,E86,) -> 151.14667
A87: 943 | B87: 08/31/23 | C87: 2023 | D87: 7316.7 | E87: 782.2 | F87: 405.8 | G87: 1900.8 | H87: 135.38 | I87: 158.58 | J87: 173.9 | K87: 148.3 | L87: 58.07 | M87: 151.69 | N87: 98.64 | O87: 59.71 | P87: 758.5 | Q87: 27.78 | R87: 102.96 | S87: 53.83 | T87: 11.66 | U87: 134.8 | V87: 60.16 | W87: 14.89 | X87: 26.22 | Y87: 26.22 | Z87: 10.36 | AA87: 36.61 | AB87: 91.1 | AC87: 494.2 | AD87: 181.2 | AE87: 17.15 | AF87: 28.91 | AG87: 172.35 | AI87: 08/31/23 | AJ87: =AVERAGE(I87,AC87,AG87) -> 275.04333 | AK87: =AVERAGE(G87,AA87,AF87,) -> 491.58 | AL87: =AVERAGE(AB87,X87,S87,Q87,O87,M87,J87,E87,) -> 151.82556
A88: 942 | B88: 08/30/23 | C88: 2023 | D88: 7321.35 | E88: 804 | F88: 410.1 | G88: 1931.4 | H88: 133.84 | I88: 159.86 | J88: 174.74 | K88: 148.88 | L88: 57.94 | M88: 151.13 | N88: 99.2 | O88: 59.88 | P88: 766.5 | Q88: 27.87 | R88: 103.48 | S88: 53.96 | T88: 11.7 | U88: 134.05 | V88: 59.64 | W88: 14.89 | X88: 26.37 | Y88: 26.37 | Z88: 10.37 | AA88: 36.65 | AB88: 91.28 | AC88: 498.3 | AD88: 194.3 | AE88: 17.17 | AF88: 28.9 | AG88: 171.35 | AI88: 08/30/23 | AJ88: =AVERAGE(I88,AC88,AG88) -> 276.50333 | AK88: =AVERAGE(G88,AA88,AF88,) -> 499.2375 | AL88: =AVERAGE(AB88,X88,S88,Q88,O88,M88,J88,E88,) -> 154.35889
A89: 941 | B89: 08/29/23 | C89: 2023 | D89: 7322.45 | E89: 810 | F89: 409.15 | G89: 1937.8 | H89: 132.56 | I89: 160.44 | J89: 176.4 | K89: 148.32 | L89: 57.86 | M89: 150.47 | N89: 99.67 | O89: 59.9 | P89: 764 | Q89: 27.93 | R89: 103.78 | S89: 53.67 | T89: 11.7 | U89: 133.8 | V89: 59.37 | W89: 15.03 | X89: 26.38 | Y89: 26.38 | Z89: 10.37 | AA89: 36.62 | AB89: 91.2 | AC89: 499 | AD89: 195.65 | AE89: 17.22 | AF89: 29.05 | AG89: 168.85 | AI89: 08/29/23 | AJ89: =AVERAGE(I89,AC89,AG89) -> 276.09667 | AK89: =AVERAGE(G89,AA89,AF89,) -> 500.8675 | AL89: =AVERAGE(AB89,X89,S89,Q89,O89,M89,J89,E89,) -> 155.10556
A90: 940 | B90: 08/28/23 | C90: 2023 | D90: 7261.5 | E90: 798.5 | F90: 405.2 | G90: 1917.6 | H90: 132.24 | I90: 158.86 | J90: 176.12 | K90: 147.68 | L90: 57.89 | M90: 150.27 | N90: 99.28 | O90: 59.5 | P90: 754 | Q90: 27.71 | R90: 103.84 | S90: 53.78 | T90: 11.57 | U90: 134.3 | V90: 58.98 | W90: 14.84 | X90: 26.25 | Y90: 26.25 | Z90: 10.31 | AA90: 36.19 | AB90: 90.34 | AC90: 494.4 | AD90: 194.4 | AE90: 16.93 | AF90: 28.66 | AG90: 165.6 | AI90: 08/28/23 | AJ90: =AVERAGE(I90,AC90,AG90) -> 272.95333 | AK90: =AVERAGE(G90,AA90,AF90,) -> 495.6125 | AL90: =AVERAGE(AB90,X90,S90,Q90,O90,M90,J90,E90,) -> 153.60778
A91: 939 | B91: 08/25/23 | C91: 2023 | D91: 7196.84 | E91: 785.3 | F91: 401.45 | G91: 1883.2 | H91: 129.88 | I91: 156.52 | J91: 174.04 | K91: 145.1 | L91: 57.32 | M91: 148.04 | N91: 98.71 | O91: 58.31 | P91: 742.5 | Q91: 27.4 | R91: 102.34 | S91: 53.51 | T91: 11.47 | U91: 132.7 | V91: 58.04 | W91: 14.79 | X91: 25.92 | Y91: 25.92 | Z91: 10.26 | AA91: 35.71 | AB91: 89.12 | AC91: 487.6 | AD91: 193.2 | AE91: 16.72 | AF91: 28.42 | AG91: 162.55 | AI91: 08/25/23 | AJ91: =AVERAGE(I91,AC91,AG91) -> 268.89 | AK91: =AVERAGE(G91,AA91,AF91,) -> 486.8325 | AL91: =AVERAGE(AB91,X91,S91,Q91,O91,M91,J91,E91,) -> 151.29333
A92: 938 | B92: 08/24/23 | C92: 2023 | D92: 7210 | E92: 783.7 | F92: 400.35 | G92: 1878.4 | H92: 129.32 | I92: 155.9 | J92: 173.98 | K92: 145.24 | L92: 57.17 | M92: 147.91 | N92: 98.13 | O92: 58.44 | P92: 736 | Q92: 27.4 | R92: 101.54 | S92: 53.26 | T92: 11.49 | U92: 132.35 | V92: 58.05 | W92: 14.69 | X92: 25.94 | Y92: 25.94 | Z92: 10.24 | AA92: 35.78 | AB92: 89.08 | AC92: 490 | AD92: 191.8 | AE92: 16.56 | AF92: 28.48 | AG92: 163.6 | AI92: 08/24/23 | AJ92: =AVERAGE(I92,AC92,AG92) -> 269.83333 | AK92: =AVERAGE(G92,AA92,AF92,) -> 485.665 | AL92: =AVERAGE(AB92,X92,S92,Q92,O92,M92,J92,E92,) -> 151.07889
A93: 937 | B93: 08/23/23 | C93: 2023 | D93: 7224.07 | E93: 790.4 | F93: 401.3 | G93: 1902.8 | H93: 130.02 | I93: 157.08 | J93: 174.58 | K93: 146.66 | L93: 56.97 | M93: 147.13 | N93: 98.97 | O93: 58.51 | P93: 742.5 | Q93: 27.41 | R93: 101.48 | S93: 52.9 | T93: 11.42 | U93: 132.5 | V93: 58.71 | W93: 14.64 | X93: 25.85 | Y93: 25.85 | Z93: 10.27 | AA93: 36.1 | AB93: 89.5 | AC93: 499.1 | AD93: 191.7 | AE93: 16.72 | AF93: 28.58 | AG93: 165.5 | AI93: 08/23/23 | AJ93: =AVERAGE(I93,AC93,AG93) -> 273.89333 | AK93: =AVERAGE(G93,AA93,AF93,) -> 491.87 | AL93: =AVERAGE(AB93,X93,S93,Q93,O93,M93,J93,E93,) -> 151.80889
A94: 936 | B94: 08/22/23 | C94: 2023 | D94: 7223.07 | E94: 790.2 | F94: 396.3 | G94: 1885.2 | H94: 128.94 | I94: 155.98 | J94: 176.56 | K94: 145.54 | L94: 57.98 | M94: 146.25 | N94: 99.61 | O94: 58.55 | P94: 745 | Q94: 27.33 | R94: 101.4 | S94: 52.63 | T94: 11.46 | U94: 131.1 | V94: 59.29 | W94: 14.7 | X94: 25.6 | Y94: 25.6 | Z94: 10.19 | AA94: 35.99 | AB94: 89.46 | AC94: 501.4 | AD94: 191.2 | AE94: 16.71 | AF94: 28.65 | AG94: 164.25 | AI94: 08/22/23 | AJ94: =AVERAGE(I94,AC94,AG94) -> 273.87667 | AK94: =AVERAGE(G94,AA94,AF94,) -> 487.46 | AL94: =AVERAGE(AB94,X94,S94,Q94,O94,M94,J94,E94,) -> 151.84222
A95: 935 | B95: 08/21/23 | C95: 2023 | D95: 7165.07 | E95: 783.9 | F95: 398 | G95: 1874 | H95: 128.12 | I95: 154.86 | J95: 174.94 | K95: 144.72 | L95: 57.59 | M95: 145.49 | N95: 98.65 | O95: 58.34 | P95: 743.5 | Q95: 27.2 | R95: 100.88 | S95: 53.06 | T95: 11.36 | U95: 130.8 | V95: 59.05 | W95: 14.74 | X95: 25.45 | Y95: 25.45 | Z95: 10.22 | AA95: 35.57 | AB95: 88.52 | AC95: 498.5 | AD95: 192.5 | AE95: 16.65 | AF95: 28.46 | AG95: 162.05 | AI95: 08/21/23 | AJ95: =AVERAGE(I95,AC95,AG95) -> 271.80333 | AK95: =AVERAGE(G95,AA95,AF95,) -> 484.5075 | AL95: =AVERAGE(AB95,X95,S95,Q95,O95,M95,J95,E95,) -> 150.76667
A96: 934 | B96: 08/18/23 | C96: 2023 | D96: 7092.72 | E96: 776.9 | F96: 398.2 | G96: 1862.6 | H96: 126.7 | I96: 154.32 | J96: 173.5 | K96: 143.42 | L96: 57.01 | M96: 146.04 | N96: 98 | O96: 58.22 | P96: 733 | Q96: 27.18 | R96: 101 | S96: 53.19 | T96: 11.33 | U96: 129.45 | V96: 59.25 | W96: 14.59 | X96: 25.31 | Y96: 25.31 | Z96: 10.26 | AA96: 35.76 | AB96: 89.06 | AC96: 492.6 | AD96: 192.55 | AE96: 16.35 | AF96: 28.47 | AG96: 160.25 | AI96: 08/18/23 | AJ96: =AVERAGE(I96,AC96,AG96) -> 269.05667 | AK96: =AVERAGE(G96,AA96,AF96,) -> 481.7075 | AL96: =AVERAGE(AB96,X96,S96,Q96,O96,M96,J96,E96,) -> 149.93333
A97: 933 | B97: 08/17/23 | C97: 2023 | D97: 7183.5 | E97: 785.1 | F97: 402.65 | G97: 1875 | H97: 127.58 | I97: 154.64 | J97: 173.8 | K97: 144.74 | L97: 56.76 | M97: 146.09 | N97: 97.67 | O97: 58.62 | P97: 739 | Q97: 27.47 | R97: 101.58 | S97: 53.26 | T97: 11.37 | U97: 128.9 | V97: 59.88 | W97: 14.49 | X97: 25.48 | Y97: 25.48 | Z97: 10.22 | AA97: 35.73 | AB97: 89.02 | AC97: 498.3 | AD97: 192.4 | AE97: 16.47 | AF97: 28.52 | AG97: 158.1 | AI97: 08/17/23 | AJ97: =AVERAGE(I97,AC97,AG97) -> 270.34667 | AK97: =AVERAGE(G97,AA97,AF97,) -> 484.8125 | AL97: =AVERAGE(AB97,X97,S97,Q97,O97,M97,J97,E97,) -> 150.98222
A98: 932 | B98: 08/16/23 | C98: 2023 | D98: 7241.1 | E98: 802.9 | F98: 407.75 | G98: 1927.2 | H98: 128.68 | I98: 158.36 | J98: 174.9 | K98: 146.22 | L98: 56.32 | M98: 146.87 | N98: 96.33 | O98: 58.48 | P98: 753.5 | Q98: 27.41 | R98: 102.4 | S98: 53.73 | T98: 11.43 | U98: 131 | V98: 60.92 | W98: 14.5 | X98: 25.41 | Y98: 25.41 | Z98: 10.22 | AA98: 36.97 | AB98: 90.9 | AC98: 506.7 | AD98: 195.8 | AE98: 16.66 | AF98: 28.56 | AG98: 160.95 | AI98: 08/16/23 | AJ98: =AVERAGE(I98,AC98,AG98) -> 275.33667 | AK98: =AVERAGE(G98,AA98,AF98,) -> 498.1825 | AL98: =AVERAGE(AB98,X98,S98,Q98,O98,M98,J98,E98,) -> 153.4
... A100: 930 | B100: 08/14/23 | C100: 2023 | D100: 7309.94 | E100: 816.2 | F100: 415.5 | G100: 1928.4 | H100: 130.64 | I100: 160.04 | J100: 176.14 | K100: 147.66 | L100: 56.58 | M100: 147.96 | N100: 97.61 | O100: 59.68 | P100: 763.5 | Q100: 27.96 | R100: 103.48 | S100: 54.91 | T100: 11.58 | U100: 133.3 | V100: 61.08 | W100: 14.55 | X100: 25.61 | Y100: 25.61 | Z100: 10.32 | AA100: 37.01 | AB100: 92.04 | AC100: 514 | AD100: 198.25 | AE100: 16.9 | AF100: 28.48 | AG100: 162.9 | AI100: 08/14/23 | AJ100: =AVERAGE(I100,AC100,AG100) -> 278.98 | AK100: =AVERAGE(G100,AA100,AF100,) -> 498.4725 | AL100: =AVERAGE(AB100,X100,S100,Q100,O100,M100,J100,E100,) -> 155.61111
A101: 929 | B101: 45238 | C101: 2023 | D101: 7317.76 | E101: 820.4 | F101: 412.3 | G101: 1924.8 | H101: 130.74 | I101: 159.34 | J101: 175.3 | K101: 147.16 | L101: 57.17 | M101: 146.93 | N101: 97.07 | O101: 59.55 | P101: 770 | Q101: 27.84 | R101: 103.6 | S101: 54.53 | T101: 11.55 | U101: 135.65 | V101: 61 | W101: 14.49 | X101: 25.54 | Y101: 25.54 | Z101: 10.26 | AA101: 36.86 | AB101: 91.5 | AC101: 517.1 | AD101: 196.4 | AE101: 16.85 | AF101: 28.31 | AG101: 162.9 | AI101: 45238 | AJ101: =AVERAGE(I101,AC101,AG101) -> 279.78 | AK101: =AVERAGE(G101,AA101,AF101,) -> 497.4925 | AL101: =AVERAGE(AB101,X101,S101,Q101,O101,M101,J101,E101,) -> 155.73222
A102: 928 | B102: 45207 | C102: 2023 | D102: 7368.95 | E102: 834.7 | F102: 419.1 | G102: 1960.2 | H102: 132.04 | I102: 160.52 | J102: 178.16 | K102: 148.44 | L102: 57.82 | M102: 148.31 | N102: 97.86 | O102: 60.3 | P102: 781.5 | Q102: 28.17 | R102: 104.16 | S102: 55.06 | T102: 11.59 | U102: 136.55 | V102: 60.89 | W102: 14.64 | X102: 25.58 | Y102: 25.58 | Z102: 10.23 | AA102: 37.59 | AB102: 91.94 | AC102: 528.4 | AD102: 200.9 | AE102: 17.44 | AF102: 28.55 | AG102: 163.75 | AI102: 45207 | AJ102: =AVERAGE(I102,AC102,AG102) -> 284.22333 | AK102: =AVERAGE(G102,AA102,AF102,) -> 506.585 | AL102: =AVERAGE(AB102,X102,S102,Q102,O102,M102,J102,E102,) -> 158.02444
A103: 927 | B103: 45177 | C103: 2023 | D103: 7317.38 | E103: 807 | F103: 406.8 | G103: 1899.4 | H103: 131.68 | I103: 160.68 | J103: 175.52 | K103: 148.02 | L103: 57.04 | M103: 146.02 | N103: 96.59 | O103: 58.55 | P103: 761 | Q103: 27.66 | R103: 103.02 | S103: 54.91 | T103: 11.5 | U103: 137.8 | V103: 60.91 | W103: 14.56 | X103: 25.45 | Y103: 25.45 | Z103: 10.17 | AA103: 37.51 | AB103: 92 | AC103: 517 | AD103: 196.8 | AE103: 17.39 | AF103: 28.52 | AG103: 161.65 | AI103: 45177 | AJ103: =AVERAGE(I103,AC103,AG103) -> 279.77667 | AK103: =AVERAGE(G103,AA103,AF103,) -> 491.3575 | AL103: =AVERAGE(AB103,X103,S103,Q103,O103,M103,J103,E103,) -> 154.12333
...

Sheet Valo cloture
A1: Date | B1: CAC40 | C1: BNP | D1: CDI | E1: AXA | F1: DG | G1: BN | H1: ACA | I1: HO | J1: SGO | K1: ENGI | L1: GLE | M1: MC | N1: OR | O1: RMS | P1: AIR | Q1: SU | R1: EL | S1: SAF | T1: TTE | U1: AI | V1: SAN | W1: GLE | X1: SA | Y1: DSY | Z1: LR | AA1: KER | AB1: RI | AC1: STLAP | AD1: ML | AE1: CAP
A2: 12/29/23 | B2: 7530.93 | C2: 62.59 | D2: 707.5 | E2: 29.49 | F2: 113.7 | G2: 58.68 | H2: 12.85 | I2: 133.95 | J2: 66.66 | K2: 15.92 | L2: 24.03 | M2: 733.6 | N2: 450.65 | O2: 1918.8 | P2: 139.78 | Q2: 181.78 | R2: 181.6 | S2: 159.46 | T2: 61.6 | U2: 160.11 | V2: 89.76 | W2: 24.03 | X2: 10.3 | Y2: 44.24 | Z2: 94.1 | AA2: 399 | AB2: 159.75 | AC2: 21.15 | AD2: 32.46 | AE2: 188.75
A3: 12/28/23 | B3: 7531.71 | C3: 62.45 | D3: 705 | E3: 29.43 | F3: 113.56 | G3: 58.51 | H3: 12.86 | I3: 134.1 | J3: 66.39 | K3: 15.96 | L3: 24.04 | M3: 731 | N3: 451.3 | O3: 1910.8 | P3: 139.68 | Q3: 181.36 | R3: 180.96 | S3: 159.62 | T3: 61.41 | U3: 160.18 | V3: 89.26 | W3: 24.04 | X3: 10.31 | Y3: 44.26 | Z3: 94.2 | AA3: 398.25 | AB3: 160.3 | AC3: 21.18 | AD3: 32.36 | AE3: 189.8
A4: 12/27/23 | B4: 7560.54 | C4: 62.99 | D4: 703 | E4: 29.58 | F4: 114.44 | G4: 58.41 | H4: 12.91 | I4: 134.3 | J4: 66.7 | K4: 16.17 | L4: 24.31 | M4: 735.4 | N4: 448.7 | O4: 1929.6 | P4: 139.42 | Q4: 181.9 | R4: 181.2 | S4: 159.96 | T4: 62.47 | U4: 160.75 | V4: 89.17 | W4: 24.31 | X4: 10.38 | Y4: 44.78 | Z4: 94.62 | AA4: 402.8 | AB4: 161.3 | AC4: 21.24 | AD4: 32.35 | AE4: 191.1
A5: 12/22/23 | B5: 7557.58 | C5: 63.01 | D5: 707.5 | E5: 29.64 | F5: 114.38 | G5: 58.32 | H5: 12.85 | I5: 134.4 | J5: 66.63 | K5: 16.16 | L5: 24.08 | M5: 737.7 | N5: 447.55 | O5: 1941.2 | P5: 139.44 | Q5: 180.96 | R5: 181.74 | S5: 159.84 | T5: 62.3 | U5: 161.24 | V5: 89.34 | W5: 24.08 | X5: 10.47 | Y5: 44.64 | Z5: 94.6 | AA5: 397.8 | AB5: 160.8 | AC5: 21.21 | AD5: 32.41 | AE5: 188.45
A6: 12/21/23 | B6: 7537.81 | C6: 62.88 | D6: 715 | E6: 29.53 | F6: 113.64 | G6: 58.3 | H6: 12.8 | I6: 134.95 | J6: 66.11 | K6: 16.24 | L6: 24.04 | M6: 743.4 | N6: 448.2 | O6: 1992.2 | P6: 138.52 | Q6: 180.44 | R6: 181.26 | S6: 159.34 | T6: 62 | U6: 160.67 | V6: 88.96 | W6: 24.04 | X6: 10.45 | Y6: 44.68 | Z6: 95.16 | AA6: 401.65 | AB6: 160.8 | AC6: 21.23 | AD6: 32.52 | AE6: 189.1
A7: 12/20/23 | B7: 7552.29 | C7: 62.86 | D7: 715 | E7: 29.38 | F7: 113.62 | G7: 58.12 | H7: 12.87 | I7: 133.85 | J7: 66.37 | K7: 16.22 | L7: 24.05 | M7: 746.9 | N7: 449.25 | O7: 1999 | P7: 137.88 | Q7: 181.02 | R7: 181.74 | S7: 158.12 | T7: 62.15 | U7: 161.33 | V7: 89.17 | W7: 24.05 | X7: 10.46 | Y7: 44.73 | Z7: 94.86 | AA7: 406.45 | AB7: 161.65 | AC7: 21.22 | AD7: 32.45 | AE7: 190.05
A8: 12/19/23 | B8: 7553.08 | C8: 62.29 | D8: 716 | E8: 29.33 | F8: 113.3 | G8: 57.88 | H8: 12.78 | I8: 134.8 | J8: 65.62 | K8: 16.05 | L8: 23.97 | M8: 745.5 | N8: 450.75 | O8: 1996.6 | P8: 139.88 | Q8: 180.44 | R8: 183.18 | S8: 160.2 | T8: 61.99 | U8: 160.47 | V8: 88.93 | W8: 23.97 | X8: 10.38 | Y8: 44.39 | Z8: 94.5 | AA8: 405.95 | AB8: 162.1 | AC8: 21.29 | AD8: 32.16 | AE8: 191
A9: 12/18/23 | B9: 7548.18 | C9: 62.39 | D9: 714.5 | E9: 29.11 | F9: 112.96 | G9: 58.27 | H9: 12.83 | I9: 135.3 | J9: 65.02 | K9: 16.09 | L9: 24.19 | M9: 741.8 | N9: 447.45 | O9: 1996.8 | P9: 139.18 | Q9: 181.02 | R9: 183.76 | S9: 160.76 | T9: 62.35 | U9: 159.98 | V9: 88.61 | W9: 24.19 | X9: 10.45 | Y9: 44.19 | Z9: 96.18 | AA9: 407.35 | AB9: 162.05 | AC9: 21.5 | AD9: 32.17 | AE9: 192.45
A10: 12/15/23 | B10: 7587.68 | C10: 63.09 | D10: 717.5 | E10: 29.17 | F10: 115.58 | G10: 57.98 | H10: 12.93 | I10: 134.9 | J10: 66.61 | K10: 16.21 | L10: 24.43 | M10: 748.4 | N10: 446.55 | O10: 2023.5 | P10: 139.52 | Q10: 181.14 | R10: 185.24 | S10: 160.16 | T10: 61.63 | U10: 159.98 | V10: 87.7 | W10: 24.43 | X10: 10.56 | Y10: 44.29 | Z10: 96.9 | AA10: 417.85 | AB10: 163.05 | AC10: 21.53 | AD10: 32.26 | AE10: 195.9
A11: 12/14/23 | B11: 7547 | C11: 62.88 | D11: 722 | E11: 29.26 | F11: 116.02 | G11: 58.2 | H11: 12.9 | I11: 134.55 | J11: 66.1 | K11: 16.27 | L11: 24.49 | M11: 746.8 | N11: 443.55 | O11: 2017 | P11: 140.06 | Q11: 179 | R11: 185.08 | S11: 160.78 | T11: 61.41 | U11: 159.18 | V11: 88.02 | W11: 24.49 | X11: 10.67 | Y11: 43.82 | Z11: 96.5 | AA11: 427.05 | AB11: 162.65 | AC11: 21.25 | AD11: 32.04 | AE11: 193.15
A12: 12/13/23 | B12: 7529.11 | C12: 60.31 | D12: 709 | E12: 29.76 | F12: 114.78 | G12: 59.31 | H12: 12.6 | I12: 138.7 | J12: 62.57 | K12: 16.16 | L12: 23.66 | M12: 734.5 | N12: 445.45 | O12: 2027 | P12: 142.3 | Q12: 176.56 | R12: 185.42 | S12: 165.72 | T12: 61.36 | U12: 162.76 | V12: 88.54 | W12: 23.66 | X12: 10.8 | Y12: 44.42 | Z12: 94.46 | AA12: 409 | AB12: 155.7 | AC12: 20.91 | AD12: 31.72 | AE12: 191.9
A13: 45272 | B13: 7542.53 | C13: 60.82 | D13: 707.5 | E13: 30.07 | F13: 115.4 | G13: 59.55 | H13: 12.66 | I13: 137.45 | J13: 63.01 | K13: 15.99 | L13: 23.71 | M13: 733.6 | N13: 444.7 | O13: 2009.5 | P13: 142.68 | Q13: 176.96 | R13: 183.56 | S13: 167.48 | T13: 61.31 | U13: 162.09 | V13: 87.87 | W13: 23.71 | X13: 11.16 | Y13: 44.84 | Z13: 94.8 | AA13: 410.45 | AB13: 155.95 | AC13: 20.98 | AD13: 31.88 | AE13: 193.05
A14: 45242 | B14: 7527.58 | C14: 61.18 | D14: 710.5 | E14: 30.06 | F14: 116.1 | G14: 59.48 | H14: 12.65 | I14: 137.4 | J14: 62.47 | K14: 16.13 | L14: 23.82 | M14: 740 | N14: 443.85 | O14: 1997.8 | P14: 142.3 | Q14: 176.56 | R14: 183.22 | S14: 165.48 | T14: 61.97 | U14: 160.56 | V14: 87.8 | W14: 23.82 | X14: 11.1 | Y14: 44.4 | Z14: 94.94 | AA14: 409.5 | AB14: 157.05 | AC14: 21.01 | AD14: 32.2 | AE14: 192.9
A15: 45150 | B15: 7437.97 | C15: 61.85 | D15: 710 | E15: 30 | F15: 115.84 | G15: 59.22 | H15: 12.61 | I15: 138.95 | J15: 61.86 | K15: 16.23 | L15: 24.04 | M15: 739.1 | N15: 441.95 | O15: 1982.4 | P15: 141.82 | Q15: 174.94 | R15: 182.7 | S15: 164.6 | T15: 61.9 | U15: 159.38 | V15: 86.13 | W15: 24.04 | X15: 11.09 | Y15: 44.22 | Z15: 93.88 | AA15: 413.8 | AB15: 159.25 | AC15: 21.02 | AD15: 31.92 | AE15: 192.15
A16: 45119 | B16: 7415.66 | C16: 61.11 | D16: 687.5 | E16: 29.9 | F16: 115.68 | G16: 59.14 | H16: 12.45 | I16: 135.5 | J16: 61.21 | K16: 16.17 | L16: 23.7 | M16: 715.6 | N16: 438.75 | O16: 1953.4 | P16: 138.36 | Q16: 172.7 | R16: 181.06 | S16: 164.12 | T16: 60.67 | U16: 158.09 | V16: 85.1 | W16: 23.7 | X16: 11.14 | Y16: 43.83 | Z16: 92 | AA16: 403.4 | AB16: 157.55 | AC16: 20.92 | AD16: 31.83 | AE16: 190.5
A17: 45089 | B17: 7384.99 | C17: 60.66 | D17: 690 | E17: 29.67 | F17: 115.68 | G17: 58.72 | H17: 12.37 | I17: 136.2 | J17: 61.2 | K17: 16.09 | L17: 23.57 | M17: 718.6 | N17: 441.4 | O17: 1957.2 | P17: 138.3 | Q17: 172.6 | R17: 180.46 | S17: 163.98 | T17: 60.65 | U17: 157.69 | V17: 86.13 | W17: 23.57 | X17: 11.13 | Y17: 43.99 | Z17: 91.6 | AA17: 404.3 | AB17: 158.3 | AC17: 21.04 | AD17: 31.6 | AE17: 190.35
A18: 45058 | B18: 7320.49 | C18: 59.76 | D18: 684.5 | E18: 29.27 | F18: 115.3 | G18: 58.62 | H18: 12.17 | I18: 135.4 | J18: 60.6 | K18: 15.99 | L18: 23.32 | M18: 713.2 | N18: 439.75 | O18: 1933.2 | P18: 136.56 | Q18: 170.02 | R18: 179.66 | S18: 160.48 | T18: 61.37 | U18: 158.58 | V18: 86.4 | W18: 23.32 | X18: 11.17 | Y18: 43.54 | Z18: 89.78 | AA18: 398.6 | AB18: 159.2 | AC18: 20.45 | AD18: 31.4 | AE18: 189.05
A19: 45028 | B19: 7313.71 | C19: 58.47 | D19: 672.5 | E19: 29.05 | F19: 113.38 | G19: 58.79 | H19: 12.13 | I19: 136.6 | J19: 59.54 | K19: 16.05 | L19: 23.08 | M19: 698.7 | N19: 436.9 | O19: 1917.4 | P19: 137.02 | Q19: 168.08 | R19: 178.06 | S19: 161.26 | T19: 61.39 | U19: 156.62 | V19: 86.59 | W19: 23.08 | X19: 11.12 | Y19: 43.13 | Z19: 88.64 | AA19: 400.05 | AB19: 158.5 | AC19: 20.3 | AD19: 31.02 | AE19: 186.9
A20: 44938 | B20: 7313.19 | C20: 57.8 | D20: 676 | E20: 28.9 | F20: 113.32 | G20: 58.59 | H20: 12.07 | I20: 139.15 | J20: 59.83 | K20: 16.05 | L20: 22.9 | M20: 699.2 | N20: 436.15 | O20: 1915.2 | P20: 138.08 | Q20: 169.8 | R20: 178.12 | S20: 163.14 | T20: 62.36 | U20: 157.45 | V20: 85.78 | W20: 22.9 | X20: 11.38 | Y20: 43.31 | Z20: 89.42 | AA20: 392.9 | AB20: 158.15 | AC20: 20.09 | AD20: 31.05 | AE20: 187
A21: 11/30/23 | B21: 7255.04 | C21: 57.77 | D21: 676.5 | E21: 28.6 | F21: 112.3 | G21: 58.97 | H21: 12.02 | I21: 136.95 | J21: 59.81 | K21: 15.92 | L21: 23.08 | M21: 702.7 | N21: 431.05 | O21: 1904.2 | P21: 136.2 | Q21: 168.62 | R21: 175.12 | S21: 161.02 | T21: 62.26 | U21: 158 | V21: 85.46 | W21: 23.08 | X21: 11.3 | Y21: 42.97 | Z21: 88.42 | AA21: 393.7 | AB21: 158.55 | AC21: 19.91 | AD21: 30.81 | AE21: 188
A22: 11/29/23 | B22: 7241.41 | C22: 56.92 | D22: 670 | E22: 28.44 | F22: 112.12 | G22: 59.15 | H22: 11.8 | I22: 138.65 | J22: 59.42 | K22: 15.87 | L22: 22.74 | M22: 690.5 | N22: 431.85 | O22: 1897 | P22: 135.56 | Q22: 167.2 | R22: 177.24 | S22: 160.14 | T22: 61.68 | U22: 157.96 | V22: 84.87 | W22: 22.74 | X22: 11.26 | Y22: 43.13 | Z22: 88.16 | AA22: 391 | AB22: 155.75 | AC22: 19.7 | AD22: 30.84 | AE22: 188.55
A23: 11/28/23 | B23: 7213.74 | C23: 56.48 | D23: 664.5 | E23: 28.48 | F23: 111.12 | G23: 59.05 | H23: 11.75 | I23: 138.35 | J23: 58.51 | K23: 15.92 | L23: 22.52 | M23: 684.5 | N23: 430.7 | O23: 1911.8 | P23: 134.56 | Q23: 166.04 | R23: 176.58 | S23: 161.2 | T23: 63.19 | U23: 158.51 | V23: 85.76 | W23: 22.52 | X23: 11.3 | Y23: 42.82 | Z23: 88.76 | AA23: 394.05 | AB23: 158.05 | AC23: 18.72 | AD23: 30.11 | AE23: 182.6
A24: 11/27/23 | B24: 7265.49 | C24: 56.42 | D24: 680 | E24: 28.36 | F24: 110.54 | G24: 59.08 | H24: 11.73 | I24: 137.45 | J24: 58.02 | K24: 15.84 | L24: 22.49 | M24: 697.3 | N24: 432.95 | O24: 1951 | P24: 133.6 | Q24: 165.7 | R24: 177 | S24: 159.78 | T24: 62.86 | U24: 157.98 | V24: 86.63 | W24: 22.49 | X24: 11.24 | Y24: 42.64 | Z24: 88.74 | AA24: 404.5 | AB24: 162.35 | AC24: 18.73 | AD24: 29.81 | AE24: 181.2
A25: 11/24/23 | B25: 7268.58 | C25: 57.03 | D25: 686 | E25: 28.46 | F25: 110.48 | G25: 59.12 | H25: 11.75 | I25: 140.55 | J25: 58.23 | K25: 15.75 | L25: 22.69 | M25: 706.9 | N25: 431.45 | O25: 1951.2 | P25: 134.66 | Q25: 166.28 | R25: 178.04 | S25: 161.02 | T25: 63.14 | U25: 157.87 | V25: 86.38 | W25: 22.69 | X25: 11.17 | Y25: 42.63 | Z25: 88.92 | AA25: 406.45 | AB25: 163.95 | AC25: 18.79 | AD25: 29.9 | AE25: 182.05
A26: 11/23/23 | B26: 7263.67 | C26: 56.9 | D26: 691 | E26: 28.24 | F26: 109.98 | G26: 58.66 | H26: 11.7 | I26: 140.5 | J26: 57.86 | K26: 15.72 | L26: 22.58 | M26: 711.6 | N26: 429.25 | O26: 1959.8 | P26: 134.58 | Q26: 164.7 | R26: 177.74 | S26: 160.9 | T26: 62.81 | U26: 157.22 | V26: 86.24 | W26: 22.58 | X26: 11.12 | Y26: 42.84 | Z26: 88.08 | AA26: 405.95 | AB26: 167.3 | AC26: 18.67 | AD26: 29.85 | AE26: 182.55
A27: 11/22/23 | B27: 7243.83 | C27: 56.58 | D27: 688.5 | E27: 28.24 | F27: 109.72 | G27: 58.55 | H27: 11.73 | I27: 140.65 | J27: 58.25 | K27: 15.59 | L27: 22.42 | M27: 712.3 | N27: 429.65 | O27: 1974 | P27: 134 | Q27: 165.24 | R27: 178.92 | S27: 160.9 | T27: 61.85 | U27: 157.13 | V27: 84.92 | W27: 22.42 | X27: 11.08 | Y27: 42.78 | Z27: 88.14 | AA27: 403.8 | AB27: 168.3 | AC27: 18.56 | AD27: 29.82 | AE27: 183.2
A28: 11/21/23 | B28: 7214.39 | C28: 56.46 | D28: 682.5 | E28: 28.2 | F28: 109 | G28: 58.19 | H28: 11.75 | I28: 140.1 | J28: 57.82 | K28: 15.54 | L28: 22.41 | M28: 704.1 | N28: 425.65 | O28: 1950.2 | P28: 133.76 | Q28: 163.88 | R28: 176.98 | S28: 160.96 | T28: 62.95 | U28: 155.98 | V28: 85.34 | W28: 22.41 | X28: 11.04 | Y28: 42.46 | Z28: 87.58 | AA28: 399.45 | AB28: 165.95 | AC28: 18.53 | AD28: 29.48 | AE28: 177.75
A29: 11/20/23 | B29: 7236.02 | C29: 56.8 | D29: 692 | E29: 28.34 | F29: 108.96 | G29: 57.43 | H29: 11.8 | I29: 138.35 | J29: 57.8 | K29: 15.61 | L29: 22.62 | M29: 717.7 | N29: 421.75 | O29: 1941.6 | P29: 133.04 | Q29: 163.3 | R29: 176.58 | S29: 160.7 | T29: 63 | U29: 154.96 | V29: 85.42 | W29: 22.62 | X29: 11.03 | Y29: 42.55 | Z29: 87.32 | AA29: 403.2 | AB29: 165.65 | AC29: 18.89 | AD29: 29.73 | AE29: 179.3
A30: 11/17/23 | B30: 7196.69 | C30: 56.73 | D30: 687 | E30: 28.39 | F30: 109.38 | G30: 57.54 | H30: 11.77 | I30: 138.15 | J30: 58.37 | K30: 15.6 | L30: 22.61 | M30: 711.6 | N30: 423.95 | O30: 1924.6 | P30: 132.26 | Q30: 166.02 | R30: 179.38 | S30: 160.56 | T30: 61.81 | U30: 154.78 | V30: 85.89 | W30: 22.61 | X30: 11.08 | Y30: 42.05 | Z30: 87.56 | AA30: 404.3 | AB30: 167.35 | AC30: 18.46 | AD30: 29.65 | AE30: 177.9
A31: 11/16/23 | B31: 7168.4 | C31: 56.09 | D31: 679 | E31: 27.98 | F31: 108.36 | G31: 57.4 | H31: 11.66 | I31: 136.85 | J31: 57.35 | K31: 15.52 | L31: 22.28 | M31: 706.1 | N31: 421 | O31: 1923 | P31: 131.46 | Q31: 164.06 | R31: 177.88 | S31: 159.02 | T31: 60.96 | U31: 153.55 | V31: 84.82 | W31: 22.28 | X31: 10.99 | Y31: 41.66 | Z31: 86.9 | AA31: 399.1 | AB31: 166.55 | AC31: 18.5 | AD31: 29.25 | AE31: 177.75
A32: 11/15/23 | B32: 7198.91 | C32: 56.37 | D32: 696.5 | E32: 27.87 | F32: 109.04 | G32: 57.53 | H32: 11.69 | I32: 137.2 | J32: 57.73 | K32: 15.32 | L32: 22.25 | M32: 719 | N32: 423.9 | O32: 1931 | P32: 131.2 | Q32: 164.46 | R32: 178.18 | S32: 157.7 | T32: 62.61 | U32: 152.75 | V32: 83.65 | W32: 22.25 | X32: 10.91 | Y32: 41.94 | Z32: 86.54 | AA32: 410.15 | AB32: 168.35 | AC32: 18.88 | AD32: 29.57 | AE32: 175
... A34: 11/13/23 | B34: 7056.09 | C34: 55.79 | D34: 669.5 | E34: 28.05 | F34: 107.1 | G34: 58.03 | H34: 11.74 | I34: 141.1 | J34: 54.47 | K34: 15.32 | L34: 21.66 | M34: 688.5 | N34: 414.65 | O34: 1858 | P34: 130.24 | Q34: 160.74 | R34: 176.76 | S34: 155.1 | T34: 62.79 | U34: 152.42 | V34: 85.29 | W34: 21.66 | X34: 11.09 | Y34: 40.69 | Z34: 83.48 | AA34: 393.75 | AB34: 164.4 | AC34: 18.32 | AD34: 28.69 | AE34: 172.45
A35: 45210 | B35: 7006.09 | C35: 55.61 | D35: 670 | E35: 27.73 | F35: 106.56 | G35: 57.37 | H35: 11.71 | I35: 138.6 | J35: 54.23 | K35: 15.3 | L35: 21.26 | M35: 687.1 | N35: 414.25 | O35: 1845.4 | P35: 128.48 | Q35: 160.8 | R35: 174.9 | S35: 153.08 | T35: 62.04 | U35: 151.45 | V35: 85.14 | W35: 21.26 | X35: 11.05 | Y35: 40.49 | Z35: 83.6 | AA35: 393.1 | AB35: 164.3 | AC35: 17.99 | AD35: 28.48 | AE35: 171.85
A36: 45180 | B36: 7025.61 | C36: 56.09 | D36: 692.5 | E36: 27.68 | F36: 106.56 | G36: 57.38 | H36: 11.72 | I36: 137.1 | J36: 54.49 | K36: 15.31 | L36: 21.39 | M36: 714.4 | N36: 419 | O36: 1874.6 | P36: 127.86 | Q36: 163.36 | R36: 175.44 | S36: 153.5 | T36: 61.36 | U36: 151.02 | V36: 86.08 | W36: 21.39 | X36: 11.03 | Y36: 40.68 | Z36: 84.8 | AA36: 406.65 | AB36: 174.35 | AC36: 18.14 | AD36: 28.57 | AE36: 173.25
A37: 45149 | B37: 6950.95 | C37: 56.1 | D37: 687.5 | E37: 27.72 | F37: 105.66 | G37: 56.91 | H37: 11.72 | I37: 137.4 | J37: 53.13 | K37: 15.14 | L37: 21.42 | M37: 703.5 | N37: 415.45 | O37: 1851 | P37: 130.38 | Q37: 150.9 | R37: 174 | S37: 152.38 | T37: 60.78 | U37: 148.56 | V37: 86.13 | W37: 21.42 | X37: 10.97 | Y37: 40.05 | Z37: 82.24 | AA37: 403.25 | AB37: 172.2 | AC37: 18.32 | AD37: 28.34 | AE37: 171.6
A38: 45118 | B38: 6963.88 | C38: 55.95 | D38: 678.5 | E38: 27.43 | F38: 105.2 | G38: 56.85 | H38: 11.59 | I38: 136 | J38: 53.04 | K38: 15.3 | L38: 21.48 | M38: 697.5 | N38: 405.45 | O38: 1814.6 | P38: 129.2 | Q38: 149.42 | R38: 172.9 | S38: 150.2 | T38: 61.24 | U38: 147.82 | V38: 84.42 | W38: 21.48 | X38: 10.97 | Y38: 39.99 | Z38: 83.34 | AA38: 400.05 | AB38: 171.1 | AC38: 18.09 | AD38: 27.95 | AE38: 173
A39: 45088 | B39: 7006.53 | C39: 56.81 | D39: 677.5 | E39: 27.83 | F39: 105.5 | G39: 56.84 | H39: 11.67 | I39: 136.75 | J39: 53.33 | K39: 15.14 | L39: 21.67 | M39: 697.2 | N39: 403.15 | O39: 1812.4 | P39: 128.42 | Q39: 149.24 | R39: 172.66 | S39: 150 | T39: 62.66 | U39: 148.58 | V39: 84.94 | W39: 21.67 | X39: 11.1 | Y39: 39.92 | Z39: 82.92 | AA39: 398.7 | AB39: 172.35 | AC39: 18.34 | AD39: 28.22 | AE39: 168.75
A40: 44996 | B40: 7046.86 | C40: 56.64 | D40: 680.5 | E40: 28.17 | F40: 106.38 | G40: 57.05 | H40: 11.68 | I40: 135.1 | J40: 54.27 | K40: 15.15 | L40: 21.8 | M40: 702.8 | N40: 403.7 | O40: 1814.6 | P40: 129.06 | Q40: 150.7 | R40: 174.24 | S40: 150.06 | T40: 62.33 | U40: 148.35 | V40: 85.35 | W40: 21.8 | X40: 11.14 | Y40: 39.44 | Z40: 83.5 | AA40: 407.25 | AB40: 173.45 | AC40: 18.7 | AD40: 28.24 | AE40: 173.55
A41: 44968 | B41: 6982.04 | C41: 55.56 | D41: 676 | E41: 28.52 | F41: 106.18 | G41: 57.11 | H41: 11.55 | I41: 137.45 | J41: 53.26 | K41: 15.16 | L41: 21.62 | M41: 701.1 | N41: 403.25 | O41: 1819.2 | P41: 129.06 | Q41: 149.48 | R41: 175.58 | S41: 151.86 | T41: 64.59 | U41: 150 | V41: 87.2 | W41: 21.62 | X41: 11.2 | Y41: 39.05 | Z41: 83.24 | AA41: 395.8 | AB41: 172.05 | AC41: 18.35 | AD41: 28.29 | AE41: 171.5
A42: 44937 | B42: 6873.55 | C42: 54.4 | D42: 651.5 | E42: 28.29 | F42: 105.36 | G42: 57.17 | H42: 11.42 | I42: 138.35 | J42: 51.51 | K42: 15.35 | L42: 21.22 | M42: 675.3 | N42: 397 | O42: 1773.8 | P42: 127.94 | Q42: 145.22 | R42: 171.42 | S42: 149.78 | T42: 63.63 | U42: 148.05 | V42: 86.85 | W42: 21.22 | X42: 11.19 | Y42: 39 | Z42: 81.9 | AA42: 382 | AB42: 168.1 | AC42: 17.93 | AD42: 27.92 | AE42: 167.65
A43: 10/31/23 | B43: 6831.67 | C43: 54.29 | D43: 652 | E43: 27.96 | F43: 104.48 | G43: 56.15 | H43: 11.38 | I43: 139.15 | J43: 51.4 | K43: 15 | L43: 21.15 | M43: 674.5 | N43: 396.15 | O43: 1759.6 | P43: 126.28 | Q43: 144.98 | R43: 170.64 | S43: 147.02 | T43: 63.2 | U43: 146.98 | V43: 85.7 | W43: 21.15 | X43: 11.11 | Y43: 38.82 | Z43: 81.48 | AA43: 383.2 | AB43: 167.5 | AC43: 17.61 | AD43: 28.02 | AE43: 166.5
A44: 10/30/23 | B44: 6809.84 | C44: 53.72 | D44: 647.5 | E44: 27.84 | F44: 103.08 | G44: 55.7 | H44: 11.23 | I44: 141.1 | J44: 51.3 | K44: 14.99 | L44: 20.81 | M44: 671 | N44: 392.05 | O44: 1752.4 | P44: 126.2 | Q44: 142.84 | R44: 168.28 | S44: 148.1 | T44: 62.99 | U44: 145.25 | V44: 84.14 | W44: 20.81 | X44: 11.06 | Y44: 38.72 | Z44: 81.54 | AA44: 383 | AB44: 166.2 | AC44: 17.05 | AD44: 28 | AE44: 161.7
A45: 10/27/23 | B45: 6784.62 | C45: 54.67 | D45: 636.5 | E45: 27.46 | F45: 102 | G45: 55.17 | H45: 11.17 | I45: 141.05 | J45: 51.44 | K45: 14.92 | L45: 20.73 | M45: 661.4 | N45: 390.55 | O45: 1748.8 | P45: 124.96 | Q45: 143.06 | R45: 168.02 | S45: 146.66 | T45: 63 | U45: 145.67 | V45: 81.44 | W45: 20.73 | X45: 11.01 | Y45: 37.86 | Z45: 81.22 | AA45: 383.5 | AB45: 165 | AC45: 17.32 | AD45: 27.75 | AE45: 160.7
A46: 10/26/23 | B46: 6825.59 | C46: 54.72 | D46: 642 | E46: 27.52 | F46: 100.48 | G46: 56.2 | H46: 11.21 | I46: 142 | J46: 49.91 | K46: 14.9 | L46: 20.74 | M46: 668.4 | N46: 393.15 | O46: 1738.8 | P46: 126.44 | Q46: 140.02 | R46: 165.7 | S46: 147.74 | T46: 62.48 | U46: 144.16 | V46: 100.46 | W46: 20.74 | X46: 10.93 | Y46: 38 | Z46: 80.34 | AA46: 384.4 | AB46: 168.25 | AC46: 17.66 | AD46: 27.68 | AE46: 163.35
A47: 10/25/23 | B47: 6846.51 | C47: 56.18 | D47: 647.5 | E47: 27.59 | F47: 100.76 | G47: 54.87 | H47: 11.26 | I47: 142.05 | J47: 49.91 | K47: 14.85 | L47: 20.91 | M47: 679.1 | N47: 399.2 | O47: 1776.4 | P47: 125.04 | Q47: 139.98 | R47: 168.58 | S47: 148.48 | T47: 62.2 | U47: 142.49 | V47: 101.02 | W47: 20.91 | X47: 10.88 | Y47: 37.77 | Z47: 81.02 | AA47: 393.3 | AB47: 169.7 | AC47: 17.79 | AD47: 27.28 | AE47: 165.05
A48: 10/24/23 | B48: 6833.91 | C48: 55.91 | D48: 652.5 | E48: 27.34 | F48: 101.08 | G48: 54.26 | H48: 11.2 | I48: 141.6 | J48: 50.06 | K48: 14.73 | L48: 20.87 | M48: 681 | N48: 394.1 | O48: 1728 | P48: 125.16 | Q48: 139.42 | R48: 167.44 | S48: 148.62 | T48: 62.03 | U48: 139.84 | V48: 98.94 | W48: 20.87 | X48: 10.84 | Y48: 34.98 | Z48: 80.64 | AA48: 407.45 | AB48: 170 | AC48: 17.72 | AD48: 27.58 | AE48: 165.2
A49: 10/23/23 | B49: 6773.82 | C49: 56.13 | D49: 635 | E49: 27.25 | F49: 99.9 | G49: 53.9 | H49: 11.32 | I49: 139.3 | J49: 50.17 | K49: 14.5 | L49: 21.05 | M49: 669.4 | N49: 386.85 | O49: 1681.2 | P49: 122.5 | Q49: 141.92 | R49: 165.5 | S49: 146.66 | T49: 62.3 | U49: 139.02 | V49: 98.31 | W49: 21.05 | X49: 10.76 | Y49: 34.07 | Z49: 81.4 | AA49: 403.5 | AB49: 167.2 | AC49: 18.02 | AD49: 27.85 | AE49: 164.1
A50: 10/20/23 | B50: 6816.17 | C50: 55.56 | D50: 632.5 | E50: 27.16 | F50: 99.62 | G50: 54.1 | H50: 11.22 | I50: 137.85 | J50: 49.76 | K50: 14.69 | L50: 20.98 | M50: 664 | N50: 380.25 | O50: 1654.2 | P50: 121.26 | Q50: 141.44 | R50: 163.06 | S50: 144.94 | T50: 62.57 | U50: 138.75 | V50: 98.83 | W50: 20.98 | X50: 10.84 | Y50: 33.96 | Z50: 80.86 | AA50: 402.8 | AB50: 165.95 | AC50: 17.65 | AD50: 27.78 | AE50: 163.2
A51: 10/19/23 | B51: 6875.77 | C51: 56.71 | D51: 642.5 | E51: 27.88 | F51: 100.6 | G51: 54.08 | H51: 11.38 | I51: 138.3 | J51: 50.24 | K51: 14.87 | L51: 21.4 | M51: 670.6 | N51: 386.2 | O51: 1680 | P51: 123.9 | Q51: 145.74 | R51: 162.14 | S51: 148.46 | T51: 63.33 | U51: 142.76 | V51: 98.81 | W51: 21.4 | X51: 10.91 | Y51: 34.85 | Z51: 83.12 | AA51: 410.65 | AB51: 166.15 | AC51: 18.1 | AD51: 28.45 | AE51: 164.4
A52: 10/18/23 | B52: 6954.1 | C52: 57.31 | D52: 640.5 | E52: 28.16 | F52: 100.82 | G52: 54.58 | H52: 11.44 | I52: 141.55 | J52: 51.23 | K52: 14.72 | L52: 21.63 | M52: 667.7 | N52: 383.1 | O52: 1686 | P52: 124.72 | Q52: 147.1 | R52: 163.62 | S52: 149.6 | T52: 63.78 | U52: 143.02 | V52: 101.36 | W52: 21.63 | X52: 11 | Y52: 35.31 | Z52: 83.98 | AA52: 409.45 | AB52: 158.6 | AC52: 18.78 | AD52: 28.77 | AE52: 164.3
A53: 10/17/23 | B53: 6969.07 | C53: 57.68 | D53: 645 | E53: 28.28 | F53: 102.76 | G53: 54.44 | H53: 11.54 | I53: 142.25 | J53: 53.37 | K53: 14.89 | L53: 21.8 | M53: 668.4 | N53: 387.4 | O53: 1689 | P53: 127.3 | Q53: 151.9 | R53: 164.44 | S53: 151.96 | T53: 63.18 | U53: 144.85 | V53: 102.94 | W53: 21.8 | X53: 10.94 | Y53: 35.41 | Z53: 85.58 | AA53: 409.5 | AB53: 160.15 | AC53: 18.88 | AD53: 29.18 | AE53: 164.55
A54: 10/16/23 | B54: 6963.02 | C54: 57.83 | D54: 644 | E54: 28.02 | F54: 102.38 | G54: 54.13 | H54: 11.54 | I54: 143.2 | J54: 53.64 | K54: 14.81 | L54: 21.95 | M54: 667.1 | N54: 386.75 | O54: 1703.8 | P54: 122.94 | Q54: 152.16 | R54: 165.62 | S54: 150.46 | T54: 63.06 | U54: 146 | V54: 103.88 | W54: 21.95 | X54: 10.93 | Y54: 35.84 | Z54: 85.62 | AA54: 410 | AB54: 159.2 | AC54: 18.69 | AD54: 29.35 | AE54: 166.15
A55: 10/13/23 | B55: 6997.48 | C55: 57.64 | D55: 640 | E55: 28.01 | F55: 102.92 | G55: 54 | H55: 11.4 | I55: 144.4 | J55: 53.21 | K55: 14.78 | L55: 21.81 | M55: 660.6 | N55: 384.65 | O55: 1705.8 | P55: 121.96 | Q55: 153.12 | R55: 164.1 | S55: 149.08 | T55: 63.17 | U55: 146.69 | V55: 103.38 | W55: 21.81 | X55: 11.04 | Y55: 35.91 | Z55: 85.62 | AA55: 406.8 | AB55: 157.1 | AC55: 18.82 | AD55: 29.03 | AE55: 165.7
A56: 45270 | B56: 7097.53 | C56: 59.44 | D56: 652 | E56: 28.36 | F56: 104.78 | G56: 54.19 | H56: 11.68 | I56: 142.8 | J56: 54.5 | K56: 14.68 | L56: 22.47 | M56: 675 | N56: 393.2 | O56: 1725.8 | P56: 125.76 | Q56: 156.3 | R56: 166.44 | S56: 152.16 | T56: 62.17 | U56: 148.71 | V56: 103.98 | W56: 22.47 | X56: 10.94 | Y56: 36.94 | Z56: 88.18 | AA56: 416.8 | AB56: 159.25 | AC56: 18.92 | AD56: 29.65 | AE56: 169.6
A57: 45240 | B57: 7080.01 | C57: 60.24 | D57: 671.5 | E57: 28.56 | F57: 105.5 | G57: 54.65 | H57: 11.68 | I57: 139 | J57: 55.04 | K57: 14.73 | L57: 22.6 | M57: 686.1 | N57: 396.8 | O57: 1751 | P57: 126.32 | Q57: 157.26 | R57: 166.52 | S57: 152.06 | T57: 61.69 | U57: 148.45 | V57: 103.32 | W57: 22.6 | X57: 11.01 | Y57: 37.05 | Z57: 87.6 | AA57: 427.95 | AB57: 160.3 | AC57: 18.93 | AD57: 29.48 | AE57: 170.05
A58: 45209 | B58: 7085.13 | C58: 59.83 | D58: 704.5 | E58: 28.32 | F58: 104.12 | G58: 54.12 | H58: 11.63 | I58: 135.4 | J58: 55.14 | K58: 14.57 | L58: 22.61 | M58: 733.5 | N58: 397.75 | O58: 1777.6 | P58: 125.6 | Q58: 156.7 | R58: 166 | S58: 150.4 | T58: 61.89 | U58: 147.04 | V58: 102.68 | W58: 22.61 | X58: 11 | Y58: 36.79 | Z58: 86.98 | AA58: 434.1 | AB58: 160 | AC58: 18.53 | AD58: 29.57 | AE58: 168.5
A59: 45179 | B59: 6980.33 | C59: 59.03 | D59: 687 | E59: 27.88 | F59: 102.22 | G59: 52.71 | H59: 11.46 | I59: 134 | J59: 54.06 | K59: 14.28 | L59: 22.36 | M59: 710.7 | N59: 387.05 | O59: 1727.8 | P59: 123.08 | Q59: 152.6 | R59: 163.3 | S59: 145.86 | T59: 61.39 | U59: 143.91 | V59: 102.58 | W59: 22.36 | X59: 11 | Y59: 35.82 | Z59: 85.64 | AA59: 419.65 | AB59: 157.15 | AC59: 18 | AD59: 29.14 | AE59: 164.05
A60: 45087 | B60: 6981.49 | C60: 59.98 | D60: 703.5 | E60: 27.97 | F60: 102.32 | G60: 51.31 | H60: 11.68 | I60: 128 | J60: 54.47 | K60: 14.13 | L60: 22.7 | M60: 729.7 | N60: 394.2 | O60: 1756.4 | P60: 124.28 | Q60: 155.58 | R60: 164.06 | S60: 144.78 | T60: 60.34 | U60: 143.49 | V60: 102.2 | W60: 22.7 | X60: 10.98 | Y60: 36.33 | Z60: 86.32 | AA60: 425.35 | AB60: 158.6 | AC60: 17.99 | AD60: 29.18 | AE60: 165.3
A61: 45056 | B61: 6970.59 | C61: 59.2 | D61: 696 | E61: 27.32 | F61: 101.58 | G61: 51.91 | H61: 11.42 | I61: 128.1 | J61: 53.52 | K61: 14.14 | L61: 22.42 | M61: 720.6 | N61: 391.35 | O61: 1731.8 | P61: 123.52 | Q61: 154.14 | R61: 163 | S61: 143.22 | T61: 59.77 | U61: 142.4 | V61: 102.86 | W61: 22.42 | X61: 10.99 | Y61: 35.24 | Z61: 85.76 | AA61: 421.45 | AB61: 159.95 | AC61: 17.84 | AD61: 28.73 | AE61: 162.7
A62: 45026 | B62: 6948.03 | C62: 58.64 | D62: 690 | E62: 27.21 | F62: 101.9 | G62: 51.61 | H62: 11.35 | I62: 128.6 | J62: 54.11 | K62: 14.03 | L62: 22.43 | M62: 712.5 | N62: 392.05 | O62: 1731 | P62: 123.54 | Q62: 153.82 | R62: 163.12 | S62: 143.76 | T62: 60.09 | U62: 142.35 | V62: 101.82 | W62: 22.43 | X62: 10.99 | Y62: 35.23 | Z62: 85.76 | AA62: 421.45 | AB62: 159.7 | AC62: 17.72 | AD62: 28.5 | AE62: 164.6
A63: 44995 | B63: 6989.77 | C63: 58.8 | D63: 685 | E63: 27.31 | F63: 101.16 | G63: 51.89 | H63: 11.39 | I63: 131.1 | J63: 54.12 | K63: 14 | L63: 22.43 | M63: 705.3 | N63: 391.85 | O63: 1705.6 | P63: 124.32 | Q63: 154.66 | R63: 162.42 | S63: 144.8 | T63: 61.28 | U63: 141.96 | V63: 101.56 | W63: 22.43 | X63: 10.78 | Y63: 35.19 | Z63: 87.18 | AA63: 421.65 | AB63: 158.9 | AC63: 17.81 | AD63: 28.59 | AE63: 160.9
A64: 44967 | B64: 7035.65 | C64: 59.69 | D64: 694 | E64: 27.69 | F64: 103.72 | G64: 51.57 | H64: 11.54 | I64: 131.85 | J64: 54.71 | K64: 14.28 | L64: 22.86 | M64: 714.9 | N64: 393.7 | O64: 1725.8 | P64: 125.56 | Q64: 154.78 | R64: 163.66 | S64: 146.28 | T64: 61.55 | U64: 142.98 | V64: 101.82 | W64: 22.86 | X64: 10.9 | Y64: 35.71 | Z64: 87.24 | AA64: 429.3 | AB64: 157 | AC64: 18.1 | AD64: 29.15 | AE64: 164.7
A65: 09/29/23 | B65: 7135.06 | C65: 60.43 | D65: 697 | E65: 28.18 | F65: 105.02 | G65: 52.26 | H65: 11.69 | I65: 133.1 | J65: 56.88 | K65: 14.53 | L65: 23.05 | M65: 716.4 | N65: 393.2 | O65: 1729.8 | P65: 126.98 | Q65: 156.98 | R65: 165.16 | S65: 148.64 | T65: 62.31 | U65: 145.31 | V65: 101.48 | W65: 23.05 | X65: 10.86 | Y65: 35.3 | Z65: 87.3 | AA65: 431.9 | AB65: 157.85 | AC65: 18.2 | AD65: 29.07 | AE65: 165.8
A66: 09/28/23 | B66: 7042.74 | C66: 60.47 | D66: 681.5 | E66: 28.35 | F66: 105.22 | G66: 51.45 | H66: 11.65 | I66: 133.6 | J66: 56.87 | K66: 14.39 | L66: 22.93 | M66: 706 | N66: 390.3 | O66: 1719.8 | P66: 126.74 | Q66: 156.5 | R66: 164.16 | S66: 149.86 | T66: 63.62 | U66: 145.4 | V66: 100.76 | W66: 22.93 | X66: 10.8 | Y66: 34.64 | Z66: 85.5 | AA66: 429.45 | AB66: 158.35 | AC66: 18.16 | AD66: 29.02 | AE66: 164.15
A67: 09/27/23 | B67: 7053.11 | C67: 60.11 | D67: 673.5 | E67: 28.3 | F67: 104.42 | G67: 51.66 | H67: 11.5 | I67: 133.2 | J67: 56.23 | K67: 14.51 | L67: 22.89 | M67: 698.7 | N67: 386.7 | O67: 1696.6 | P67: 124 | Q67: 155.32 | R67: 162.64 | S67: 149.48 | T67: 62.93 | U67: 144.07 | V67: 101.68 | W67: 22.89 | X67: 10.82 | Y67: 34.68 | Z67: 85.04 | AA67: 427.25 | AB67: 159.45 | AC67: 17.85 | AD67: 28.92 | AE67: 165.45
A68: 09/26/23 | B68: 7033.83 | C68: 60.23 | D68: 668 | E68: 28.65 | F68: 104.06 | G68: 52.5 | H68: 11.44 | I68: 132.65 | J68: 56.35 | K68: 14.74 | L68: 22.62 | M68: 703 | N68: 387.55 | O68: 1707 | P68: 123.58 | Q68: 152.92 | R68: 163.22 | S68: 147.24 | T68: 61.91 | U68: 144.64 | V68: 102.78 | W68: 22.62 | X68: 10.99 | Y68: 34.39 | Z68: 84.82 | AA68: 429.95 | AB68: 161 | AC68: 17.99 | AD68: 29.05 | AE68: 164.05
A69: 09/25/23 | B69: 7087.63 | C69: 60.42 | D69: 678 | E69: 28.62 | F69: 104.54 | G69: 52.41 | H69: 11.45 | I69: 132.75 | J69: 56.23 | K69: 14.84 | L69: 22.97 | M69: 713.3 | N69: 391.5 | O69: 1732.8 | P69: 122.96 | Q69: 155.38 | R69: 165.78 | S69: 147.14 | T69: 62.13 | U69: 145.69 | V69: 102.64 | W69: 22.97 | X69: 10.99 | Y69: 34.95 | Z69: 85.02 | AA69: 439.55 | AB69: 162.2 | AC69: 18.06 | AD69: 29.43 | AE69: 165.65
A70: 09/22/23 | B70: 7133.65 | C70: 60.74 | D70: 699 | E70: 28.82 | F70: 105.34 | G70: 53.02 | H70: 11.5 | I70: 132.7 | J70: 56.13 | K70: 14.96 | L70: 23.12 | M70: 732.3 | N70: 398.35 | O70: 1793 | P70: 123.88 | Q70: 154.14 | R70: 167.96 | S70: 147.2 | T70: 61.91 | U70: 145.95 | V70: 102.1 | W70: 23.12 | X70: 11.09 | Y70: 35.01 | Z70: 84.44 | AA70: 460.45 | AB70: 166.3 | AC70: 18.28 | AD70: 29.5 | AE70: 166.75
A71: 09/21/23 | B71: 7199.11 | C71: 61.65 | D71: 694.5 | E71: 29.15 | F71: 106.18 | G71: 53.56 | H71: 11.68 | I71: 134.5 | J71: 56.93 | K71: 14.94 | L71: 23.49 | M71: 729.3 | N71: 399.7 | O71: 1766.6 | P71: 125.52 | Q71: 155 | R71: 169.42 | S71: 148.04 | T71: 61.88 | U71: 146 | V71: 102.5 | W71: 23.49 | X71: 11.29 | Y71: 34.51 | Z71: 86 | AA71: 453.6 | AB71: 166.45 | AC71: 18.16 | AD71: 30.16 | AE71: 168.05
A72: 09/20/23 | B72: 7272.68 | C72: 62.07 | D72: 702 | E72: 29.35 | F72: 107.68 | G72: 54.08 | H72: 11.8 | I72: 137.3 | J72: 57.94 | K72: 15.17 | L72: 23.83 | M72: 736.7 | N72: 410 | O72: 1876.4 | P72: 129.64 | Q72: 157.96 | R72: 175.34 | S72: 152.04 | T72: 62.29 | U72: 147.42 | V72: 103.8 | W72: 23.83 | X72: 11.25 | Y72: 35.22 | Z72: 87.68 | AA72: 457.6 | AB72: 168.7 | AC72: 18.61 | AD72: 30.29 | AE72: 168.9
A73: 09/19/23 | B73: 7247.02 | C73: 61.11 | D73: 698.5 | E73: 29.31 | F73: 106.24 | G73: 53.56 | H73: 11.65 | I73: 139.55 | J73: 57.23 | K73: 15.29 | L73: 23.14 | M73: 736.8 | N73: 400.35 | O73: 1845.6 | P73: 129.28 | Q73: 155.64 | R73: 171.86 | S73: 151.74 | T73: 63.04 | U73: 149.84 | V73: 102.1 | W73: 23.14 | X73: 11.17 | Y73: 34.67 | Z73: 87.5 | AA73: 456.85 | AB73: 168.45 | AC73: 18.05 | AD73: 30.36 | AE73: 166.5
A74: 09/18/23 | B74: 7255.03 | C74: 60.11 | D74: 707 | E74: 29.07 | F74: 106.24 | G74: 53.81 | H74: 11.55 | I74: 138.95 | J74: 56.95 | K74: 15.1 | L74: 23.28 | M74: 742.5 | N74: 404.4 | O74: 1874.4 | P74: 130.04 | Q74: 156.92 | R74: 173.42 | S74: 151.7 | T74: 61.99 | U74: 149.4 | V74: 101.68 | W74: 23.28 | X74: 11.1 | Y74: 35.27 | Z74: 88.24 | AA74: 459.45 | AB74: 169.25 | AC74: 17.79 | AD74: 30.11 | AE74: 165.95
A75: 09/15/23 | B75: 7366.21 | C75: 61.46 | D75: 720.5 | E75: 29.39 | F75: 107.48 | G75: 53.79 | H75: 11.84 | I75: 139.5 | J75: 57.24 | K75: 15.2 | L75: 26.47 | M75: 761.2 | N75: 410 | O75: 1903.6 | P75: 131.32 | Q75: 157.44 | R75: 175.32 | S75: 152.42 | T75: 62.37 | U75: 152.78 | V75: 102.8 | W75: 26.47 | X75: 11.06 | Y75: 35.34 | Z75: 88.38 | AA75: 469.1 | AB75: 171.9 | AC75: 17.88 | AD75: 30.27 | AE75: 170.1
A76: 09/14/23 | B76: 7184.25 | C76: 61.3 | D76: 713.5 | E76: 29.15 | F76: 106.24 | G76: 53.49 | H76: 11.71 | I76: 138.05 | J76: 56.57 | K76: 15.15 | L76: 26.56 | M76: 742.6 | N76: 402 | O76: 1876 | P76: 130.4 | Q76: 155.78 | R76: 176.24 | S76: 150.6 | T76: 62.28 | U76: 150.91 | V76: 102.42 | W76: 26.56 | X76: 10.98 | Y76: 35.24 | Z76: 86.96 | AA76: 461 | AB76: 171.4 | AC76: 17.58 | AD76: 29.8 | AE76: 167.85
A77: 09/13/23 | B77: 7184.56 | C77: 59.89 | D77: 697 | E77: 28.58 | F77: 104.02 | G77: 53.2 | H77: 11.54 | I77: 139.85 | J77: 56.21 | K77: 14.9 | L77: 26.2 | M77: 729.6 | N77: 397.5 | O77: 1836.2 | P77: 130.52 | Q77: 153.38 | R77: 173.92 | S77: 148.5 | T77: 61.23 | U77: 149.42 | V77: 101.5 | W77: 26.2 | X77: 10.92 | Y77: 35.25 | Z77: 86.56 | AA77: 461.85 | AB77: 171.85 | AC77: 17.76 | AD77: 29.7 | AE77: 167.05
A78: 45269 | B78: 7241.99 | C78: 59.87 | D78: 700.5 | E78: 28.15 | F78: 105.16 | G78: 53.53 | H78: 11.45 | I78: 139.85 | J78: 56.99 | K78: 14.88 | L78: 25.95 | M78: 734.4 | N78: 401.3 | O78: 1836.2 | P78: 130.48 | Q78: 156.64 | R78: 173.8 | S78: 149.12 | T78: 61.29 | U78: 150.09 | V78: 101.68 | W78: 25.95 | X78: 10.97 | Y78: 35.64 | Z78: 88.14 | AA78: 463.7 | AB78: 171.55 | AC78: 17.82 | AD78: 29.84 | AE78: 169.25
A79: 45239 | B79: 7253.65 | C79: 59.51 | D79: 711 | E79: 27.96 | F79: 103.58 | G79: 54.2 | H79: 11.3 | I79: 139.35 | J79: 57.37 | K79: 14.89 | L79: 25.72 | M79: 742.2 | N79: 407.15 | O79: 1855.6 | P79: 133.66 | Q79: 157.4 | R79: 174.24 | S79: 150.08 | T79: 60.74 | U79: 151.6 | V79: 101.82 | W79: 25.72 | X79: 10.92 | Y79: 36.37 | Z79: 88.14 | AA79: 468.15 | AB79: 173.4 | AC79: 17.37 | AD79: 29.89 | AE79: 170.4
A80: 45147 | B80: 7136.56 | C80: 58.43 | D80: 714 | E80: 27.71 | F80: 102.96 | G80: 53.57 | H80: 11.16 | I80: 138.7 | J80: 57.37 | K80: 14.83 | L80: 25.28 | M80: 740 | N80: 404.25 | O80: 1849.4 | P80: 135.44 | Q80: 157.12 | R80: 173.34 | S80: 148.54 | T80: 60.38 | U80: 150.44 | V80: 100.34 | W80: 25.28 | X80: 10.79 | Y80: 36.45 | Z80: 90.76 | AA80: 469.7 | AB80: 174.5 | AC80: 16.99 | AD80: 29.52 | AE80: 170.3
A81: 45116 | B81: 7165.98 | C81: 58.57 | D81: 701.5 | E81: 27.53 | F81: 102.5 | G81: 53.22 | H81: 11.21 | I81: 137.3 | J81: 57.28 | K81: 14.66 | L81: 25.42 | M81: 724.1 | N81: 398.4 | O81: 1834.4 | P81: 136.42 | Q81: 156.98 | R81: 173.36 | S81: 148.46 | T81: 59.88 | U81: 150.56 | V81: 99.68 | W81: 25.42 | X81: 10.78 | Y81: 36.41 | Z81: 90.86 | AA81: 462.85 | AB81: 174.45 | AC81: 16.95 | AD81: 29.95 | AE81: 168.2
A82: 45086 | B82: 7168.84 | C82: 58.6 | D82: 710 | E82: 27.59 | F82: 102.36 | G82: 52.73 | H82: 11.26 | I82: 136.7 | J82: 57.71 | K82: 14.5 | L82: 25.53 | M82: 731.5 | N82: 398.2 | O82: 1833.4 | P82: 133.94 | Q82: 157.74 | R82: 172.22 | S82: 146.04 | T82: 59.51 | U82: 149.69 | V82: 98.24 | W82: 25.53 | X82: 10.55 | Y82: 36.57 | Z82: 91.36 | AA82: 468.7 | AB82: 176.6 | AC82: 16.92 | AD82: 30.09 | AE82: 170.45
A83: 45055 | B83: 7183.8 | C83: 59.39 | D83: 728 | E83: 27.84 | F83: 102.1 | G83: 52.79 | H83: 11.36 | I83: 137.15 | J83: 57.59 | K83: 14.58 | L83: 25.68 | M83: 759.1 | N83: 403.85 | O83: 1868.2 | P83: 134.1 | Q83: 156.72 | R83: 174.2 | S83: 145.7 | T83: 59.9 | U83: 148.89 | V83: 99.03 | W83: 25.68 | X83: 10.38 | Y83: 36.66 | Z83: 90.26 | AA83: 479.8 | AB83: 179.1 | AC83: 16.91 | AD83: 29.78 | AE83: 172.35
A84: 45025 | B84: 7267.25 | C84: 59.44 | D84: 751.5 | E84: 27.73 | F84: 102.78 | G84: 53.37 | H84: 11.59 | I84: 136.7 | J84: 58.36 | K84: 14.75 | L84: 25.84 | M84: 772.6 | N84: 405.75 | O84: 1882.4 | P84: 134.18 | Q84: 157.26 | R84: 175.32 | S84: 146.08 | T84: 58.72 | U84: 151.33 | V84: 98.03 | W84: 25.84 | X84: 10.38 | Y84: 36.68 | Z84: 90.76 | AA84: 490.55 | AB84: 181 | AC84: 16.81 | AD84: 29.2 | AE84: 171.3
A85: 44935 | B85: 7294.49 | C85: 59.59 | D85: 750 | E85: 27.85 | F85: 102.72 | G85: 53.76 | H85: 11.65 | I85: 135.25 | J85: 60.25 | K85: 14.82 | L85: 26.28 | M85: 775.8 | N85: 405.2 | O85: 1885.8 | P85: 133.86 | Q85: 157.44 | R85: 174.18 | S85: 146.06 | T85: 58.89 | U85: 152.02 | V85: 98.61 | W85: 26.28 | X85: 10.43 | Y85: 36.47 | Z85: 90.84 | AA85: 488.8 | AB85: 181.4 | AC85: 16.79 | AD85: 29.01 | AE85: 172
A86: 08/31/23 | B86: 7316.7 | C86: 59.71 | D86: 758.5 | E86: 27.78 | F86: 102.96 | G86: 53.83 | H86: 11.66 | I86: 134.8 | J86: 60.16 | K86: 14.89 | L86: 26.22 | M86: 782.2 | N86: 405.8 | O86: 1900.8 | P86: 135.38 | Q86: 158.58 | R86: 173.9 | S86: 148.3 | T86: 58.07 | U86: 151.69 | V86: 98.64 | W86: 26.22 | X86: 10.36 | Y86: 36.61 | Z86: 91.1 | AA86: 494.2 | AB86: 181.2 | AC86: 17.15 | AD86: 28.91 | AE86: 172.35
A87: 08/30/23 | B87: 7321.35 | C87: 59.88 | D87: 766.5 | E87: 27.87 | F87: 103.48 | G87: 53.96 | H87: 11.7 | I87: 134.05 | J87: 59.64 | K87: 14.89 | L87: 26.37 | M87: 804 | N87: 410.1 | O87: 1931.4 | P87: 133.84 | Q87: 159.86 | R87: 174.74 | S87: 148.88 | T87: 57.94 | U87: 151.13 | V87: 99.2 | W87: 26.37 | X87: 10.37 | Y87: 36.65 | Z87: 91.28 | AA87: 498.3 | AB87: 194.3 | AC87: 17.17 | AD87: 28.9 | AE87: 171.35
A88: 08/29/23 | B88: 7322.45 | C88: 59.9 | D88: 764 | E88: 27.93 | F88: 103.78 | G88: 53.67 | H88: 11.7 | I88: 133.8 | J88: 59.37 | K88: 15.03 | L88: 26.38 | M88: 810 | N88: 409.15 | O88: 1937.8 | P88: 132.56 | Q88: 160.44 | R88: 176.4 | S88: 148.32 | T88: 57.86 | U88: 150.47 | V88: 99.67 | W88: 26.38 | X88: 10.37 | Y88: 36.62 | Z88: 91.2 | AA88: 499 | AB88: 195.65 | AC88: 17.22 | AD88: 29.05 | AE88: 168.85
A89: 08/28/23 | B89: 7261.5 | C89: 59.5 | D89: 754 | E89: 27.71 | F89: 103.84 | G89: 53.78 | H89: 11.57 | I89: 134.3 | J89: 58.98 | K89: 14.84 | L89: 26.25 | M89: 798.5 | N89: 405.2 | O89: 1917.6 | P89: 132.24 | Q89: 158.86 | R89: 176.12 | S89: 147.68 | T89: 57.89 | U89: 150.27 | V89: 99.28 | W89: 26.25 | X89: 10.31 | Y89: 36.19 | Z89: 90.34 | AA89: 494.4 | AB89: 194.4 | AC89: 16.93 | AD89: 28.66 | AE89: 165.6
A90: 08/25/23 | B90: 7196.84 | C90: 58.31 | D90: 742.5 | E90: 27.4 | F90: 102.34 | G90: 53.51 | H90: 11.47 | I90: 132.7 | J90: 58.04 | K90: 14.79 | L90: 25.92 | M90: 785.3 | N90: 401.45 | O90: 1883.2 | P90: 129.88 | Q90: 156.52 | R90: 174.04 | S90: 145.1 | T90: 57.32 | U90: 148.04 | V90: 98.71 | W90: 25.92 | X90: 10.26 | Y90: 35.71 | Z90: 89.12 | AA90: 487.6 | AB90: 193.2 | AC90: 16.72 | AD90: 28.42 | AE90: 162.55
A91: 08/24/23 | B91: 7210 | C91: 58.44 | D91: 736 | E91: 27.4 | F91: 101.54 | G91: 53.26 | H91: 11.49 | I91: 132.35 | J91: 58.05 | K91: 14.69 | L91: 25.94 | M91: 783.7 | N91: 400.35 | O91: 1878.4 | P91: 129.32 | Q91: 155.9 | R91: 173.98 | S91: 145.24 | T91: 57.17 | U91: 147.91 | V91: 98.13 | W91: 25.94 | X91: 10.24 | Y91: 35.78 | Z91: 89.08 | AA91: 490 | AB91: 191.8 | AC91: 16.56 | AD91: 28.48 | AE91: 163.6
A92: 08/23/23 | B92: 7224.07 | C92: 58.51 | D92: 742.5 | E92: 27.41 | F92: 101.48 | G92: 52.9 | H92: 11.42 | I92: 132.5 | J92: 58.71 | K92: 14.64 | L92: 25.85 | M92: 790.4 | N92: 401.3 | O92: 1902.8 | P92: 130.02 | Q92: 157.08 | R92: 174.58 | S92: 146.66 | T92: 56.97 | U92: 147.13 | V92: 98.97 | W92: 25.85 | X92: 10.27 | Y92: 36.1 | Z92: 89.5 | AA92: 499.1 | AB92: 191.7 | AC92: 16.72 | AD92: 28.58 | AE92: 165.5
A93: 08/22/23 | B93: 7223.07 | C93: 58.55 | D93: 745 | E93: 27.33 | F93: 101.4 | G93: 52.63 | H93: 11.46 | I93: 131.1 | J93: 59.29 | K93: 14.7 | L93: 25.6 | M93: 790.2 | N93: 396.3 | O93: 1885.2 | P93: 128.94 | Q93: 155.98 | R93: 176.56 | S93: 145.54 | T93: 57.98 | U93: 146.25 | V93: 99.61 | W93: 25.6 | X93: 10.19 | Y93: 35.99 | Z93: 89.46 | AA93: 501.4 | AB93: 191.2 | AC93: 16.71 | AD93: 28.65 | AE93: 164.25
A94: 08/21/23 | B94: 7165.07 | C94: 58.34 | D94: 743.5 | E94: 27.2 | F94: 100.88 | G94: 53.06 | H94: 11.36 | I94: 130.8 | J94: 59.05 | K94: 14.74 | L94: 25.45 | M94: 783.9 | N94: 398 | O94: 1874 | P94: 128.12 | Q94: 154.86 | R94: 174.94 | S94: 144.72 | T94: 57.59 | U94: 145.49 | V94: 98.65 | W94: 25.45 | X94: 10.22 | Y94: 35.57 | Z94: 88.52 | AA94: 498.5 | AB94: 192.5 | AC94: 16.65 | AD94: 28.46 | AE94: 162.05
A95: 08/18/23 | B95: 7092.72 | C95: 58.22 | D95: 733 | E95: 27.18 | F95: 101 | G95: 53.19 | H95: 11.33 | I95: 129.45 | J95: 59.25 | K95: 14.59 | L95: 25.31 | M95: 776.9 | N95: 398.2 | O95: 1862.6 | P95: 126.7 | Q95: 154.32 | R95: 173.5 | S95: 143.42 | T95: 57.01 | U95: 146.04 | V95: 98 | W95: 25.31 | X95: 10.26 | Y95: 35.76 | Z95: 89.06 | AA95: 492.6 | AB95: 192.55 | AC95: 16.35 | AD95: 28.47 | AE95: 160.25
A96: 08/17/23 | B96: 7183.5 | C96: 58.62 | D96: 739 | E96: 27.47 | F96: 101.58 | G96: 53.26 | H96: 11.37 | I96: 128.9 | J96: 59.88 | K96: 14.49 | L96: 25.48 | M96: 785.1 | N96: 402.65 | O96: 1875 | P96: 127.58 | Q96: 154.64 | R96: 173.8 | S96: 144.74 | T96: 56.76 | U96: 146.09 | V96: 97.67 | W96: 25.48 | X96: 10.22 | Y96: 35.73 | Z96: 89.02 | AA96: 498.3 | AB96: 192.4 | AC96: 16.47 | AD96: 28.52 | AE96: 158.1
A97: 08/16/23 | B97: 7241.1 | C97: 58.48 | D97: 753.5 | E97: 27.41 | F97: 102.4 | G97: 53.73 | H97: 11.43 | I97: 131 | J97: 60.92 | K97: 14.5 | L97: 25.41 | M97: 802.9 | N97: 407.75 | O97: 1927.2 | P97: 128.68 | Q97: 158.36 | R97: 174.9 | S97: 146.22 | T97: 56.32 | U97: 146.87 | V97: 96.33 | W97: 25.41 | X97: 10.22 | Y97: 36.97 | Z97: 90.9 | AA97: 506.7 | AB97: 195.8 | AC97: 16.66 | AD97: 28.56 | AE97: 160.95
... A99: 08/14/23 | B99: 7309.94 | C99: 59.68 | D99: 763.5 | E99: 27.96 | F99: 103.48 | G99: 54.91 | H99: 11.58 | I99: 133.3 | J99: 61.08 | K99: 14.55 | L99: 25.61 | M99: 816.2 | N99: 415.5 | O99: 1928.4 | P99: 130.64 | Q99: 160.04 | R99: 176.14 | S99: 147.66 | T99: 56.58 | U99: 147.96 | V99: 97.61 | W99: 25.61 | X99: 10.32 | Y99: 37.01 | Z99: 92.04 | AA99: 514 | AB99: 198.25 | AC99: 16.9 | AD99: 28.48 | AE99: 162.9
A100: 45238 | B100: 7317.76 | C100: 59.55 | D100: 770 | E100: 27.84 | F100: 103.6 | G100: 54.53 | H100: 11.55 | I100: 135.65 | J100: 61 | K100: 14.49 | L100: 25.54 | M100: 820.4 | N100: 412.3 | O100: 1924.8 | P100: 130.74 | Q100: 159.34 | R100: 175.3 | S100: 147.16 | T100: 57.17 | U100: 146.93 | V100: 97.07 | W100: 25.54 | X100: 10.26 | Y100: 36.86 | Z100: 91.5 | AA100: 517.1 | AB100: 196.4 | AC100: 16.85 | AD100: 28.31 | AE100: 162.9
A101: 45207 | B101: 7368.95 | C101: 60.3 | D101: 781.5 | E101: 28.17 | F101: 104.16 | G101: 55.06 | H101: 11.59 | I101: 136.55 | J101: 60.89 | K101: 14.64 | L101: 25.58 | M101: 834.7 | N101: 419.1 | O101: 1960.2 | P101: 132.04 | Q101: 160.52 | R101: 178.16 | S101: 148.44 | T101: 57.82 | U101: 148.31 | V101: 97.86 | W101: 25.58 | X101: 10.23 | Y101: 37.59 | Z101: 91.94 | AA101: 528.4 | AB101: 200.9 | AC101: 17.44 | AD101: 28.55 | AE101: 163.75
A102: 45177 | B102: 7317.38 | C102: 58.55 | D102: 761 | E102: 27.66 | F102: 103.02 | G102: 54.91 | H102: 11.5 | I102: 137.8 | J102: 60.91 | K102: 14.56 | L102: 25.45 | M102: 807 | N102: 406.8 | O102: 1899.4 | P102: 131.68 | Q102: 160.68 | R102: 175.52 | S102: 148.02 | T102: 57.04 | U102: 146.02 | V102: 96.59 | W102: 25.45 | X102: 10.17 | Y102: 37.51 | Z102: 92 | AA102: 517 | AB102: 196.8 | AC102: 17.39 | AD102: 28.52 | AE102: 161.65
...
